Workbook
Name Slicer_CITY: #N/A
Name Slicer_TYPE_CNTRL: #N/A
Name Slicer_TYPE_HOSP: #N/A

Sheet Append1
A1: FAC_NO | B1: FAC_NAME | C1: YEAR_QTR | D1: BEG_DATE | E1: END_DATE | F1: OP_STATUS | G1: COUNTY_NAME | H1: HSA | I1: HFPA | J1: TYPE_CNTRL | K1: TYPE_HOSP | L1: TEACH_RURL | M1: PHONE | N1: ADDRESS | O1: CITY | P1: ZIP_CODE | Q1: CEO | R1: LIC_BEDS | S1: AVL_BEDS | T1: STF_BEDS | U1: DIS_MCAR | V1: DIS_MCAR_MC | W1: DIS_MCAL | X1: DIS_MCAL_MC | Y1: DIS_CNTY | Z1: DIS_CNTY_MC | AA1: DIS_THRD | AB1: DIS_THRD_MC | AC1: DIS_INDGNT | AD1: DIS_OTH | AE1: DIS_TOT | AF1: DIS_LTC | AG1: DAY_MCAR | AH1: DAY_MCAR_MC | AI1: DAY_MCAL | AJ1: DAY_MCAL_MC | AK1: DAY_CNTY | AL1: DAY_CNTY_MC | AM1: DAY_THRD | AN1: DAY_THRD_MC | AO1: DAY_INDGNT | AP1: DAY_OTH | AQ1: DAY_TOT | AR1: DAY_LTC | AS1: Patient Days | AT1: VIS_MCAR | AU1: VIS_MCAR_MC | AV1: VIS_MCAL | AW1: VIS_MCAL_MC | AX1: VIS_CNTY | AY1: VIS_CNTY_MC | AZ1: VIS_THRD | BA1: VIS_THRD_MC | BB1: VIS_INDGNT | BC1: VIS_OTH | BD1: VIS_TOT | BE1: GRIP_MCAR | BF1: GRIP_MCAR_MC | BG1: GRIP_MCAL | BH1: GRIP_MCAL_MC | BI1: GRIP_CNTY | BJ1: GRIP_CNTY_MC | BK1: GRIP_THRD | BL1: GRIP_THRD_MC | BM1: GRIP_INDGNT | BN1: GRIP_OTH | BO1: GRIP_TOT | BP1: GROP_MCAR | BQ1: GROP_MCAR_MC | BR1: GROP_MCAL | BS1: GROP_MCAL_MC | BT1: GROP_CNTY | BU1: GROP_CNTY_MC | BV1: GROP_THRD | BW1: GROP_THRD_MC | BX1: GROP_INDGNT | BY1: GROP_OTH | BZ1: GROP_TOT | CA1: BAD_DEBT | CB1: CADJ_MCAR | CC1: CADJ_MCAR_MC | CD1: CADJ_MCAL | CE1: CADJ_MCAL_MC | CF1: DISP_855 | CG1: CADJ_CNTY | CH1: CADJ_CNTY_MC | CI1: CADJ_THRD | CJ1: CADJ_THRD_MC | CK1: CHAR_HB | CL1: CHAR_OTH | CM1: SUB_INDGNT | CN1: TCH_ALLOW | CO1: TCH_SUPP | CP1: DED_OTH | CQ1: DED_TOT | CR1: CAP_MCAR | CS1: CAP_MCAL | CT1: CAP_CNTY | CU1: CAP_THRD | CV1: CAP_TOT | CW1: NET_MCAR | CX1: NET_MCAR_MC | CY1: NET_MCAL | CZ1: NET_MCAL_MC | DA1: NET_CNTY | DB1: NET_CNTY_MC | DC1: NET_THRD | DD1: NET_THRD_MC | DE1: NET_INDGNT | DF1: NET_OTH | DG1: NET_TOT | DH1: OTH_OP_REV | DI1: TOT_OP_EXP | DJ1: PHY_COMP | DK1: NONOP_REV | DL1: DIS_PIPS | DM1: DAY_PIPS | DN1: EXP_PIPS | DO1: EXP_POPS | DP1: CAP_EXP | DQ1: FIX_ASSETS | DR1: DISP_TRNFR | DS1: DIS_TOT_CC | DT1: PAT_DAY_TOT_CC | DU1: TOT_OUT_VIS_CC | DV1: GROS_INPAT_REV_CC | DW1: GROS_OUTPAT_REV_CC | DX1: CONTR_ADJ_CC | DY1: OTHR_DEDUCT_CC | DZ1: CAP_PREM_REV_CC | EA1: NET_PAT_REV_CC | EB1: QA_FEES | EC1: QA_SUPPL_PAY | ED1: MNGD_CARE_QA_PAY
A2: 106150788 | B2: ADVENTIST HEALTH BAKERSFIELD | C2: 20174 | D2: 43009 | E2: 43100 | F2: Open | G2: Kern | H2: 9 | I2: 617 | J2: Non Profit Corp. | K2: Comparable | M2: 661-395-3000 | N2: 2615 CHESTER AVENUE | O2: BAKERSFIELD | P2: 93301 | Q2: SHARLET BRIGGS | R2: 254 | S2: 254 | T2: 185 | U2: 887 | V2: 765 | W2: 199 | X2: 1046 | Y2: 0 | Z2: 0 | AA2: 198 | AB2: 1170 | AC2: 0 | AD2: 70 | AE2: 4335 | AF2: 0 | AG2: 4003 | AH2: 3050 | AI2: 761 | AJ2: 3872 | AK2: 0 | AL2: 0 | AM2: 914 | AN2: 3747 | AO2: 0 | AP2: 267 | AQ2: 16614 | AR2: 0 | AS2: =Append1[[#This Row],[DAY_MCAR]]+Append1[[#This Row],[DAY_MCAR_MC]]+Append1[[#This Row],[DAY_MCAL]]+Append1[[#This Row],[DAY_MCAL_MC]]+Append1[[#This Row],[DAY_CNTY]]+Append1[[#This Row],[DAY_CNTY_MC]]+Append1[[#This Row],[DAY_THRD]]+Append1[[#This Row],[DAY_THRD_MC]]+Append1[[#This Row],[DAY_INDGNT]]+Append1[[#This Row],[DAY_OTH]]+Append1[[#This Row],[DAY_TOT]]+Append1[[#This Row],[DAY_LTC]] -> 33228 | AT2: 9776 | AU2: 3643 | AV2: 1306 | AW2: 11632 | AX2: 0 | AY2: 0 | AZ2: 2246 | BA2: 17962 | BB2: 0 | BC2: 2158 | BD2: 48723 | BE2: 71363118 | BF2: 60854375 | BG2: 14411053 | BH2: 57375871 | BI2: 0 | BJ2: 0 | BK2: 13990742 | BL2: 71149390 | BM2: 0 | BN2: 3307155 | BO2: 292451704 | BP2: 35210808 | BQ2: 28891174 | BR2: 5871109 | BS2: 39946555 | BT2: 0 | BU2: 0 | BV2: 13119193 | BW2: 58922262 | BX2: 0 | BY2: 4197975 | BZ2: 186159076 | CA2: 2272704 | CB2: 88051161 | CC2: 73421577 | CD2: 17883664 | CE2: 52659594 | CF2: 0 | CG2: 0 | CH2: 0 | CI2: 22267567 | CJ2: 93439065 | CK2: 0 | CL2: 3375466 | CM2: 0 | CN2: 0 | CO2: 0 | CP2: 6413785 | CQ2: 359784583 | CR2: 0 | CS2: 0 | CT2: 0 | CU2: 0 | CV2: 0 | CW2: 18033505 | CX2: 15996768 | CY2: 2236458 | CZ2: 44373536 | DA2: 0 | DB2: 0 | DC2: 4535581 | DD2: 32971878 | DE2: 0 | DF2: 678471 | DG2: 118826197 | DH2: 1181367 | DI2: 101757921 | DJ2: 0 | DK2: 837982 | DL2: 0 | DM2: 0 | DN2: 0 | DO2: 0 | DP2: 1494309 | DQ2: 137223161 | DR2: 0 | DS2: 0 | DT2: 0 | DU2: 0 | DV2: 0 | DW2: 0 | DX2: 0 | DY2: 0 | DZ2: 0 | EA2: 0 | EB2: 0 | EC2: 0 | ED2: 0
A3: 106171049 | B3: ADVENTIST HEALTH CLEARLAKE | C3: 20174 | D3: 43009 | E3: 43100 | F3: Open | G3: Lake | H3: 1 | I3: 115 | J3: Non Profit Corp. | K3: Comparable | L3: Rural | M3: 707-995-5820 | N3: 15630 18TH AVENUE | O3: CLEARLAKE | P3: 95422 | Q3: DAVID SANTOS | R3: 25 | S3: 25 | T3: 20 | U3: 195 | V3: 4 | W3: 17 | X3: 112 | Y3: 0 | Z3: 0 | AA3: 15 | AB3: 20 | AC3: 0 | AD3: 5 | AE3: 368 | AF3: 0 | AG3: 868 | AH3: 11 | AI3: 38 | AJ3: 447 | AK3: 0 | AL3: 0 | AM3: 63 | AN3: 62 | AO3: 0 | AP3: 8 | AQ3: 1497 | AR3: 0 | AS3: =Append1[[#This Row],[DAY_MCAR]]+Append1[[#This Row],[DAY_MCAR_MC]]+Append1[[#This Row],[DAY_MCAL]]+Append1[[#This Row],[DAY_MCAL_MC]]+Append1[[#This Row],[DAY_CNTY]]+Append1[[#This Row],[DAY_CNTY_MC]]+Append1[[#This Row],[DAY_THRD]]+Append1[[#This Row],[DAY_THRD_MC]]+Append1[[#This Row],[DAY_INDGNT]]+Append1[[#This Row],[DAY_OTH]]+Append1[[#This Row],[DAY_TOT]]+Append1[[#This Row],[DAY_LTC]] -> 2994 | AT3: 18850 | AU3: 236 | AV3: 6102 | AW3: 20417 | AX3: 0 | AY3: 0 | AZ3: 5841 | BA3: 2733 | BB3: 0 | BC3: 924 | BD3: 55103 | BE3: 9108603 | BF3: 401527 | BG3: 458182 | BH3: 5172868 | BI3: 0 | BJ3: 0 | BK3: 745016 | BL3: 835281 | BM3: 0 | BN3: 154674 | BO3: 16876151 | BP3: 16993939 | BQ3: 337344 | BR3: 3388635 | BS3: 15461946 | BT3: 0 | BU3: 0 | BV3: 1377158 | BW3: 5539582 | BX3: 0 | BY3: 1014594 | BZ3: 44113198 | CA3: 837648 | CB3: 14636391 | CC3: 579208 | CD3: 2402057 | CE3: 14238831 | CF3: 446943 | CG3: 0 | CH3: 0 | CI3: 343536 | CJ3: 4205989 | CK3: 0 | CL3: 2126830 | CM3: 0 | CN3: 0 | CO3: 0 | CP3: 1187033 | CQ3: 41004466 | CR3: 0 | CS3: 3354996 | CT3: 0 | CU3: 0 | CV3: 3354996 | CW3: 9842914 | CX3: 145722 | CY3: 1400652 | CZ3: 8890055 | DA3: 0 | DB3: 0 | DC3: 78938 | DD3: 3870071 | DE3: 0 | DF3: -888473 | DG3: 23339879 | DH3: 1269975 | DI3: 21613570 | DJ3: 0 | DK3: 21280 | DL3: 0 | DM3: 0 | DN3: 0 | DO3: 0 | DP3: 1224819 | DQ3: 31842591 | DR3: 0 | DS3: 0 | DT3: 0 | DU3: 0 | DV3: 0 | DW3: 0 | DX3: 0 | DY3: 0 | DZ3: 0 | EA3: 0 | EB3: 0 | EC3: 0 | ED3: 0
A4: 106040875 | B4: ADVENTIST HEALTH FEATHER RIVER | C4: 20174 | D4: 43009 | E4: 43100 | F4: Open | G4: Butte | H4: 1 | I4: 220 | J4: Church | K4: Comparable | M4: 530-877-9361 | N4: 5974 PENTZ ROAD | O4: PARADISE | P4: 95969 | Q4: MONTY KNITTEL | R4: 100 | S4: 100 | T4: 51 | U4: 617 | V4: 28 | W4: 47 | X4: 288 | Y4: 0 | Z4: 0 | AA4: 12 | AB4: 160 | AC4: 0 | AD4: 25 | AE4: 1177 | AF4: 0 | AG4: 2588 | AH4: 112 | AI4: 178 | AJ4: 880 | AK4: 0 | AL4: 0 | AM4: 27 | AN4: 455 | AO4: 0 | AP4: 61 | AQ4: 4301 | AR4: 0 | AS4: =Append1[[#This Row],[DAY_MCAR]]+Append1[[#This Row],[DAY_MCAR_MC]]+Append1[[#This Row],[DAY_MCAL]]+Append1[[#This Row],[DAY_MCAL_MC]]+Append1[[#This Row],[DAY_CNTY]]+Append1[[#This Row],[DAY_CNTY_MC]]+Append1[[#This Row],[DAY_THRD]]+Append1[[#This Row],[DAY_THRD_MC]]+Append1[[#This Row],[DAY_INDGNT]]+Append1[[#This Row],[DAY_OTH]]+Append1[[#This Row],[DAY_TOT]]+Append1[[#This Row],[DAY_LTC]] -> 8602 | AT4: 43568 | AU4: 1420 | AV4: 8061 | AW4: 27051 | AX4: 0 | AY4: 0 | AZ4: 1536 | BA4: 15412 | BB4: 0 | BC4: 1333 | BD4: 98381 | BE4: 67622023 | BF4: 2819880 | BG4: 4441575 | BH4: 20572218 | BI4: 0 | BJ4: 0 | BK4: 243598 | BL4: 14158556 | BM4: 0 | BN4: 1205706 | BO4: 111063556 | BP4: 93661341 | BQ4: 4226744 | BR4: 6930263 | BS4: 48359752 | BT4: 0 | BU4: 0 | BV4: 1337201 | BW4: 41649982 | BX4: 0 | BY4: 3131743 | BZ4: 199297026 | CA4: 1671586 | CB4: 140043971 | CC4: 6453618 | CD4: 9839806 | CE4: 47831823 | CF4: -55561 | CG4: 0 | CH4: 0 | CI4: 985992 | CJ4: 40331353 | CK4: 0 | CL4: 3665330 | CM4: 0 | CN4: 0 | CO4: 0 | CP4: 5969731 | CQ4: 256737649 | CR4: 0 | CS4: 0 | CT4: 0 | CU4: 0 | CV4: 0 | CW4: 19281147 | CX4: 484383 | CY4: 1321065 | CZ4: 20548740 | DA4: 0 | DB4: 0 | DC4: 43201 | DD4: 12695126 | DE4: 0 | DF4: -750729 | DG4: 53622933 | DH4: 4999673 | DI4: 52516178 | DJ4: 0 | DK4: 75243 | DL4: 0 | DM4: 0 | DN4: 0 | DO4: 0 | DP4: 600686 | DQ4: 55496213 | DR4: 0 | DS4: 0 | DT4: 0 | DU4: 0 | DV4: 0 | DW4: 0 | DX4: 0 | DY4: 0 | DZ4: 0 | EA4: 0 | EB4: 0 | EC4: 0 | ED4: 0
A5: 106190323 | B5: ADVENTIST HEALTH GLENDALE | C5: 20174 | D5: 43009 | E5: 43100 | F5: Open | G5: Los Angeles | H5: 11 | I5: 909 | J5: Church | K5: Comparable | M5: 818-409-8000 | N5: 1509 WILSON TERRACE | O5: GLENDALE | P5: 91206 | Q5: KEVIN ROBERTS | R5: 515 | S5: 462 | T5: 258 | U5: 2087 | V5: 416 | W5: 351 | X5: 857 | Y5: 0 | Z5: 0 | AA5: 72 | AB5: 1063 | AC5: 0 | AD5: 143 | AE5: 4989 | AF5: 0 | AG5: 11732 | AH5: 1666 | AI5: 2161 | AJ5: 3075 | AK5: 0 | AL5: 0 | AM5: 302 | AN5: 3898 | AO5: 0 | AP5: 513 | AQ5: 23347 | AR5: 0 | AS5: =Append1[[#This Row],[DAY_MCAR]]+Append1[[#This Row],[DAY_MCAR_MC]]+Append1[[#This Row],[DAY_MCAL]]+Append1[[#This Row],[DAY_MCAL_MC]]+Append1[[#This Row],[DAY_CNTY]]+Append1[[#This Row],[DAY_CNTY_MC]]+Append1[[#This Row],[DAY_THRD]]+Append1[[#This Row],[DAY_THRD_MC]]+Append1[[#This Row],[DAY_INDGNT]]+Append1[[#This Row],[DAY_OTH]]+Append1[[#This Row],[DAY_TOT]]+Append1[[#This Row],[DAY_LTC]] -> 46694 | AT5: 15308 | AU5: 1797 | AV5: 1257 | AW5: 9199 | AX5: 0 | AY5: 0 | AZ5: 3091 | BA5: 18033 | BB5: 0 | BC5: 1539 | BD5: 50224 | BE5: 192501958 | BF5: 37131928 | BG5: 31621277 | BH5: 71349447 | BI5: 0 | BJ5: 0 | BK5: 2188511 | BL5: 63651555 | BM5: 0 | BN5: 1816942 | BO5: 400261618 | BP5: 47868105 | BQ5: 12741879 | BR5: 6064401 | BS5: 45766658 | BT5: 0 | BU5: 0 | BV5: 2034365 | BW5: 50828732 | BX5: 0 | BY5: 13439358 | BZ5: 178743498 | CA5: 1353024 | CB5: 195736244 | CC5: 39647374 | CD5: 33934687 | CE5: 82184741 | CF5: 0 | CG5: 0 | CH5: 0 | CI5: 2138526 | CJ5: 52646291 | CK5: 0 | CL5: 2960341 | CM5: 0 | CN5: 0 | CO5: 0 | CP5: 13115679 | CQ5: 423716907 | CR5: 0 | CS5: 0 | CT5: 0 | CU5: 0 | CV5: 0 | CW5: 38804853 | CX5: 9013132 | CY5: 3705832 | CZ5: 34369691 | DA5: 0 | DB5: 0 | DC5: 1504194 | DD5: 59114403 | DE5: 0 | DF5: 8776104 | DG5: 155288209 | DH5: 2935654 | DI5: 112145651 | DJ5: 0 | DK5: 177146 | DL5: 0 | DM5: 0 | DN5: 0 | DO5: 0 | DP5: 2313385 | DQ5: 205118797 | DR5: 0 | DS5: 0 | DT5: 0 | DU5: 0 | DV5: 0 | DW5: 0 | DX5: 0 | DY5: 0 | DZ5: 0 | EA5: 0 | EB5: 0 | EC5: 0 | ED5: 0
A6: 106164029 | B6: ADVENTIST HEALTH HANFORD | C6: 20174 | D6: 43009 | E6: 43100 | F6: Open | G6: Kings | H6: 9 | I6: 615 | J6: Church | K6: Comparable | L6: Rural | M6: 559-582-9000 | N6: 115 MALL DRIVE | O6: HANFORD | P6: 93230 | Q6: WAYNE FERCH | R6: 230 | S6: 230 | T6: 122 | U6: 904 | V6: 153 | W6: 203 | X6: 882 | Y6: 0 | Z6: 0 | AA6: 151 | AB6: 377 | AC6: 2 | AD6: 85 | AE6: 2757 | AF6: 0 | AG6: 4584 | AH6: 678 | AI6: 780 | AJ6: 2940 | AK6: 0 | AL6: 0 | AM6: 447 | AN6: 1153 | AO6: 2 | AP6: 300 | AQ6: 10884 | AR6: 0 | AS6: =Append1[[#This Row],[DAY_MCAR]]+Append1[[#This Row],[DAY_MCAR_MC]]+Append1[[#This Row],[DAY_MCAL]]+Append1[[#This Row],[DAY_MCAL_MC]]+Append1[[#This Row],[DAY_CNTY]]+Append1[[#This Row],[DAY_CNTY_MC]]+Append1[[#This Row],[DAY_THRD]]+Append1[[#This Row],[DAY_THRD_MC]]+Append1[[#This Row],[DAY_INDGNT]]+Append1[[#This Row],[DAY_OTH]]+Append1[[#This Row],[DAY_TOT]]+Append1[[#This Row],[DAY_LTC]] -> 21768 | AT6: 13805 | AU6: 2032 | AV6: 3511 | AW6: 28941 | AX6: 0 | AY6: 0 | AZ6: 4537 | BA6: 15450 | BB6: 16 | BC6: 2842 | BD6: 71134 | BE6: 39810356 | BF6: 6458934 | BG6: 6161904 | BH6: 29503443 | BI6: 0 | BJ6: 0 | BK6: 4068300 | BL6: 11571065 | BM6: 25619 | BN6: 2453459 | BO6: 100053080 | BP6: 30739682 | BQ6: 6417684 | BR6: 8076606 | BS6: 68114587 | BT6: 0 | BU6: 0 | BV6: 10142611 | BW6: 33777390 | BX6: 49311 | BY6: 8213491 | BZ6: 165531362 | CA6: 7438010 | CB6: 64011090 | CC6: 10934754 | CD6: 13422518 | CE6: 55841578 | CF6: -500703 | CG6: 0 | CH6: 0 | CI6: 8436734 | CJ6: 20856183 | CK6: 0 | CL6: 2601162 | CM6: 0 | CN6: 0 | CO6: 0 | CP6: 10840275 | CQ6: 193881601 | CR6: 0 | CS6: 4002842 | CT6: 0 | CU6: 0 | CV6: 4002842 | CW6: 13973438 | CX6: 2152418 | CY6: 13576339 | CZ6: 19188628 | DA6: 0 | DB6: 0 | DC6: 2811770 | DD6: 23031345 | DE6: 3582 | DF6: 968163 | DG6: 75705683 | DH6: 659085 | DI6: 73036977 | DJ6: 0 | DK6: -2762995 | DL6: 0 | DM6: 0 | DN6: 0 | DO6: 0 | DP6: 2921916 | DQ6: 192203815 | DR6: 0 | DS6: 0 | DT6: 0 | DU6: 0 | DV6: 0 | DW6: 0 | DX6: 0 | DY6: 0 | DZ6: 0 | EA6: 0 | EB6: 0 | EC6: 0 | ED6: 0
A7: 106234038 | B7: ADVENTIST HEALTH HOWARD MEMORIAL | C7: 20174 | D7: 43009 | E7: 43100 | F7: Open | G7: Mendocino | H7: 1 | I7: 112 | J7: Non Profit Corp. | K7: Comparable | M7: 707-459-6801 | N7: 1 MARCELA DRIVE | O7: WILLITS | P7: 95490 | Q7: JASON WELLS | R7: 25 | S7: 25 | T7: 23 | U7: 248 | V7: 28 | W7: 16 | X7: 67 | Y7: 0 | Z7: 0 | AA7: 14 | AB7: 62 | AC7: 0 | AD7: 13 | AE7: 448 | AF7: 0 | AG7: 987 | AH7: 95 | AI7: 71 | AJ7: 259 | AK7: 0 | AL7: 0 | AM7: 63 | AN7: 197 | AO7: 0 | AP7: 38 | AQ7: 1710 | AR7: 0 | AS7: =Append1[[#This Row],[DAY_MCAR]]+Append1[[#This Row],[DAY_MCAR_MC]]+Append1[[#This Row],[DAY_MCAL]]+Append1[[#This Row],[DAY_MCAL_MC]]+Append1[[#This Row],[DAY_CNTY]]+Append1[[#This Row],[DAY_CNTY_MC]]+Append1[[#This Row],[DAY_THRD]]+Append1[[#This Row],[DAY_THRD_MC]]+Append1[[#This Row],[DAY_INDGNT]]+Append1[[#This Row],[DAY_OTH]]+Append1[[#This Row],[DAY_TOT]]+Append1[[#This Row],[DAY_LTC]] -> 3420 | AT7: 4770 | AU7: 429 | AV7: 178 | AW7: 3566 | AX7: 0 | AY7: 0 | AZ7: 310 | BA7: 3417 | BB7: 0 | BC7: 497 | BD7: 13167 | BE7: 13624482 | BF7: 1262162 | BG7: 883113 | BH7: 3944627 | BI7: 0 | BJ7: 0 | BK7: 225401 | BL7: 3873953 | BM7: 0 | BN7: 590569 | BO7: 24404307 | BP7: 6150104 | BQ7: 492621 | BR7: 549796 | BS7: 5486013 | BT7: 0 | BU7: 0 | BV7: 259371 | BW7: 4909870 | BX7: 0 | BY7: 817414 | BZ7: 18665189 | CA7: 909831 | CB7: 12424484 | CC7: 1220226 | CD7: 866212 | CE7: 9726042 | CF7: 0 | CG7: 0 | CH7: 0 | CI7: 297779 | CJ7: 3566538 | CK7: 0 | CL7: 934900 | CM7: 0 | CN7: 0 | CO7: 0 | CP7: 1065567 | CQ7: 31011579 | CR7: 0 | CS7: 1447009 | CT7: 0 | CU7: 0 | CV7: 1447009 | CW7: 7086385 | CX7: 477180 | CY7: 550284 | CZ7: 807498 | DA7: 0 | DB7: 0 | DC7: 71026 | DD7: 4517287 | DE7: 0 | DF7: -4734 | DG7: 13504926 | DH7: 568803 | DI7: 12823221 | DJ7: 0 | DK7: 415970 | DL7: 0 | DM7: 0 | DN7: 0 | DO7: 0 | DP7: 0 | DQ7: 61136675 | DR7: 0 | DS7: 0 | DT7: 0 | DU7: 0 | DV7: 0 | DW7: 0 | DX7: 0 | DY7: 0 | DZ7: 0 | EA7: 0 | EB7: 0 | EC7: 0 | ED7: 0
A8: 106390923 | B8: ADVENTIST HEALTH LODI MEMORIAL | C8: 20174 | D8: 43009 | E8: 43100 | F8: Open | G8: San Joaquin | H8: 6 | I8: 505 | J8: Non Profit Corp. | K8: Comparable | M8: 209-334-3411 | N8: 975 SOUTH FAIRMONT AVENUE | O8: LODI | P8: 95240 | Q8: DANIEL WOLCOTT | R8: 190 | S8: 190 | T8: 101 | U8: 1037 | V8: 206 | W8: 171 | X8: 539 | Y8: 0 | Z8: 0 | AA8: 42 | AB8: 353 | AC8: 3 | AD8: 38 | AE8: 2389 | AF8: 0 | AG8: 4146 | AH8: 896 | AI8: 603 | AJ8: 1933 | AK8: 0 | AL8: 0 | AM8: 161 | AN8: 1075 | AO8: 6 | AP8: 122 | AQ8: 8942 | AR8: 0 | AS8: =Append1[[#This Row],[DAY_MCAR]]+Append1[[#This Row],[DAY_MCAR_MC]]+Append1[[#This Row],[DAY_MCAL]]+Append1[[#This Row],[DAY_MCAL_MC]]+Append1[[#This Row],[DAY_CNTY]]+Append1[[#This Row],[DAY_CNTY_MC]]+Append1[[#This Row],[DAY_THRD]]+Append1[[#This Row],[DAY_THRD_MC]]+Append1[[#This Row],[DAY_INDGNT]]+Append1[[#This Row],[DAY_OTH]]+Append1[[#This Row],[DAY_TOT]]+Append1[[#This Row],[DAY_LTC]] -> 17884 | AT8: 20774 | AU8: 3361 | AV8: 3752 | AW8: 25150 | AX8: 0 | AY8: 0 | AZ8: 4710 | BA8: 14130 | BB8: 114 | BC8: 1374 | BD8: 73365 | BE8: 102878214 | BF8: 20949872 | BG8: 13411150 | BH8: 44450964 | BI8: 0 | BJ8: 0 | BK8: 5203980 | BL8: 30185051 | BM8: 231866 | BN8: 3019848 | BO8: 220330945 | BP8: 41343700 | BQ8: 8584396 | BR8: 7694154 | BS8: 46918591 | BT8: 0 | BU8: 0 | BV8: 6233552 | BW8: 33847035 | BX8: 153087 | BY8: 5039825 | BZ8: 149814340 | CA8: 5481324 | CB8: 146434384 | CC8: 25317532 | CD8: 15320317 | CE8: 57841858 | CF8: 0 | CG8: 0 | CH8: 0 | CI8: 7503312 | CJ8: 43101325 | CK8: 0 | CL8: 1984076 | CM8: 0 | CN8: 0 | CO8: 0 | CP8: 8775595 | CQ8: 311759723 | CR8: 0 | CS8: 518139 | CT8: 0 | CU8: 0 | CV8: 518139 | CW8: 13893937 | CX8: 2981248 | CY8: 10311096 | CZ8: 13034169 | DA8: 0 | DB8: 0 | DC8: 1703911 | DD8: 16794834 | DE8: 1051 | DF8: 183455 | DG8: 58903701 | DH8: 424765 | DI8: 54739688 | DJ8: 0 | DK8: -2987392 | DL8: 0 | DM8: 0 | DN8: 0 | DO8: 0 | DP8: 397676 | DQ8: 135770978 | DR8: 0 | DS8: 0 | DT8: 0 | DU8: 0 | DV8: 0 | DW8: 0 | DX8: 0 | DY8: 0 | DZ8: 0 | EA8: 0 | EB8: 0 | EC8: 0 | ED8: 0
A9: 106100797 | B9: ADVENTIST HEALTH REEDLEY | C9: 20174 | D9: 43009 | E9: 43100 | F9: Open | G9: Fresno | H9: 9 | I9: 607 | J9: District | K9: Comparable | L9: Rural | M9: 559-582-9000 | N9: 372 WEST CYPRESS AVENUE | O9: REEDLEY | P9: 93654 | Q9: WAYNE FERCH | R9: 49 | S9: 49 | T9: 15 | U9: 46 | V9: 7 | W9: 63 | X9: 260 | Y9: 0 | Z9: 0 | AA9: 1 | AB9: 62 | AC9: 0 | AD9: 8 | AE9: 447 | AF9: 0 | AG9: 204 | AH9: 23 | AI9: 142 | AJ9: 506 | AK9: 0 | AL9: 0 | AM9: 1 | AN9: 142 | AO9: 0 | AP9: 16 | AQ9: 1034 | AR9: 0 | AS9: =Append1[[#This Row],[DAY_MCAR]]+Append1[[#This Row],[DAY_MCAR_MC]]+Append1[[#This Row],[DAY_MCAL]]+Append1[[#This Row],[DAY_MCAL_MC]]+Append1[[#This Row],[DAY_CNTY]]+Append1[[#This Row],[DAY_CNTY_MC]]+Append1[[#This Row],[DAY_THRD]]+Append1[[#This Row],[DAY_THRD_MC]]+Append1[[#This Row],[DAY_INDGNT]]+Append1[[#This Row],[DAY_OTH]]+Append1[[#This Row],[DAY_TOT]]+Append1[[#This Row],[DAY_LTC]] -> 2068 | AT9: 19868 | AU9: 4040 | AV9: 14006 | AW9: 91659 | AX9: 0 | AY9: 0 | AZ9: 1400 | BA9: 19247 | BB9: 3539 | BC9: 2894 | BD9: 156653 | BE9: 1534647 | BF9: 153064 | BG9: 1222415 | BH9: 4398407 | BI9: 0 | BJ9: 0 | BK9: 8657 | BL9: 1167613 | BM9: 0 | BN9: 153470 | BO9: 8638273 | BP9: 8462781 | BQ9: 1546207 | BR9: 6062832 | BS9: 34988813 | BT9: 0 | BU9: 0 | BV9: 1106906 | BW9: 7743132 | BX9: 601050 | BY9: 2291282 | BZ9: 62803003 | CA9: 921316 | CB9: 4920055 | CC9: 1004291 | CD9: 11817451 | CE9: 4016484 | CF9: -2355983 | CG9: 0 | CH9: 0 | CI9: -5629 | CJ9: 3433285 | CK9: 0 | CL9: 1388496 | CM9: 0 | CN9: 0 | CO9: 0 | CP9: 2688990 | CQ9: 27828756 | CR9: 0 | CS9: 0 | CT9: 0 | CU9: 155462 | CV9: 155462 | CW9: 4067413 | CX9: 392927 | CY9: 1996570 | CZ9: 32852847 | DA9: 0 | DB9: 0 | DC9: 280959 | DD9: 3743004 | DE9: 101784 | DF9: 332478 | DG9: 43767982 | DH9: 986527 | DI9: 36432935 | DJ9: 0 | DK9: 314387 | DL9: 0 | DM9: 0 | DN9: 0 | DO9: 0 | DP9: 359595 | DQ9: 21735162 | DR9: 0 | DS9: 0 | DT9: 0 | DU9: 0 | DV9: 0 | DW9: 0 | DX9: 0 | DY9: 0 | DZ9: 0 | EA9: 0 | EB9: 0 | EC9: 0 | ED9: 0
A10: 106560525 | B10: ADVENTIST HEALTH SIMI VALLEY | C10: 20174 | D10: 43009 | E10: 43100 | F10: Open | G10: Ventura | H10: 10 | I10: 813 | J10: Church | K10: Comparable | M10: 805-955-6000 | N10: 2975 SYCAMORE DRIVE | O10: SIMI VALLEY | P10: 93065 | Q10: JENNIFER SWENSON | R10: 144 | S10: 85 | T10: 74 | U10: 666 | V10: 176 | W10: 45 | X10: 244 | Y10: 0 | Z10: 0 | AA10: 31 | AB10: 520 | AC10: 0 | AD10: 42 | AE10: 1724 | AF10: 0 | AG10: 2845 | AH10: 674 | AI10: 152 | AJ10: 842 | AK10: 0 | AL10: 0 | AM10: 99 | AN10: 1734 | AO10: 0 | AP10: 124 | AQ10: 6470 | AR10: 0 | AS10: =Append1[[#This Row],[DAY_MCAR]]+Append1[[#This Row],[DAY_MCAR_MC]]+Append1[[#This Row],[DAY_MCAL]]+Append1[[#This Row],[DAY_MCAL_MC]]+Append1[[#This Row],[DAY_CNTY]]+Append1[[#This Row],[DAY_CNTY_MC]]+Append1[[#This Row],[DAY_THRD]]+Append1[[#This Row],[DAY_THRD_MC]]+Append1[[#This Row],[DAY_INDGNT]]+Append1[[#This Row],[DAY_OTH]]+Append1[[#This Row],[DAY_TOT]]+Append1[[#This Row],[DAY_LTC]] -> 12940 | AT10: 5838 | AU10: 760 | AV10: 427 | AW10: 3512 | AX10: 0 | AY10: 0 | AZ10: 2692 | BA10: 10032 | BB10: 0 | BC10: 749 | BD10: 24010 | BE10: 45164367 | BF10: 11654673 | BG10: 2967630 | BH10: 11686044 | BI10: 0 | BJ10: 0 | BK10: 1159441 | BL10: 26084904 | BM10: 0 | BN10: 334815 | BO10: 99051874 | BP10: 13924573 | BQ10: 5501097 | BR10: 2732854 | BS10: 13091342 | BT10: 0 | BU10: 0 | BV10: 993153 | BW10: 29694081 | BX10: 0 | BY10: 2452187 | BZ10: 68389287 | CA10: 1105470 | CB10: 46959193 | CC10: 11970047 | CD10: 4101945 | CE10: 24678197 | CF10: 0 | CG10: 0 | CH10: 0 | CI10: 883661 | CJ10: 35142772 | CK10: 0 | CL10: 1671997 | CM10: 0 | CN10: 0 | CO10: 0 | CP10: 5792787 | CQ10: 132306069 | CR10: 0 | CS10: 0 | CT10: 0 | CU10: 0 | CV10: 0 | CW10: 10097716 | CX10: 5107520 | CY10: 1587979 | CZ10: 144809 | DA10: 0 | DB10: 0 | DC10: 830838 | DD10: 19243516 | DE10: 0 | DF10: -1877286 | DG10: 35135092 | DH10: 804786 | DI10: 38280988 | DJ10: 0 | DK10: 154685 | DL10: 0 | DM10: 0 | DN10: 0 | DO10: 0 | DP10: 3107043 | DQ10: 132761888 | DR10: 0 | DS10: 0 | DT10: 0 | DU10: 0 | DV10: 0 | DW10: 0 | DX10: 0 | DY10: 0 | DZ10: 0 | EA10: 0 | EB10: 0 | EC10: 0 | ED10: 0
A11: 106554011 | B11: ADVENTIST HEALTH SONORA - GREENLEY | C11: 20174 | D11: 43009 | E11: 43100 | F11: Open | G11: Tuolumne | H11: 6 | I11: 513 | J11: Church | K11: Comparable | L11: Rural | M11: 209-536-5000 | N11: 1000 GREENLEY ROAD | O11: SONORA | P11: 95370 | Q11: MICHELLE FUENTES | R11: 152 | S11: 152 | T11: 117 | U11: 623 | V11: 29 | W11: 26 | X11: 185 | Y11: 0 | Z11: 0 | AA11: 40 | AB11: 194 | AC11: 1 | AD11: 18 | AE11: 1116 | AF11: 25 | AG11: 2616 | AH11: 127 | AI11: 5983 | AJ11: 699 | AK11: 0 | AL11: 0 | AM11: 261 | AN11: 696 | AO11: 1 | AP11: 20 | AQ11: 10403 | AR11: 6072 | AS11: =Append1[[#This Row],[DAY_MCAR]]+Append1[[#This Row],[DAY_MCAR_MC]]+Append1[[#This Row],[DAY_MCAL]]+Append1[[#This Row],[DAY_MCAL_MC]]+Append1[[#This Row],[DAY_CNTY]]+Append1[[#This Row],[DAY_CNTY_MC]]+Append1[[#This Row],[DAY_THRD]]+Append1[[#This Row],[DAY_THRD_MC]]+Append1[[#This Row],[DAY_INDGNT]]+Append1[[#This Row],[DAY_OTH]]+Append1[[#This Row],[DAY_TOT]]+Append1[[#This Row],[DAY_LTC]] -> 26878 | AT11: 49228 | AU11: 2050 | AV11: 4302 | AW11: 16992 | AX11: 0 | AY11: 0 | AZ11: 6985 | BA11: 26407 | BB11: 23 | BC11: 2145 | BD11: 108132 | BE11: 46072278 | BF11: 2231309 | BG11: 4112991 | BH11: 12297683 | BI11: 0 | BJ11: 0 | BK11: 3986169 | BL11: 14788267 | BM11: 121652 | BN11: 251794 | BO11: 83862143 | BP11: 79005882 | BQ11: 3821085 | BR11: 4203507 | BS11: 22905408 | BT11: 0 | BU11: 0 | BV11: 8098811 | BW11: 36762240 | BX11: 69341 | BY11: 2046027 | BZ11: 156912301 | CA11: 1945017 | CB11: 104128444 | CC11: 4368103 | CD11: 1339449 | CE11: 29517278 | CF11: 0 | CG11: 0 | CH11: 0 | CI11: 6005578 | CJ11: 26144096 | CK11: 0 | CL11: 2029165 | CM11: 0 | CN11: 0 | CO11: 0 | CP11: 4478410 | CQ11: 179955540 | CR11: 0 | CS11: 0 | CT11: 0 | CU11: 0 | CV11: 0 | CW11: 23231828 | CX11: 1265696 | CY11: 7949997 | CZ11: 3577857 | DA11: 0 | DB11: 0 | DC11: 3407562 | DD11: 20970954 | DE11: 2930 | DF11: 412080 | DG11: 60818904 | DH11: 2051373 | DI11: 54717601 | DJ11: 0 | DK11: 215023 | DL11: 0 | DM11: 0 | DN11: 0 | DO11: 0 | DP11: 10085538 | DQ11: 84544054 | DR11: 0 | DS11: 0 | DT11: 0 | DU11: 0 | DV11: 0 | DW11: 0 | DX11: 0 | DY11: 0 | DZ11: 0 | EA11: 0 | EB11: 0 | EC11: 0 | ED11: 0
A12: 106281078 | B12: ADVENTIST HEALTH ST. HELENA | C12: 20174 | D12: 43009 | E12: 43100 | F12: Open | G12: Napa | H12: 3 | I12: 407 | J12: Non Profit Corp. | K12: Comparable | M12: 707-963-3611 | N12: 10 WOODLAND ROAD | O12: ST. HELENA | P12: 94574 | Q12: STEVEN HERBER | R12: 151 | S12: 151 | T12: 71 | U12: 616 | V12: 50 | W12: 154 | X12: 140 | Y12: 0 | Z12: 0 | AA12: 28 | AB12: 209 | AC12: 0 | AD12: 1 | AE12: 1198 | AF12: 0 | AG12: 3048 | AH12: 286 | AI12: 1230 | AJ12: 585 | AK12: 0 | AL12: 0 | AM12: 254 | AN12: 754 | AO12: 0 | AP12: 2 | AQ12: 6159 | AR12: 0 | AS12: =Append1[[#This Row],[DAY_MCAR]]+Append1[[#This Row],[DAY_MCAR_MC]]+Append1[[#This Row],[DAY_MCAL]]+Append1[[#This Row],[DAY_MCAL_MC]]+Append1[[#This Row],[DAY_CNTY]]+Append1[[#This Row],[DAY_CNTY_MC]]+Append1[[#This Row],[DAY_THRD]]+Append1[[#This Row],[DAY_THRD_MC]]+Append1[[#This Row],[DAY_INDGNT]]+Append1[[#This Row],[DAY_OTH]]+Append1[[#This Row],[DAY_TOT]]+Append1[[#This Row],[DAY_LTC]] -> 12318 | AT12: 7053 | AU12: 144 | AV12: 164 | AW12: 1424 | AX12: 0 | AY12: 0 | AZ12: 1172 | BA12: 3884 | BB12: 0 | BC12: 184 | BD12: 14025 | BE12: 89882183 | BF12: 11649080 | BG12: 11066552 | BH12: 8790749 | BI12: 0 | BJ12: 0 | BK12: 2258544 | BL12: 27807792 | BM12: 0 | BN12: 701441 | BO12: 152156341 | BP12: 40500514 | BQ12: 806876 | BR12: 2246735 | BS12: 10626816 | BT12: 0 | BU12: 0 | BV12: 2579497 | BW12: 21449495 | BX12: 0 | BY12: 1444802 | BZ12: 79654735 | CA12: 457013 | CB12: 107395777 | CC12: 6341487 | CD12: 11842404 | CE12: 10222215 | CF12: -1401796 | CG12: 0 | CH12: 0 | CI12: 2531638 | CJ12: 29385050 | CK12: 0 | CL12: 3485791 | CM12: 0 | CN12: 0 | CO12: 0 | CP12: 3190774 | CQ12: 173450353 | CR12: 0 | CS12: 6371417 | CT12: 0 | CU12: 0 | CV12: 6371417 | CW12: 22004887 | CX12: 6021987 | CY12: 2019820 | CZ12: 16764255 | DA12: 0 | DB12: 0 | DC12: 1974095 | DD12: 18097014 | DE12: 0 | DF12: -2149918 | DG12: 64732140 | DH12: 1680512 | DI12: 58996235 | DJ12: 0 | DK12: 26582 | DL12: 0 | DM12: 0 | DN12: 0 | DO12: 0 | DP12: 1005365 | DQ12: 87857460 | DR12: 0 | DS12: 0 | DT12: 0 | DU12: 0 | DV12: 0 | DW12: 0 | DX12: 0 | DY12: 0 | DZ12: 0 | EA12: 0 | EB12: 0 | EC12: 0 | ED12: 0
A13: 106150808 | B13: ADVENTIST HEALTH TEHACHAPI VALLEY | C13: 20174 | D13: 43009 | E13: 43100 | F13: Open | G13: Kern | H13: 9 | I13: 623 | J13: District | K13: Comparable | L13: Rural | M13: 661-823-3000 | N13: 115 WEST E STREET | O13: TEHACHAPI | P13: 93561 | Q13: DAVID EASTMAN | R13: 28 | S13: 24 | T13: 14 | U13: 8 | V13: 2 | W13: 0 | X13: 6 | Y13: 0 | Z13: 0 | AA13: 3 | AB13: 1 | AC13: 0 | AD13: 0 | AE13: 20 | AF13: 0 | AG13: 22 | AH13: 5 | AI13: 0 | AJ13: 12 | AK13: 0 | AL13: 0 | AM13: 4 | AN13: 3 | AO13: 0 | AP13: 0 | AQ13: 46 | AR13: 0 | AS13: =Append1[[#This Row],[DAY_MCAR]]+Append1[[#This Row],[DAY_MCAR_MC]]+Append1[[#This Row],[DAY_MCAL]]+Append1[[#This Row],[DAY_MCAL_MC]]+Append1[[#This Row],[DAY_CNTY]]+Append1[[#This Row],[DAY_CNTY_MC]]+Append1[[#This Row],[DAY_THRD]]+Append1[[#This Row],[DAY_THRD_MC]]+Append1[[#This Row],[DAY_INDGNT]]+Append1[[#This Row],[DAY_OTH]]+Append1[[#This Row],[DAY_TOT]]+Append1[[#This Row],[DAY_LTC]] -> 92 | AT13: 1335 | AU13: 345 | AV13: 744 | AW13: 5326 | AX13: 0 | AY13: 0 | AZ13: 315 | BA13: 1088 | BB13: 0 | BC13: 451 | BD13: 9604 | BE13: 55216 | BF13: 14370 | BG13: 0 | BH13: 44017 | BI13: 0 | BJ13: 0 | BK13: 34464 | BL13: 5998 | BM13: 0 | BN13: 0 | BO13: 154065 | BP13: 3106973 | BQ13: 1746755 | BR13: 1004832 | BS13: 6237997 | BT13: 0 | BU13: 0 | BV13: 332867 | BW13: 3941182 | BX13: 0 | BY13: 525815 | BZ13: 16896421 | CA13: 273100 | CB13: 2860557 | CC13: 1045127 | CD13: -1612495 | CE13: 2777723 | CF13: -34449 | CG13: 0 | CH13: 0 | CI13: 282618 | CJ13: 2517688 | CK13: 0 | CL13: 2072977 | CM13: 0 | CN13: 0 | CO13: 0 | CP13: 918204 | CQ13: 11101050 | CR13: 0 | CS13: 3150 | CT13: 0 | CU13: 0 | CV13: 3150 | CW13: 432655 | CX13: 715998 | CY13: 2617326 | CZ13: 3541890 | DA13: 0 | DB13: 0 | DC13: 678715 | DD13: 835490 | DE13: 0 | DF13: -2869488 | DG13: 5952586 | DH13: 11332 | DI13: 6521466 | DJ13: 0 | DK13: 15897 | DL13: 0 | DM13: 0 | DN13: 0 | DO13: 0 | DP13: 2135395 | DQ13: 30661791 | DR13: 0 | DS13: 0 | DT13: 0 | DU13: 0 | DV13: 0 | DW13: 0 | DX13: 0 | DY13: 0 | DZ13: 0 | EA13: 0 | EB13: 0 | EC13: 0 | ED13: 0
A14: 106231396 | B14: ADVENTIST HEALTH UKIAH VALLEY | C14: 20174 | D14: 43009 | E14: 43100 | F14: Open | G14: Mendocino | H14: 1 | I14: 113 | J14: Church | K14: Comparable | L14: Rural | M14: 707-462-3111 | N14: 275 HOSPITAL DRIVE | O14: UKIAH | P14: 95482 | Q14: GWEN MATTHEWS | R14: 67 | S14: 50 | T14: 35 | U14: 348 | V14: 37 | W14: 58 | X14: 304 | Y14: 0 | Z14: 0 | AA14: 19 | AB14: 129 | AC14: 0 | AD14: 16 | AE14: 911 | AF14: 0 | AG14: 1316 | AH14: 118 | AI14: 158 | AJ14: 829 | AK14: 0 | AL14: 0 | AM14: 56 | AN14: 353 | AO14: 0 | AP14: 68 | AQ14: 2898 | AR14: 0 | AS14: =Append1[[#This Row],[DAY_MCAR]]+Append1[[#This Row],[DAY_MCAR_MC]]+Append1[[#This Row],[DAY_MCAL]]+Append1[[#This Row],[DAY_MCAL_MC]]+Append1[[#This Row],[DAY_CNTY]]+Append1[[#This Row],[DAY_CNTY_MC]]+Append1[[#This Row],[DAY_THRD]]+Append1[[#This Row],[DAY_THRD_MC]]+Append1[[#This Row],[DAY_INDGNT]]+Append1[[#This Row],[DAY_OTH]]+Append1[[#This Row],[DAY_TOT]]+Append1[[#This Row],[DAY_LTC]] -> 5796 | AT14: 21711 | AU14: 1449 | AV14: 1049 | AW14: 17324 | AX14: 0 | AY14: 0 | AZ14: 2019 | BA14: 15719 | BB14: 0 | BC14: 1378 | BD14: 60649 | BE14: 15410138 | BF14: 1499435 | BG14: 2306900 | BH14: 10625189 | BI14: 0 | BJ14: 0 | BK14: 100781 | BL14: 6371852 | BM14: 0 | BN14: 736840 | BO14: 37051135 | BP14: 32970299 | BQ14: 2031697 | BR14: 1963927 | BS14: 22342177 | BT14: 0 | BU14: 0 | BV14: 660530 | BW14: 21087607 | BX14: 0 | BY14: 1915538 | BZ14: 82971775 | CA14: 188206 | CB14: 36415592 | CC14: 2838752 | CD14: 2864613 | CE14: 27272966 | CF14: 283801 | CG14: 0 | CH14: 0 | CI14: 750639 | CJ14: 13521334 | CK14: 0 | CL14: 1986874 | CM14: 0 | CN14: 0 | CO14: 0 | CP14: 3411326 | CQ14: 89534103 | CR14: 0 | CS14: 11097862 | CT14: 0 | CU14: 0 | CV14: 11097862 | CW14: 10903672 | CX14: 623279 | CY14: 1430645 | CZ14: 16300955 | DA14: 0 | DB14: 0 | DC14: -46157 | DD14: 12623436 | DE14: 0 | DF14: -249161 | DG14: 41586669 | DH14: 634904 | DI14: 34384258 | DJ14: 0 | DK14: 20659 | DL14: 0 | DM14: 0 | DN14: 0 | DO14: 0 | DP14: 8989499 | DQ14: 59408731 | DR14: 0 | DS14: 0 | DT14: 0 | DU14: 0 | DV14: 0 | DW14: 0 | DX14: 0 | DY14: 0 | DZ14: 0 | EA14: 0 | EB14: 0 | EC14: 0 | ED14: 0
A15: 106481015 | B15: ADVENTIST HEALTH VALLEJO | C15: 20174 | D15: 43009 | E15: 43100 | F15: Open | G15: Solano | H15: 3 | I15: 409 | J15: Non Profit Corp. | K15: Comparable | M15: 707-963-3611 | N15: 525 OREGON STREET | O15: VALLEJO | P15: 94590 | Q15: DR STEVE HERBER | R15: 61 | S15: 61 | T15: 60 | U15: 139 | V15: 33 | W15: 121 | X15: 0 | Y15: 0 | Z15: 0 | AA15: 35 | AB15: 288 | AC15: 0 | AD15: 0 | AE15: 616 | AF15: 0 | AG15: 1649 | AH15: 236 | AI15: 1083 | AJ15: 0 | AK15: 0 | AL15: 0 | AM15: 230 | AN15: 1911 | AO15: 0 | AP15: 0 | AQ15: 5109 | AR15: 0 | AS15: =Append1[[#This Row],[DAY_MCAR]]+Append1[[#This Row],[DAY_MCAR_MC]]+Append1[[#This Row],[DAY_MCAL]]+Append1[[#This Row],[DAY_MCAL_MC]]+Append1[[#This Row],[DAY_CNTY]]+Append1[[#This Row],[DAY_CNTY_MC]]+Append1[[#This Row],[DAY_THRD]]+Append1[[#This Row],[DAY_THRD_MC]]+Append1[[#This Row],[DAY_INDGNT]]+Append1[[#This Row],[DAY_OTH]]+Append1[[#This Row],[DAY_TOT]]+Append1[[#This Row],[DAY_LTC]] -> 10218 | AT15: 623 | AU15: 0 | AV15: 0 | AW15: 0 | AX15: 0 | AY15: 0 | AZ15: 262 | BA15: 250 | BB15: 0 | BC15: 21 | BD15: 1156 | BE15: 6168864 | BF15: 810033 | BG15: 3940124 | BH15: 0 | BI15: 0 | BJ15: 0 | BK15: 1142163 | BL15: 7885259 | BM15: 0 | BN15: 0 | BO15: 19946443 | BP15: 1608737 | BQ15: 0 | BR15: 0 | BS15: 0 | BT15: 0 | BU15: 0 | BV15: 364980 | BW15: 753854 | BX15: 0 | BY15: 66647 | BZ15: 2794218 | CA15: 128776 | CB15: 8286635 | CC15: -435751 | CD15: 3680709 | CE15: 60282 | CF15: 0 | CG15: 0 | CH15: 0 | CI15: 414993 | CJ15: -164201 | CK15: 0 | CL15: 794142 | CM15: 0 | CN15: 0 | CO15: 0 | CP15: 273009 | CQ15: 13038594 | CR15: 0 | CS15: 0 | CT15: 0 | CU15: 0 | CV15: 0 | CW15: -739353 | CX15: 1206644 | CY15: -395823 | CZ15: -57926 | DA15: 0 | DB15: 0 | DC15: 1130076 | DD15: 8303649 | DE15: 0 | DF15: 254800 | DG15: 9702067 | DH15: 61263 | DI15: 7967569 | DJ15: 0 | DK15: 0 | DL15: 0 | DM15: 0 | DN15: 0 | DO15: 0 | DP15: 0 | DQ15: 0 | DR15: 0 | DS15: 0 | DT15: 0 | DU15: 0 | DV15: 0 | DW15: 0 | DX15: 0 | DY15: 0 | DZ15: 0 | EA15: 0 | EB15: 0 | EC15: 0 | ED15: 0
A16: 106190878 | B16: ADVENTIST HEALTH WHITE MEMORIAL | C16: 20174 | D16: 43009 | E16: 43100 | F16: Open | G16: Los Angeles | H16: 11 | I16: 925 | J16: Non Profit Corp. | K16: Comparable | L16: Teaching | M16: 323-268-5000 | N16: 1720 CESAR E. CHAVEZ AVENUE | O16: LOS ANGELES | P16: 90033 | Q16: JOHN RAFFOUL | R16: 353 | S16: 353 | T16: 236 | U16: 869 | V16: 592 | W16: 1126 | X16: 1566 | Y16: 0 | Z16: 0 | AA16: 44 | AB16: 667 | AC16: 0 | AD16: 107 | AE16: 4971 | AF16: 0 | AG16: 5023 | AH16: 2234 | AI16: 5386 | AJ16: 5794 | AK16: 0 | AL16: 0 | AM16: 223 | AN16: 2097 | AO16: 0 | AP16: 250 | AQ16: 21007 | AR16: 0 | AS16: =Append1[[#This Row],[DAY_MCAR]]+Append1[[#This Row],[DAY_MCAR_MC]]+Append1[[#This Row],[DAY_MCAL]]+Append1[[#This Row],[DAY_MCAL_MC]]+Append1[[#This Row],[DAY_CNTY]]+Append1[[#This Row],[DAY_CNTY_MC]]+Append1[[#This Row],[DAY_THRD]]+Append1[[#This Row],[DAY_THRD_MC]]+Append1[[#This Row],[DAY_INDGNT]]+Append1[[#This Row],[DAY_OTH]]+Append1[[#This Row],[DAY_TOT]]+Append1[[#This Row],[DAY_LTC]] -> 42014 | AT16: 7438 | AU16: 4328 | AV16: 4815 | AW16: 13112 | AX16: 0 | AY16: 0 | AZ16: 2053 | BA16: 7399 | BB16: 0 | BC16: 1864 | BD16: 41009 | BE16: 88121172 | BF16: 58435399 | BG16: 79955471 | BH16: 129948050 | BI16: 0 | BJ16: 0 | BK16: 1066617 | BL16: 36939547 | BM16: 0 | BN16: 3090726 | BO16: 397556982 | BP16: 24015834 | BQ16: 24935181 | BR16: 19094785 | BS16: 70043899 | BT16: 0 | BU16: 0 | BV16: 859141 | BW16: 28025221 | BX16: 0 | BY16: 4060707 | BZ16: 171034768 | CA16: -666694 | CB16: 84309825 | CC16: 69622282 | CD16: 79101294 | CE16: 116193469 | CF16: -4200677 | CG16: 0 | CH16: 0 | CI16: 5339405 | CJ16: 46543730 | CK16: 0 | CL16: 5564474 | CM16: 0 | CN16: 0 | CO16: 0 | CP16: 18845425 | CQ16: 420652533 | CR16: 50128 | CS16: 8638600 | CT16: 0 | CU16: 0 | CV16: 8688728 | CW16: 22076225 | CX16: 12917099 | CY16: 19522606 | CZ16: 97132405 | DA16: 0 | DB16: 0 | DC16: -3565764 | DD16: 10056348 | DE16: 0 | DF16: -1510974 | DG16: 156627945 | DH16: 6778659 | DI16: 104937463 | DJ16: 0 | DK16: 1786754 | DL16: 0 | DM16: 0 | DN16: 0 | DO16: 0 | DP16: 5116278 | DQ16: 158766508 | DR16: 0 | DS16: 0 | DT16: 0 | DU16: 0 | DV16: 0 | DW16: 0 | DX16: 0 | DY16: 0 | DZ16: 0 | EA16: 0 | EB16: 0 | EC16: 0 | ED16: 0
A17: 106301098 | B17: AHMC ANAHEIM REGIONAL MEDICAL CENTER | C17: 20174 | D17: 43009 | E17: 43100 | F17: Open | G17: Orange | H17: 13 | I17: 1012 | J17: Non Profit Other | K17: Comparable | M17: 714-999-5102 | N17: 1111 WEST LA PALMA AVENUE | O17: ANAHEIM | P17: 92801 | Q17: RICHARD CASTRO | R17: 223 | S17: 223 | T17: 223 | U17: 640 | V17: 446 | W17: 326 | X17: 795 | Y17: 0 | Z17: 0 | AA17: 20 | AB17: 366 | AC17: 0 | AD17: 67 | AE17: 2660 | AF17: 0 | AG17: 3123 | AH17: 2396 | AI17: 1473 | AJ17: 2975 | AK17: 0 | AL17: 0 | AM17: 148 | AN17: 925 | AO17: 0 | AP17: 174 | AQ17: 11214 | AR17: 0 | AS17: =Append1[[#This Row],[DAY_MCAR]]+Append1[[#This Row],[DAY_MCAR_MC]]+Append1[[#This Row],[DAY_MCAL]]+Append1[[#This Row],[DAY_MCAL_MC]]+Append1[[#This Row],[DAY_CNTY]]+Append1[[#This Row],[DAY_CNTY_MC]]+Append1[[#This Row],[DAY_THRD]]+Append1[[#This Row],[DAY_THRD_MC]]+Append1[[#This Row],[DAY_INDGNT]]+Append1[[#This Row],[DAY_OTH]]+Append1[[#This Row],[DAY_TOT]]+Append1[[#This Row],[DAY_LTC]] -> 22428 | AT17: 2139 | AU17: 1621 | AV17: 1820 | AW17: 5104 | AX17: 0 | AY17: 0 | AZ17: 428 | BA17: 2819 | BB17: 0 | BC17: 954 | BD17: 14885 | BE17: 59135165 | BF17: 49109383 | BG17: 21560270 | BH17: 58378353 | BI17: 0 | BJ17: 0 | BK17: 2564368 | BL17: 29332726 | BM17: 0 | BN17: 4009529 | BO17: 224089794 | BP17: 15836944 | BQ17: 23725753 | BR17: 7331467 | BS17: 31314960 | BT17: 0 | BU17: 0 | BV17: 2808802 | BW17: 21535734 | BX17: 0 | BY17: 2694065 | BZ17: 105247725 | CA17: 1816523 | CB17: 65267134 | CC17: 63124742 | CD17: 26159547 | CE17: 51231602 | CF17: -787500 | CG17: 0 | CH17: 0 | CI17: 4283934 | CJ17: 42137072 | CK17: 0 | CL17: 0 | CM17: 0 | CN17: 0 | CO17: 0 | CP17: 2080689 | CQ17: 255313743 | CR17: 0 | CS17: 0 | CT17: 0 | CU17: 0 | CV17: 0 | CW17: 9704975 | CX17: 9710394 | CY17: 3519690 | CZ17: 38461712 | DA17: 0 | DB17: 0 | DC17: 1089235 | DD17: 8731388 | DE17: 0 | DF17: 2806382 | DG17: 74023776 | DH17: 141495 | DI17: 51206733 | DJ17: 0 | DK17: 0 | DL17: 0 | DM17: 0 | DN17: 0 | DO17: 0 | DP17: 77388 | DQ17: 5762288 | DR17: 0 | DS17: 0 | DT17: 0 | DU17: 0 | DV17: 0 | DW17: 0 | DX17: 0 | DY17: 0 | DZ17: 0 | EA17: 0 | EB17: 0 | EC17: 0 | ED17: 0
A18: 106010735 | B18: ALAMEDA HOSPITAL | C18: 20174 | D18: 43009 | E18: 43100 | F18: Open | G18: Alameda | H18: 5 | I18: 417 | J18: Non Profit Corp. | K18: Comparable | M18: 510-437-4800 | N18: 2070 CLINTON AVENUE | O18: ALAMEDA | P18: 94501 | Q18: DELVECCHIO FINLEY | R18: 251 | S18: 217 | T18: 217 | U18: 326 | V18: 46 | W18: 55 | X18: 126 | Y18: 0 | Z18: 14 | AA18: 11 | AB18: 74 | AC18: 0 | AD18: 12 | AE18: 664 | AF18: 0 | AG18: 4571 | AH18: 407 | AI18: 11758 | AJ18: 941 | AK18: 0 | AL18: 54 | AM18: 36 | AN18: 984 | AO18: 0 | AP18: 226 | AQ18: 18977 | AR18: 0 | AS18: =Append1[[#This Row],[DAY_MCAR]]+Append1[[#This Row],[DAY_MCAR_MC]]+Append1[[#This Row],[DAY_MCAL]]+Append1[[#This Row],[DAY_MCAL_MC]]+Append1[[#This Row],[DAY_CNTY]]+Append1[[#This Row],[DAY_CNTY_MC]]+Append1[[#This Row],[DAY_THRD]]+Append1[[#This Row],[DAY_THRD_MC]]+Append1[[#This Row],[DAY_INDGNT]]+Append1[[#This Row],[DAY_OTH]]+Append1[[#This Row],[DAY_TOT]]+Append1[[#This Row],[DAY_LTC]] -> 37954 | AT18: 1954 | AU18: 285 | AV18: 213 | AW18: 1888 | AX18: 0 | AY18: 83 | AZ18: 338 | BA18: 1376 | BB18: 0 | BC18: 1493 | BD18: 7630 | BE18: 28843292 | BF18: 3165124 | BG18: 17792965 | BH18: 9924367 | BI18: 0 | BJ18: 1794348 | BK18: 542200 | BL18: 4352546 | BM18: 0 | BN18: 862512 | BO18: 67277354 | BP18: 11691106 | BQ18: 1873071 | BR18: 1252337 | BS18: 9712552 | BT18: 0 | BU18: 1182425 | BV18: 1080459 | BW18: 5931698 | BX18: 0 | BY18: 1587646 | BZ18: 34311294 | CA18: 1838844 | CB18: 33564138 | CC18: 4004000 | CD18: 16357960 | CE18: 16606086 | CF18: -632250 | CG18: 0 | CH18: 2976773 | CI18: 1357584 | CJ18: 7262406 | CK18: 0 | CL18: 488807 | CM18: 0 | CN18: 0 | CO18: 0 | CP18: 0 | CQ18: 83824348 | CR18: 0 | CS18: 0 | CT18: 415784 | CU18: 0 | CV18: 415784 | CW18: 6970260 | CX18: 1034195 | CY18: 3319592 | CZ18: 3030833 | DA18: 0 | DB18: 415784 | DC18: 265075 | DD18: 3021838 | DE18: 0 | DF18: 122507 | DG18: 18180084 | DH18: 384106 | DI18: 26859719 | DJ18: 0 | DK18: 1923909 | DL18: 0 | DM18: 0 | DN18: 0 | DO18: 0 | DP18: 0 | DQ18: 7328505 | DR18: 0 | DS18: 0 | DT18: 0 | DU18: 0 | DV18: 0 | DW18: 0 | DX18: 0 | DY18: 0 | DZ18: 0 | EA18: 0 | EB18: 0 | EC18: 0 | ED18: 0
A19: 106190017 | B19: ALHAMBRA HOSPITAL MEDICAL CENTER | C19: 20174 | D19: 43009 | E19: 43100 | F19: Open | G19: Los Angeles | H19: 11 | I19: 913 | J19: Investor - Ptnr. | K19: Comparable | M19: 626-570-1606 | N19: 100 SOUTH RAYMOND AVENUE | O19: ALHAMBRA | P19: 91801 | Q19: IRIS LAI | R19: 144 | S19: 144 | T19: 144 | U19: 414 | V19: 303 | W19: 36 | X19: 515 | Y19: 0 | Z19: 0 | AA19: 7 | AB19: 115 | AC19: 0 | AD19: 14 | AE19: 1404 | AF19: 4 | AG19: 2796 | AH19: 1296 | AI19: 633 | AJ19: 3471 | AK19: 0 | AL19: 0 | AM19: 19 | AN19: 463 | AO19: 0 | AP19: 62 | AQ19: 8740 | AR19: 2364 | AS19: =Append1[[#This Row],[DAY_MCAR]]+Append1[[#This Row],[DAY_MCAR_MC]]+Append1[[#This Row],[DAY_MCAL]]+Append1[[#This Row],[DAY_MCAL_MC]]+Append1[[#This Row],[DAY_CNTY]]+Append1[[#This Row],[DAY_CNTY_MC]]+Append1[[#This Row],[DAY_THRD]]+Append1[[#This Row],[DAY_THRD_MC]]+Append1[[#This Row],[DAY_INDGNT]]+Append1[[#This Row],[DAY_OTH]]+Append1[[#This Row],[DAY_TOT]]+Append1[[#This Row],[DAY_LTC]] -> 19844 | AT19: 989 | AU19: 610 | AV19: 455 | AW19: 2616 | AX19: 0 | AY19: 0 | AZ19: 37 | BA19: 857 | BB19: 0 | BC19: 1267 | BD19: 6831 | BE19: 37307669 | BF19: 19579324 | BG19: 6031893 | BH19: 36021848 | BI19: 0 | BJ19: 0 | BK19: 347976 | BL19: 6458953 | BM19: 0 | BN19: 652463 | BO19: 106400126 | BP19: 6753359 | BQ19: 3947532 | BR19: 1750230 | BS19: 10282475 | BT19: 0 | BU19: 0 | BV19: 329342 | BW19: 5429667 | BX19: 0 | BY19: 1927527 | BZ19: 30420132 | CA19: 480556 | CB19: 33327323 | CC19: 25832341 | CD19: 7110843 | CE19: 46969132 | CF19: 0 | CG19: 0 | CH19: 0 | CI19: 417266 | CJ19: 9966576 | CK19: 0 | CL19: 0 | CM19: 0 | CN19: 0 | CO19: 0 | CP19: 1730417 | CQ19: 125834454 | CR19: 29000055 | CS19: 4813475 | CT19: 0 | CU19: 0 | CV19: 33813530 | CW19: 10733705 | CX19: 26694570 | CY19: 671280 | CZ19: 4148665 | DA19: 0 | DB19: 0 | DC19: 260052 | DD19: 1922044 | DE19: 0 | DF19: 369018 | DG19: 44799334 | DH19: 205527 | DI19: 46112648 | DJ19: 0 | DK19: 123810 | DL19: 0 | DM19: 0 | DN19: 0 | DO19: 0 | DP19: 282613 | DQ19: 7102067 | DR19: 0 | DS19: 0 | DT19: 0 | DU19: 0 | DV19: 0 | DW19: 0 | DX19: 0 | DY19: 0 | DZ19: 0 | EA19: 0 | EB19: 0 | EC19: 0 | ED19: 0
A20: 106010739 | B20: ALTA BATES SUMMIT MEDICAL CENTER - ALTA BATES CAMPUS | C20: 20174 | D20: 43009 | E20: 43100 | F20: Open | G20: Alameda | H20: 5 | I20: 415 | J20: Non Profit Corp. | K20: Comparable | M20: 510-204-4444 | N20: 2450 ASHBY AVENUE | O20: BERKELEY | P20: 94705 | Q20: CHARLES PROSPER | R20: 402 | S20: 402 | T20: 241 | U20: 819 | V20: 221 | W20: 601 | X20: 886 | Y20: 0 | Z20: 0 | AA20: 148 | AB20: 1276 | AC20: 33 | AD20: 13 | AE20: 3997 | AF20: 0 | AG20: 4317 | AH20: 1041 | AI20: 2552 | AJ20: 2913 | AK20: 0 | AL20: 0 | AM20: 1941 | AN20: 5568 | AO20: 135 | AP20: 41 | AQ20: 18508 | AR20: 0 | AS20: =Append1[[#This Row],[DAY_MCAR]]+Append1[[#This Row],[DAY_MCAR_MC]]+Append1[[#This Row],[DAY_MCAL]]+Append1[[#This Row],[DAY_MCAL_MC]]+Append1[[#This Row],[DAY_CNTY]]+Append1[[#This Row],[DAY_CNTY_MC]]+Append1[[#This Row],[DAY_THRD]]+Append1[[#This Row],[DAY_THRD_MC]]+Append1[[#This Row],[DAY_INDGNT]]+Append1[[#This Row],[DAY_OTH]]+Append1[[#This Row],[DAY_TOT]]+Append1[[#This Row],[DAY_LTC]] -> 37016 | AT20: 7599 | AU20: 1908 | AV20: 785 | AW20: 4659 | AX20: 4 | AY20: 0 | AZ20: 250 | BA20: 7742 | BB20: 0 | BC20: 430 | BD20: 23377 | BE20: 63490666 | BF20: 16027829 | BG20: 30587318 | BH20: 47512590 | BI20: 0 | BJ20: 0 | BK20: 24936629 | BL20: 75176664 | BM20: 1837771 | BN20: 558968 | BO20: 260128435 | BP20: 65254269 | BQ20: 18517938 | BR20: 6287452 | BS20: 34692343 | BT20: 61726 | BU20: 0 | BV20: 3251142 | BW20: 67706590 | BX20: 0 | BY20: 2176393 | BZ20: 197947853 | CA20: 3594071 | CB20: 99706178 | CC20: 29308392 | CD20: -66674262 | CE20: 65166599 | CF20: 0 | CG20: 0 | CH20: 0 | CI20: 20810253 | CJ20: 63775552 | CK20: 0 | CL20: 1724634 | CM20: 0 | CN20: 0 | CO20: 0 | CP20: 0 | CQ20: 217411417 | CR20: 813202 | CS20: 0 | CT20: 0 | CU20: 5481154 | CV20: 6294356 | CW20: 29038757 | CX20: 6050577 | CY20: 103549032 | CZ20: 17038334 | DA20: 61726 | DB20: 0 | DC20: 7377518 | DD20: 83730146 | DE20: 113137 | DF20: 0 | DG20: 246959227 | DH20: 2116654 | DI20: 214145635 | DJ20: 0 | DK20: 2373188 | DL20: 0 | DM20: 0 | DN20: 0 | DO20: 0 | DP20: 5731783 | DQ20: 86423187 | DR20: 0 | DS20: 0 | DT20: 0 | DU20: 0 | DV20: 0 | DW20: 0 | DX20: 0 | DY20: 0 | DZ20: 0 | EA20: 0 | EB20: 0 | EC20: 0 | ED20: 0
A21: 106010937 | B21: ALTA BATES SUMMIT MEDICAL CENTER - SUMMIT HAWTHORNE | C21: 20174 | D21: 43009 | E21: 43100 | F21: Open | G21: Alameda | H21: 5 | I21: 417 | J21: Non Profit Corp. | K21: Comparable | M21: 510-655-4000 | N21: 350 HAWTHORNE AVENUE | O21: OAKLAND | P21: 94609 | Q21: CHARLES PROSPER | R21: 354 | S21: 354 | T21: 236 | U21: 1505 | V21: 303 | W21: 225 | X21: 641 | Y21: 0 | Z21: 0 | AA21: 68 | AB21: 475 | AC21: 23 | AD21: 7 | AE21: 3247 | AF21: 0 | AG21: 8509 | AH21: 1807 | AI21: 1734 | AJ21: 3501 | AK21: 0 | AL21: 0 | AM21: 235 | AN21: 2543 | AO21: 75 | AP21: 21 | AQ21: 18425 | AR21: 0 | AS21: =Append1[[#This Row],[DAY_MCAR]]+Append1[[#This Row],[DAY_MCAR_MC]]+Append1[[#This Row],[DAY_MCAL]]+Append1[[#This Row],[DAY_MCAL_MC]]+Append1[[#This Row],[DAY_CNTY]]+Append1[[#This Row],[DAY_CNTY_MC]]+Append1[[#This Row],[DAY_THRD]]+Append1[[#This Row],[DAY_THRD_MC]]+Append1[[#This Row],[DAY_INDGNT]]+Append1[[#This Row],[DAY_OTH]]+Append1[[#This Row],[DAY_TOT]]+Append1[[#This Row],[DAY_LTC]] -> 36850 | AT21: 3261 | AU21: 520 | AV21: 415 | AW21: 4334 | AX21: 0 | AY21: 0 | AZ21: 160 | BA21: 2639 | BB21: 359 | BC21: 282 | BD21: 11970 | BE21: 134971546 | BF21: 29500534 | BG21: 22945388 | BH21: 56108542 | BI21: 0 | BJ21: 0 | BK21: 4477033 | BL21: 46356064 | BM21: 1487244 | BN21: 422893 | BO21: 296269244 | BP21: 39217657 | BQ21: 10089165 | BR21: 6944543 | BS21: 28958085 | BT21: 0 | BU21: 0 | BV21: 1790880 | BW21: 42947602 | BX21: 1953472 | BY21: 1553229 | BZ21: 133454633 | CA21: 3555394 | CB21: 142757295 | CC21: 32555467 | CD21: 18060999 | CE21: 65253776 | CF21: 0 | CG21: 0 | CH21: 0 | CI21: 3594648 | CJ21: 28071121 | CK21: 0 | CL21: 3440716 | CM21: 0 | CN21: 0 | CO21: 0 | CP21: 0 | CQ21: 297289416 | CR21: 0 | CS21: 0 | CT21: 0 | CU21: 0 | CV21: 0 | CW21: 31431908 | CX21: 7034232 | CY21: 11828932 | CZ21: 19812851 | DA21: 0 | DB21: 0 | DC21: 2673265 | DD21: 56212557 | DE21: 3440716 | DF21: 0 | DG21: 132434461 | DH21: -7134396 | DI21: 272388995 | DJ21: 0 | DK21: 5715504 | DL21: 0 | DM21: 0 | DN21: 0 | DO21: 0 | DP21: 13405541 | DQ21: 510783761 | DR21: 0 | DS21: 0 | DT21: 0 | DU21: 0 | DV21: 0 | DW21: 0 | DX21: 0 | DY21: 0 | DZ21: 0 | EA21: 0 | EB21: 0 | EC21: 0 | ED21: 0
A22: 106370749 | B22: ALVARADO PARKWAY INSTITUTE BHS | C22: 20174 | D22: 43009 | E22: 43100 | F22: Open | G22: San Diego | H22: 14 | I22: 1422 | J22: Investor - Corp. | K22: Comparable | M22: 619-465-4411 | N22: 7050 PARKWAY DRIVE | O22: LA MESA | P22: 91942 | Q22: PATRICK ZIEMER | R22: 66 | S22: 66 | T22: 66 | U22: 197 | V22: 52 | W22: 71 | X22: 0 | Y22: 0 | Z22: 0 | AA22: 0 | AB22: 221 | AC22: 0 | AD22: 4 | AE22: 545 | AF22: 0 | AG22: 2541 | AH22: 638 | AI22: 857 | AJ22: 0 | AK22: 0 | AL22: 0 | AM22: 0 | AN22: 1319 | AO22: 0 | AP22: 14 | AQ22: 5369 | AR22: 0 | AS22: =Append1[[#This Row],[DAY_MCAR]]+Append1[[#This Row],[DAY_MCAR_MC]]+Append1[[#This Row],[DAY_MCAL]]+Append1[[#This Row],[DAY_MCAL_MC]]+Append1[[#This Row],[DAY_CNTY]]+Append1[[#This Row],[DAY_CNTY_MC]]+Append1[[#This Row],[DAY_THRD]]+Append1[[#This Row],[DAY_THRD_MC]]+Append1[[#This Row],[DAY_INDGNT]]+Append1[[#This Row],[DAY_OTH]]+Append1[[#This Row],[DAY_TOT]]+Append1[[#This Row],[DAY_LTC]] -> 10738 | AT22: 28822 | AU22: 2371 | AV22: 0 | AW22: 0 | AX22: 0 | AY22: 0 | AZ22: 0 | BA22: 2755 | BB22: 0 | BC22: 112 | BD22: 34060 | BE22: 7585000 | BF22: 1057500 | BG22: 2140000 | BH22: 0 | BI22: 0 | BJ22: 0 | BK22: 0 | BL22: 2625000 | BM22: 0 | BN22: 32500 | BO22: 13440000 | BP22: 6386582 | BQ22: 345629 | BR22: 0 | BS22: 0 | BT22: 0 | BU22: 0 | BV22: 0 | BW22: 231772 | BX22: 0 | BY22: 24544 | BZ22: 6988527 | CA22: 423210 | CB22: 8835457 | CC22: 0 | CD22: 1788907 | CE22: 0 | CF22: 0 | CG22: 0 | CH22: 0 | CI22: 0 | CJ22: 3001677 | CK22: 0 | CL22: 0 | CM22: 0 | CN22: 0 | CO22: 0 | CP22: 0 | CQ22: 14049251 | CR22: 0 | CS22: 0 | CT22: 0 | CU22: 0 | CV22: 0 | CW22: 4712916 | CX22: 1403128 | CY22: 351093 | CZ22: 0 | DA22: 0 | DB22: 0 | DC22: 0 | DD22: -144905 | DE22: 0 | DF22: 57044 | DG22: 6379276 | DH22: 0 | DI22: 6654605 | DJ22: 0 | DK22: 0 | DL22: 0 | DM22: 0 | DN22: 0 | DO22: 0 | DP22: 132724 | DQ22: 1743168 | DR22: 0 | DS22: 0 | DT22: 0 | DU22: 0 | DV22: 0 | DW22: 0 | DX22: 0 | DY22: 0 | DZ22: 0 | EA22: 0 | EB22: 0 | EC22: 0 | ED22: 0
A23: 106194010 | B23: AMERICAN RECOVERY CENTER | C23: 20174 | D23: 43009 | E23: 43100 | F23: Open | G23: Los Angeles | H23: 11 | I23: 917 | J23: Non Profit Corp. | K23: Comparable | M23: 909-865-2336 | N23: 2180 VALLEY BOULEVARD | O23: POMONA | P23: 91768 | Q23: SHIRLEY SUMMERS | R23: 173 | S23: 173 | T23: 173 | U23: 0 | V23: 0 | W23: 0 | X23: 0 | Y23: 486 | Z23: 0 | AA23: 0 | AB23: 0 | AC23: 0 | AD23: 0 | AE23: 486 | AF23: 0 | AG23: 0 | AH23: 0 | AI23: 0 | AJ23: 0 | AK23: 9031 | AL23: 0 | AM23: 0 | AN23: 0 | AO23: 0 | AP23: 0 | AQ23: 9031 | AR23: 0 | AS23: =Append1[[#This Row],[DAY_MCAR]]+Append1[[#This Row],[DAY_MCAR_MC]]+Append1[[#This Row],[DAY_MCAL]]+Append1[[#This Row],[DAY_MCAL_MC]]+Append1[[#This Row],[DAY_CNTY]]+Append1[[#This Row],[DAY_CNTY_MC]]+Append1[[#This Row],[DAY_THRD]]+Append1[[#This Row],[DAY_THRD_MC]]+Append1[[#This Row],[DAY_INDGNT]]+Append1[[#This Row],[DAY_OTH]]+Append1[[#This Row],[DAY_TOT]]+Append1[[#This Row],[DAY_LTC]] -> 18062 | AT23: 0 | AU23: 0 | AV23: 0 | AW23: 0 | AX23: 1536 | AY23: 0 | AZ23: 0 | BA23: 0 | BB23: 0 | BC23: 0 | BD23: 1536 | BE23: 0 | BF23: 0 | BG23: 0 | BH23: 0 | BI23: 1984847 | BJ23: 0 | BK23: 0 | BL23: 0 | BM23: 0 | BN23: 0 | BO23: 1984847 | BP23: 0 | BQ23: 0 | BR23: 0 | BS23: 0 | BT23: 101864 | BU23: 0 | BV23: 0 | BW23: 0 | BX23: 0 | BY23: 0 | BZ23: 101864 | CA23: 0 | CB23: 0 | CC23: 0 | CD23: 0 | CE23: 0 | CF23: 0 | CG23: 0 | CH23: 0 | CI23: 0 | CJ23: 0 | CK23: 0 | CL23: 0 | CM23: 0 | CN23: 0 | CO23: 0 | CP23: 0 | CQ23: 0 | CR23: 0 | CS23: 0 | CT23: 0 | CU23: 0 | CV23: 0 | CW23: 0 | CX23: 0 | CY23: 0 | CZ23: 0 | DA23: 2086711 | DB23: 0 | DC23: 0 | DD23: 0 | DE23: 0 | DF23: 0 | DG23: 2086711 | DH23: 0 | DI23: 1480214 | DJ23: 58213 | DK23: 0 | DL23: 0 | DM23: 0 | DN23: 0 | DO23: 0 | DP23: 0 | DQ23: 2473214 | DR23: 0 | DS23: 0 | DT23: 0 | DU23: 0 | DV23: 0 | DW23: 0 | DX23: 0 | DY23: 0 | DZ23: 0 | EA23: 0 | EB23: 0 | EC23: 0 | ED23: 0
A24: 106301188 | B24: ANAHEIM GLOBAL MEDICAL CENTER | C24: 20174 | D24: 43009 | E24: 43100 | F24: Open | G24: Orange | H24: 13 | I24: 1012 | J24: Investor - Corp. | K24: Comparable | M24: 714-835-3555 | N24: 1025 SOUTH ANAHEIM BOULEVARD. | O24: ANAHEIM | P24: 92805 | Q24: SUZANNE RICHARDS | R24: 188 | S24: 188 | T24: 188 | U24: 138 | V24: 140 | W24: 389 | X24: 174 | Y24: 0 | Z24: 0 | AA24: 160 | AB24: 71 | AC24: 0 | AD24: 42 | AE24: 1114 | AF24: 0 | AG24: 1946 | AH24: 1110 | AI24: 4910 | AJ24: 656 | AK24: 0 | AL24: 0 | AM24: 1514 | AN24: 306 | AO24: 0 | AP24: 186 | AQ24: 10628 | AR24: 0 | AS24: =Append1[[#This Row],[DAY_MCAR]]+Append1[[#This Row],[DAY_MCAR_MC]]+Append1[[#This Row],[DAY_MCAL]]+Append1[[#This Row],[DAY_MCAL_MC]]+Append1[[#This Row],[DAY_CNTY]]+Append1[[#This Row],[DAY_CNTY_MC]]+Append1[[#This Row],[DAY_THRD]]+Append1[[#This Row],[DAY_THRD_MC]]+Append1[[#This Row],[DAY_INDGNT]]+Append1[[#This Row],[DAY_OTH]]+Append1[[#This Row],[DAY_TOT]]+Append1[[#This Row],[DAY_LTC]] -> 21256 | AT24: 609 | AU24: 333 | AV24: 1414 | AW24: 2171 | AX24: 0 | AY24: 0 | AZ24: 960 | BA24: 696 | BB24: 0 | BC24: 629 | BD24: 6812 | BE24: 8886142 | BF24: 10584440 | BG24: 14705310 | BH24: 6376520 | BI24: 0 | BJ24: 0 | BK24: 6184738 | BL24: 3365679 | BM24: 0 | BN24: 1257958 | BO24: 51360787 | BP24: 2527605 | BQ24: 1927798 | BR24: 2732778 | BS24: 5763099 | BT24: 0 | BU24: 0 | BV24: 2872557 | BW24: 2966150 | BX24: 0 | BY24: 1859919 | BZ24: 20649906 | CA24: 2109698 | CB24: 7772904 | CC24: 10691781 | CD24: 13457979 | CE24: 11140687 | CF24: -1799999 | CG24: 0 | CH24: 0 | CI24: 3498060 | CJ24: 2967824 | CK24: 0 | CL24: 0 | CM24: 0 | CN24: 0 | CO24: 0 | CP24: 970320 | CQ24: 50809254 | CR24: 0 | CS24: 0 | CT24: 0 | CU24: 0 | CV24: 0 | CW24: 3640843 | CX24: 1820457 | CY24: 5780108 | CZ24: 998931 | DA24: 0 | DB24: 0 | DC24: 5559235 | DD24: 3364005 | DE24: 0 | DF24: 37860 | DG24: 21201439 | DH24: 47331 | DI24: 18837326 | DJ24: 348579 | DK24: 0 | DL24: 0 | DM24: 0 | DN24: 0 | DO24: 0 | DP24: 293139 | DQ24: 2077974 | DR24: 0 | DS24: 0 | DT24: 0 | DU24: 0 | DV24: 0 | DW24: 0 | DX24: 0 | DY24: 0 | DZ24: 0 | EA24: 0 | EB24: 0 | EC24: 0 | ED24: 0
A25: 106190034 | B25: ANTELOPE VALLEY HOSPITAL | C25: 20174 | D25: 43009 | E25: 43100 | F25: Open | G25: Los Angeles | H25: 11 | I25: 901 | J25: District | K25: Comparable | M25: 661-949-5000 | N25: 1600 WEST AVENUE J | O25: LANCASTER | P25: 93534 | Q25: MICHAEL WALL | R25: 420 | S25: 393 | T25: 249 | U25: 890 | V25: 753 | W25: 730 | X25: 1545 | Y25: 0 | Z25: 0 | AA25: 1179 | AB25: 0 | AC25: 95 | AD25: 35 | AE25: 5227 | AF25: 0 | AG25: 4337 | AH25: 3041 | AI25: 3328 | AJ25: 5407 | AK25: 0 | AL25: 0 | AM25: 3876 | AN25: 0 | AO25: 426 | AP25: 225 | AQ25: 20640 | AR25: 0 | AS25: =Append1[[#This Row],[DAY_MCAR]]+Append1[[#This Row],[DAY_MCAR_MC]]+Append1[[#This Row],[DAY_MCAL]]+Append1[[#This Row],[DAY_MCAL_MC]]+Append1[[#This Row],[DAY_CNTY]]+Append1[[#This Row],[DAY_CNTY_MC]]+Append1[[#This Row],[DAY_THRD]]+Append1[[#This Row],[DAY_THRD_MC]]+Append1[[#This Row],[DAY_INDGNT]]+Append1[[#This Row],[DAY_OTH]]+Append1[[#This Row],[DAY_TOT]]+Append1[[#This Row],[DAY_LTC]] -> 41280 | AT25: 5113 | AU25: 2685 | AV25: 4419 | AW25: 15520 | AX25: 0 | AY25: 0 | AZ25: 7679 | BA25: 0 | BB25: 6834 | BC25: 525 | BD25: 42775 | BE25: 67535230 | BF25: 54642418 | BG25: 41511791 | BH25: 79950347 | BI25: 0 | BJ25: 0 | BK25: 64827058 | BL25: 0 | BM25: 7302602 | BN25: 2928162 | BO25: 318697608 | BP25: 17448903 | BQ25: 23297978 | BR25: 13266843 | BS25: 52424146 | BT25: 0 | BU25: 0 | BV25: 37047079 | BW25: 0 | BX25: 6634072 | BY25: 2634081 | BZ25: 152753102 | CA25: 1682613 | CB25: 68466449 | CC25: 60006389 | CD25: 45441331 | CE25: 117938456 | CF25: -2368418 | CG25: 0 | CH25: 0 | CI25: 79242093 | CJ25: 0 | CK25: 0 | CL25: 2724440 | CM25: 0 | CN25: 0 | CO25: 0 | CP25: 591315 | CQ25: 373724668 | CR25: 0 | CS25: 0 | CT25: 0 | CU25: 0 | CV25: 0 | CW25: 16517684 | CX25: 17934007 | CY25: 11705720 | CZ25: 14436037 | DA25: 0 | DB25: 0 | DC25: 22632044 | DD25: 0 | DE25: 9529621 | DF25: 4970929 | DG25: 97726042 | DH25: 13542251 | DI25: 100721722 | DJ25: 0 | DK25: 110582 | DL25: 0 | DM25: 0 | DN25: 0 | DO25: 0 | DP25: 23463896 | DQ25: 177846360 | DR25: 0 | DS25: 0 | DT25: 0 | DU25: 0 | DV25: 0 | DW25: 0 | DX25: 0 | DY25: 0 | DZ25: 0 | EA25: 0 | EB25: 0 | EC25: 0 | ED25: 0
A26: 106364231 | B26: ARROWHEAD REGIONAL MEDICAL CENTER | C26: 20174 | D26: 43009 | E26: 43100 | F26: Open | G26: San Bernardino | H26: 12 | I26: 1209 | J26: City/County | K26: Comparable | L26: Teaching | M26: 909-580-1000 | N26: 400 N. PEPPER AVENUE | O26: COLTON | P26: 92324 | Q26: WILLIAM GILBERT | R26: 456 | S26: 436 | T26: 368 | U26: 647 | V26: 0 | W26: 2053 | X26: 2275 | Y26: 0 | Z26: 0 | AA26: 237 | AB26: 0 | AC26: 257 | AD26: 6 | AE26: 5475 | AF26: 0 | AG26: 4149 | AH26: 0 | AI26: 12150 | AJ26: 9282 | AK26: 0 | AL26: 0 | AM26: 1425 | AN26: 0 | AO26: 933 | AP26: 10 | AQ26: 27949 | AR26: 0 | AS26: =Append1[[#This Row],[DAY_MCAR]]+Append1[[#This Row],[DAY_MCAR_MC]]+Append1[[#This Row],[DAY_MCAL]]+Append1[[#This Row],[DAY_MCAL_MC]]+Append1[[#This Row],[DAY_CNTY]]+Append1[[#This Row],[DAY_CNTY_MC]]+Append1[[#This Row],[DAY_THRD]]+Append1[[#This Row],[DAY_THRD_MC]]+Append1[[#This Row],[DAY_INDGNT]]+Append1[[#This Row],[DAY_OTH]]+Append1[[#This Row],[DAY_TOT]]+Append1[[#This Row],[DAY_LTC]] -> 55898 | AT26: 12479 | AU26: 0 | AV26: 50092 | AW26: 11642 | AX26: 5 | AY26: 0 | AZ26: 2169 | BA26: 0 | BB26: 5922 | BC26: 208 | BD26: 82517 | BE26: 43287233 | BF26: 0 | BG26: 68295088 | BH26: 84319607 | BI26: 0 | BJ26: 0 | BK26: 16966317 | BL26: 0 | BM26: 9017593 | BN26: 96651 | BO26: 221982489 | BP26: 23330158 | BQ26: 0 | BR26: 48214092 | BS26: 38810302 | BT26: 4560 | BU26: 0 | BV26: 6206527 | BW26: 0 | BX26: 13779706 | BY26: 483989 | BZ26: 130829334 | CA26: 493032 | CB26: 46138377 | CC26: 0 | CD26: 84392576 | CE26: 76725500 | CF26: -3744040 | CG26: 4560 | CH26: 0 | CI26: 15467250 | CJ26: 0 | CK26: 0 | CL26: 19357589 | CM26: 0 | CN26: 0 | CO26: 0 | CP26: 0 | CQ26: 238834844 | CR26: 0 | CS26: 0 | CT26: 0 | CU26: 0 | CV26: 0 | CW26: 20479014 | CX26: 0 | CY26: 35860644 | CZ26: 46404409 | DA26: 0 | DB26: 0 | DC26: 7705594 | DD26: 0 | DE26: 3439710 | DF26: 87608 | DG26: 113976979 | DH26: 14286660 | DI26: 132548751 | DJ26: 0 | DK26: 7734868 | DL26: 0 | DM26: 0 | DN26: 0 | DO26: 0 | DP26: 887651 | DQ26: 347800530 | DR26: 0 | DS26: 0 | DT26: 0 | DU26: 0 | DV26: 0 | DW26: 0 | DX26: 0 | DY26: 0 | DZ26: 0 | EA26: 0 | EB26: 0 | EC26: 0 | ED26: 0
A27: 106400683 | B27: ATASCADERO STATE HOSPITAL | C27: 20174 | D27: 43009 | E27: 43100 | F27: Open | G27: San Luis Obispo | H27: 8 | I27: 801 | J27: State | K27: State Hospitals | M27: 805-468-2000 | N27: 10333 EL CAMINO REAL | O27: ATASCADERO | P27: 93422 | Q27: JON MORALES | R27: 1275 | S27: 1183 | T27: 1183 | U27: 8 | V27: 0 | W27: 0 | X27: 0 | Y27: 0 | Z27: 0 | AA27: 1 | AB27: 0 | AC27: 0 | AD27: 334 | AE27: 343 | AF27: 0 | AG27: 23778 | AH27: 0 | AI27: 0 | AJ27: 0 | AK27: 0 | AL27: 0 | AM27: 4 | AN27: 0 | AO27: 0 | AP27: 78105 | AQ27: 101887 | AR27: 0 | AS27: =Append1[[#This Row],[DAY_MCAR]]+Append1[[#This Row],[DAY_MCAR_MC]]+Append1[[#This Row],[DAY_MCAL]]+Append1[[#This Row],[DAY_MCAL_MC]]+Append1[[#This Row],[DAY_CNTY]]+Append1[[#This Row],[DAY_CNTY_MC]]+Append1[[#This Row],[DAY_THRD]]+Append1[[#This Row],[DAY_THRD_MC]]+Append1[[#This Row],[DAY_INDGNT]]+Append1[[#This Row],[DAY_OTH]]+Append1[[#This Row],[DAY_TOT]]+Append1[[#This Row],[DAY_LTC]] -> 203774 | AT27: 0 | AU27: 0 | AV27: 0 | AW27: 0 | AX27: 0 | AY27: 0 | AZ27: 0 | BA27: 0 | BB27: 0 | BC27: 0 | BD27: 0 | BE27: 12089271 | BF27: 0 | BG27: 0 | BH27: 0 | BI27: 0 | BJ27: 0 | BK27: 1792 | BL27: 0 | BM27: 0 | BN27: 39710260 | BO27: 51801323 | BP27: 0 | BQ27: 0 | BR27: 0 | BS27: 0 | BT27: 0 | BU27: 0 | BV27: 0 | BW27: 0 | BX27: 0 | BY27: 0 | BZ27: 0 | CA27: 0 | CB27: 0 | CC27: 0 | CD27: 0 | CE27: 0 | CF27: 0 | CG27: 0 | CH27: 0 | CI27: 0 | CJ27: 0 | CK27: 0 | CL27: 0 | CM27: 0 | CN27: 0 | CO27: 0 | CP27: 7532 | CQ27: 7532 | CR27: 0 | CS27: 0 | CT27: 0 | CU27: 0 | CV27: 0 | CW27: 12089271 | CX27: 0 | CY27: 0 | CZ27: 0 | DA27: 0 | DB27: 0 | DC27: 1792 | DD27: 0 | DE27: 0 | DF27: 39702728 | DG27: 51793791 | DH27: 0 | DI27: 64212889 | DJ27: 0 | DK27: 12419098 | DL27: 0 | DM27: 0 | DN27: 0 | DO27: 0 | DP27: 0 | DQ27: 0 | DR27: 0 | DS27: 0 | DT27: 0 | DU27: 0 | DV27: 0 | DW27: 0 | DX27: 0 | DY27: 0 | DZ27: 0 | EA27: 0 | EB27: 0 | EC27: 0 | ED27: 0
A28: 106494048 | B28: AURORA BEHAVIORAL HEALTHCARE - SANTA ROSA | C28: 20174 | D28: 43009 | E28: 43100 | F28: Open | G28: Sonoma | H28: 3 | I28: 401 | J28: Investor - Corp. | K28: Comparable | M28: 707-800-7700 | N28: 1287 FULTON ROAD | O28: SANTA ROSA | P28: 95401 | Q28: SUSAN ROSE | R28: 95 | S28: 95 | T28: 64 | U28: 129 | V28: 19 | W28: 242 | X28: 0 | Y28: 87 | Z28: 0 | AA28: 7 | AB28: 209 | AC28: 0 | AD28: 1 | AE28: 694 | AF28: 0 | AG28: 1353 | AH28: 191 | AI28: 2016 | AJ28: 0 | AK28: 722 | AL28: 0 | AM28: 81 | AN28: 1519 | AO28: 0 | AP28: 5 | AQ28: 5887 | AR28: 0 | AS28: =Append1[[#This Row],[DAY_MCAR]]+Append1[[#This Row],[DAY_MCAR_MC]]+Append1[[#This Row],[DAY_MCAL]]+Append1[[#This Row],[DAY_MCAL_MC]]+Append1[[#This Row],[DAY_CNTY]]+Append1[[#This Row],[DAY_CNTY_MC]]+Append1[[#This Row],[DAY_THRD]]+Append1[[#This Row],[DAY_THRD_MC]]+Append1[[#This Row],[DAY_INDGNT]]+Append1[[#This Row],[DAY_OTH]]+Append1[[#This Row],[DAY_TOT]]+Append1[[#This Row],[DAY_LTC]] -> 11774 | AT28: 248 | AU28: 89 | AV28: 0 | AW28: 0 | AX28: 0 | AY28: 0 | AZ28: 0 | BA28: 455 | BB28: 0 | BC28: 0 | BD28: 792 | BE28: 2709025 | BF28: 382400 | BG28: 4033950 | BH28: 0 | BI28: 1445975 | BJ28: 0 | BK28: 162175 | BL28: 3047325 | BM28: 0 | BN28: 10025 | BO28: 11790875 | BP28: 140700 | BQ28: 56700 | BR28: 0 | BS28: 0 | BT28: 0 | BU28: 0 | BV28: 0 | BW28: 270550 | BX28: 0 | BY28: 0 | BZ28: 467950 | CA28: 0 | CB28: 1098326 | CC28: 200957 | CD28: 1679681 | CE28: 0 | CF28: 0 | CG28: 622883 | CH28: 0 | CI28: 66945 | CJ28: 720619 | CK28: 0 | CL28: 0 | CM28: 0 | CN28: 0 | CO28: 0 | CP28: 1317 | CQ28: 4390728 | CR28: 0 | CS28: 0 | CT28: 0 | CU28: 0 | CV28: 0 | CW28: 1751399 | CX28: 238143 | CY28: 2354269 | CZ28: 0 | DA28: 823092 | DB28: 0 | DC28: 95230 | DD28: 2597256 | DE28: 0 | DF28: 8708 | DG28: 7868097 | DH28: 1811 | DI28: 7790631 | DJ28: 967691 | DK28: -1097 | DL28: 0 | DM28: 0 | DN28: 0 | DO28: 0 | DP28: 20927 | DQ28: 180841 | DR28: 0 | DS28: 0 | DT28: 0 | DU28: 0 | DV28: 0 | DW28: 0 | DX28: 0 | DY28: 0 | DZ28: 0 | EA28: 0 | EB28: 0 | EC28: 0 | ED28: 0
A29: 106190163 | B29: AURORA CHARTER OAK | C29: 20174 | D29: 43009 | E29: 43100 | F29: Open | G29: Los Angeles | H29: 11 | I29: 915 | J29: Investor - Corp. | K29: Comparable | M29: 626-966-1632 | N29: 1161 EAST COVINA BOULEVARD | O29: COVINA | P29: 91724 | Q29: TODD SMITH | R29: 134 | S29: 134 | T29: 123 | U29: 198 | V29: 128 | W29: 382 | X29: 0 | Y29: 100 | Z29: 0 | AA29: 72 | AB29: 445 | AC29: 193 | AD29: 10 | AE29: 1528 | AF29: 0 | AG29: 2337 | AH29: 1214 | AI29: 2800 | AJ29: 0 | AK29: 792 | AL29: 0 | AM29: 642 | AN29: 2934 | AO29: 473 | AP29: 114 | AQ29: 11306 | AR29: 0 | AS29: =Append1[[#This Row],[DAY_MCAR]]+Append1[[#This Row],[DAY_MCAR_MC]]+Append1[[#This Row],[DAY_MCAL]]+Append1[[#This Row],[DAY_MCAL_MC]]+Append1[[#This Row],[DAY_CNTY]]+Append1[[#This Row],[DAY_CNTY_MC]]+Append1[[#This Row],[DAY_THRD]]+Append1[[#This Row],[DAY_THRD_MC]]+Append1[[#This Row],[DAY_INDGNT]]+Append1[[#This Row],[DAY_OTH]]+Append1[[#This Row],[DAY_TOT]]+Append1[[#This Row],[DAY_LTC]] -> 22612 | AT29: 1076 | AU29: 347 | AV29: 0 | AW29: 0 | AX29: 0 | AY29: 0 | AZ29: 100 | BA29: 1104 | BB29: 0 | BC29: 30 | BD29: 2657 | BE29: 3532700 | BF29: 1784250 | BG29: 4166125 | BH29: 0 | BI29: 1207225 | BJ29: 0 | BK29: 1008325 | BL29: 4410700 | BM29: 748525 | BN29: 165425 | BO29: 17023275 | BP29: 526240 | BQ29: 160640 | BR29: 0 | BS29: 0 | BT29: 0 | BU29: 0 | BV29: 48160 | BW29: 524000 | BX29: 0 | BY29: 18560 | BZ29: 1277600 | CA29: 485665 | CB29: 1563936 | CC29: 832249 | CD29: 2108635 | CE29: 0 | CF29: 0 | CG29: 770036 | CH29: 0 | CI29: 510612 | CJ29: 2002861 | CK29: 0 | CL29: 711657 | CM29: 0 | CN29: 0 | CO29: 0 | CP29: 79307 | CQ29: 9064958 | CR29: 0 | CS29: 0 | CT29: 0 | CU29: 0 | CV29: 0 | CW29: 2495004 | CX29: 1059929 | CY29: 2019183 | CZ29: 0 | DA29: 437189 | DB29: 0 | DC29: 498975 | DD29: 2584091 | DE29: 36868 | DF29: 104678 | DG29: 9235917 | DH29: 7136 | DI29: 8771804 | DJ29: 280855 | DK29: 459529 | DL29: 0 | DM29: 0 | DN29: 0 | DO29: 0 | DP29: 788697 | DQ29: 1382119 | DR29: 0 | DS29: 0 | DT29: 0 | DU29: 0 | DV29: 0 | DW29: 0 | DX29: 0 | DY29: 0 | DZ29: 0 | EA29: 0 | EB29: 0 | EC29: 0 | ED29: 0
A30: 106190462 | B30: AURORA LAS ENCINAS HOSPITAL | C30: 20174 | D30: 43009 | E30: 43100 | F30: Open | G30: Los Angeles | H30: 11 | I30: 911 | J30: Investor - Corp. | K30: Comparable | M30: 626-795-9901 | N30: 2900 EAST DEL MAR BOULEVARD | O30: PASADENA | P30: 91107 | Q30: TOM MAHLE | R30: 118 | S30: 118 | T30: 78 | U30: 210 | V30: 77 | W30: 65 | X30: 0 | Y30: 2 | Z30: 0 | AA30: 505 | AB30: 490 | AC30: 17 | AD30: 26 | AE30: 1392 | AF30: 0 | AG30: 1513 | AH30: 490 | AI30: 259 | AJ30: 0 | AK30: 6 | AL30: 0 | AM30: 1770 | AN30: 2675 | AO30: 72 | AP30: 364 | AQ30: 7149 | AR30: 0 | AS30: =Append1[[#This Row],[DAY_MCAR]]+Append1[[#This Row],[DAY_MCAR_MC]]+Append1[[#This Row],[DAY_MCAL]]+Append1[[#This Row],[DAY_MCAL_MC]]+Append1[[#This Row],[DAY_CNTY]]+Append1[[#This Row],[DAY_CNTY_MC]]+Append1[[#This Row],[DAY_THRD]]+Append1[[#This Row],[DAY_THRD_MC]]+Append1[[#This Row],[DAY_INDGNT]]+Append1[[#This Row],[DAY_OTH]]+Append1[[#This Row],[DAY_TOT]]+Append1[[#This Row],[DAY_LTC]] -> 14298 | AT30: 568 | AU30: 99 | AV30: 0 | AW30: 0 | AX30: 0 | AY30: 0 | AZ30: 84 | BA30: 2269 | BB30: 0 | BC30: 22 | BD30: 3042 | BE30: 2250675 | BF30: 742000 | BG30: 390200 | BH30: 0 | BI30: 9050 | BJ30: 0 | BK30: 2651750 | BL30: 4080325 | BM30: 108475 | BN30: 560175 | BO30: 10792650 | BP30: 273600 | BQ30: 35840 | BR30: 0 | BS30: 0 | BT30: 0 | BU30: 0 | BV30: 47680 | BW30: 1116960 | BX30: 0 | BY30: 13120 | BZ30: 1487200 | CA30: 251667 | CB30: 947083 | CC30: 296047 | CD30: 178219 | CE30: 0 | CF30: 0 | CG30: 3830 | CH30: 0 | CI30: 803972 | CJ30: 1756138 | CK30: 0 | CL30: 108475 | CM30: 0 | CN30: 0 | CO30: 0 | CP30: 228255 | CQ30: 4573686 | CR30: 0 | CS30: 0 | CT30: 0 | CU30: 0 | CV30: 0 | CW30: 1577192 | CX30: 481793 | CY30: 211981 | CZ30: 0 | DA30: 5220 | DB30: 0 | DC30: 1895458 | DD30: 3189480 | DE30: 0 | DF30: 345040 | DG30: 7706164 | DH30: 33912 | DI30: 6727021 | DJ30: 198771 | DK30: 574932 | DL30: 0 | DM30: 0 | DN30: 0 | DO30: 0 | DP30: 34144 | DQ30: 1843037 | DR30: 0 | DS30: 0 | DT30: 0 | DU30: 0 | DV30: 0 | DW30: 0 | DX30: 0 | DY30: 0 | DZ30: 0 | EA30: 0 | EB30: 0 | EC30: 0 | ED30: 0
A31: 106374024 | B31: AURORA SAN DIEGO | C31: 20174 | D31: 43009 | E31: 43100 | F31: Open | G31: San Diego | H31: 14 | I31: 1412 | J31: Investor - Corp. | K31: Comparable | M31: 858-675-4200 | N31: 11878 AVENUE OF INDUSTRY | O31: SAN DIEGO | P31: 92128 | Q31: ALAIN AZCONA | R31: 80 | S31: 80 | T31: 74 | U31: 59 | V31: 53 | W31: 47 | X31: 0 | Y31: 4 | Z31: 0 | AA31: 150 | AB31: 415 | AC31: 1 | AD31: 8 | AE31: 737 | AF31: 0 | AG31: 764 | AH31: 496 | AI31: 262 | AJ31: 0 | AK31: 30 | AL31: 0 | AM31: 2318 | AN31: 2854 | AO31: 6 | AP31: 55 | AQ31: 6785 | AR31: 0 | AS31: =Append1[[#This Row],[DAY_MCAR]]+Append1[[#This Row],[DAY_MCAR_MC]]+Append1[[#This Row],[DAY_MCAL]]+Append1[[#This Row],[DAY_MCAL_MC]]+Append1[[#This Row],[DAY_CNTY]]+Append1[[#This Row],[DAY_CNTY_MC]]+Append1[[#This Row],[DAY_THRD]]+Append1[[#This Row],[DAY_THRD_MC]]+Append1[[#This Row],[DAY_INDGNT]]+Append1[[#This Row],[DAY_OTH]]+Append1[[#This Row],[DAY_TOT]]+Append1[[#This Row],[DAY_LTC]] -> 13570 | AT31: 288 | AU31: 122 | AV31: 0 | AW31: 0 | AX31: 0 | AY31: 0 | AZ31: 548 | BA31: 2793 | BB31: 0 | BC31: 58 | BD31: 3809 | BE31: 1147425 | BF31: 746850 | BG31: 397125 | BH31: 0 | BI31: 45100 | BJ31: 0 | BK31: 3504425 | BL31: 4299325 | BM31: 9050 | BN31: 82700 | BO31: 10232000 | BP31: 146400 | BQ31: 59040 | BR31: 0 | BS31: 0 | BT31: 0 | BU31: 0 | BV31: 304000 | BW31: 1524480 | BX31: 0 | BY31: 28320 | BZ31: 2062240 | CA31: 263125 | CB31: 546639 | CC31: 287154 | CD31: 167540 | CE31: 0 | CF31: 0 | CG31: 19069 | CH31: 0 | CI31: 1099241 | CJ31: 2164111 | CK31: 0 | CL31: 9050 | CM31: 0 | CN31: 0 | CO31: 0 | CP31: 89926 | CQ31: 4645855 | CR31: 0 | CS31: 0 | CT31: 0 | CU31: 0 | CV31: 0 | CW31: 747186 | CX31: 518736 | CY31: 229585 | CZ31: 0 | DA31: 26031 | DB31: 0 | DC31: 2709184 | DD31: 3396570 | DE31: 0 | DF31: 21093 | DG31: 7648385 | DH31: 23691 | DI31: 6279241 | DJ31: 211575 | DK31: -1027 | DL31: 0 | DM31: 0 | DN31: 0 | DO31: 0 | DP31: 197929 | DQ31: 444442 | DR31: 0 | DS31: 0 | DT31: 0 | DU31: 0 | DV31: 0 | DW31: 0 | DX31: 0 | DY31: 0 | DZ31: 0 | EA31: 0 | EB31: 0 | EC31: 0 | ED31: 0
A32: 106560203 | B32: AURORA VISTA DEL MAR HOSPITAL | C32: 20174 | D32: 43009 | E32: 43100 | F32: Open | G32: Ventura | H32: 10 | I32: 809 | J32: Investor - Corp. | K32: Comparable | M32: 805-653-6434 | N32: 801 SENECA STREET | O32: VENTURA | P32: 93001 | Q32: JENIFER NYHUIS | R32: 87 | S32: 87 | T32: 52 | U32: 100 | V32: 5 | W32: 207 | X32: 0 | Y32: 60 | Z32: 0 | AA32: 49 | AB32: 330 | AC32: 2 | AD32: 3 | AE32: 756 | AF32: 0 | AG32: 842 | AH32: 20 | AI32: 1126 | AJ32: 0 | AK32: 354 | AL32: 0 | AM32: 777 | AN32: 1603 | AO32: 12 | AP32: 7 | AQ32: 4741 | AR32: 0 | AS32: =Append1[[#This Row],[DAY_MCAR]]+Append1[[#This Row],[DAY_MCAR_MC]]+Append1[[#This Row],[DAY_MCAL]]+Append1[[#This Row],[DAY_MCAL_MC]]+Append1[[#This Row],[DAY_CNTY]]+Append1[[#This Row],[DAY_CNTY_MC]]+Append1[[#This Row],[DAY_THRD]]+Append1[[#This Row],[DAY_THRD_MC]]+Append1[[#This Row],[DAY_INDGNT]]+Append1[[#This Row],[DAY_OTH]]+Append1[[#This Row],[DAY_TOT]]+Append1[[#This Row],[DAY_LTC]] -> 9482 | AT32: 102 | AU32: 21 | AV32: 0 | AW32: 0 | AX32: 0 | AY32: 0 | AZ32: 20 | BA32: 285 | BB32: 0 | BC32: 9 | BD32: 437 | BE32: 1295925 | BF32: 32850 | BG32: 1820775 | BH32: 0 | BI32: 571050 | BJ32: 0 | BK32: 1245625 | BL32: 2613525 | BM32: 19025 | BN32: 12850 | BO32: 7611625 | BP32: 69120 | BQ32: 14720 | BR32: 0 | BS32: 0 | BT32: 0 | BU32: 0 | BV32: 11840 | BW32: 188960 | BX32: 0 | BY32: 5600 | BZ32: 290240 | CA32: 108534 | CB32: 587273 | CC32: 29633 | CD32: 903932 | CE32: 0 | CF32: -60146 | CG32: 275043 | CH32: 0 | CI32: 521486 | CJ32: 1119623 | CK32: 0 | CL32: 19025 | CM32: 0 | CN32: 0 | CO32: 0 | CP32: 11751 | CQ32: 3516154 | CR32: 0 | CS32: 0 | CT32: 0 | CU32: 0 | CV32: 0 | CW32: 777772 | CX32: 17937 | CY32: 976989 | CZ32: 0 | DA32: 296007 | DB32: 0 | DC32: 735979 | DD32: 1574328 | DE32: 0 | DF32: 6699 | DG32: 4385711 | DH32: 12172 | DI32: 3806633 | DJ32: 100471 | DK32: -784 | DL32: 0 | DM32: 0 | DN32: 0 | DO32: 0 | DP32: 1111700 | DQ32: 285346 | DR32: 0 | DS32: 0 | DT32: 0 | DU32: 0 | DV32: 0 | DW32: 0 | DX32: 0 | DY32: 0 | DZ32: 0 | EA32: 0 | EB32: 0 | EC32: 0 | ED32: 0
A33: 106154044 | B33: BAKERSFIELD BEHAVIORAL HEALTHCARE HOSPITAL | C33: 20174 | D33: 43009 | E33: 43100 | F33: Open | G33: Kern | H33: 9 | I33: 617 | J33: Non Profit Corp. | K33: Comparable | M33: 661-398-1800 | N33: 5201 WHITE LANE | O33: BAKERSFIELD | P33: 93309 | Q33: BECKIE SHAUINGER | R33: 90 | S33: 90 | T33: 55 | U33: 108 | V33: 22 | W33: 290 | X33: 0 | Y33: 155 | Z33: 0 | AA33: 6 | AB33: 229 | AC33: 10 | AD33: 0 | AE33: 820 | AF33: 0 | AG33: 812 | AH33: 95 | AI33: 1834 | AJ33: 0 | AK33: 1071 | AL33: 0 | AM33: 35 | AN33: 1176 | AO33: 36 | AP33: 5 | AQ33: 5064 | AR33: 0 | AS33: =Append1[[#This Row],[DAY_MCAR]]+Append1[[#This Row],[DAY_MCAR_MC]]+Append1[[#This Row],[DAY_MCAL]]+Append1[[#This Row],[DAY_MCAL_MC]]+Append1[[#This Row],[DAY_CNTY]]+Append1[[#This Row],[DAY_CNTY_MC]]+Append1[[#This Row],[DAY_THRD]]+Append1[[#This Row],[DAY_THRD_MC]]+Append1[[#This Row],[DAY_INDGNT]]+Append1[[#This Row],[DAY_OTH]]+Append1[[#This Row],[DAY_TOT]]+Append1[[#This Row],[DAY_LTC]] -> 10128 | AT33: 183 | AU33: 82 | AV33: 0 | AW33: 0 | AX33: 0 | AY33: 0 | AZ33: 15 | BA33: 508 | BB33: 0 | BC33: 0 | BD33: 788 | BE33: 1626575 | BF33: 190500 | BG33: 3674925 | BH33: 0 | BI33: 2145875 | BJ33: 0 | BK33: 70150 | BL33: 2357475 | BM33: 72125 | BN33: 10025 | BO33: 10147650 | BP33: 107450 | BQ33: 46550 | BR33: 0 | BS33: 0 | BT33: 0 | BU33: 0 | BV33: 7525 | BW33: 307650 | BX33: 0 | BY33: 0 | BZ33: 469175 | CA33: 0 | CB33: 943720 | CC33: 125513 | CD33: 2393432 | CE33: 0 | CF33: 0 | CG33: 1812833 | CH33: 0 | CI33: 33042 | CJ33: 1158757 | CK33: 0 | CL33: 31770 | CM33: 0 | CN33: 0 | CO33: 0 | CP33: 1767 | CQ33: 6500834 | CR33: 0 | CS33: 0 | CT33: 0 | CU33: 0 | CV33: 0 | CW33: 790305 | CX33: 111537 | CY33: 1281493 | CZ33: 0 | DA33: 333042 | DB33: 0 | DC33: 44633 | DD33: 1506368 | DE33: 40355 | DF33: 8258 | DG33: 4115991 | DH33: 9295 | DI33: 3899015 | DJ33: 176050 | DK33: -756 | DL33: 0 | DM33: 0 | DN33: 0 | DO33: 0 | DP33: 34257 | DQ33: 505122 | DR33: 0 | DS33: 0 | DT33: 0 | DU33: 0 | DV33: 0 | DW33: 0 | DX33: 0 | DY33: 0 | DZ33: 0 | EA33: 0 | EB33: 0 | EC33: 0 | ED33: 0
A34: 106154101 | B34: BAKERSFIELD HEART HOSPITAL | C34: 20174 | D34: 43009 | E34: 43100 | F34: Open | G34: Kern | H34: 9 | I34: 617 | J34: Investor - Corp. | K34: Comparable | M34: 661-316-6000 | N34: 3001 SILLECT AVENUE | O34: BAKERSFIELD | P34: 93308 | Q34: MICHELLE OXFORD | R34: 47 | S34: 47 | T34: 47 | U34: 532 | V34: 82 | W34: 17 | X34: 88 | Y34: 0 | Z34: 0 | AA34: 131 | AB34: 0 | AC34: 0 | AD34: 21 | AE34: 871 | AF34: 0 | AG34: 2060 | AH34: 316 | AI34: 65 | AJ34: 340 | AK34: 0 | AL34: 0 | AM34: 510 | AN34: 0 | AO34: 0 | AP34: 85 | AQ34: 3376 | AR34: 0 | AS34: =Append1[[#This Row],[DAY_MCAR]]+Append1[[#This Row],[DAY_MCAR_MC]]+Append1[[#This Row],[DAY_MCAL]]+Append1[[#This Row],[DAY_MCAL_MC]]+Append1[[#This Row],[DAY_CNTY]]+Append1[[#This Row],[DAY_CNTY_MC]]+Append1[[#This Row],[DAY_THRD]]+Append1[[#This Row],[DAY_THRD_MC]]+Append1[[#This Row],[DAY_INDGNT]]+Append1[[#This Row],[DAY_OTH]]+Append1[[#This Row],[DAY_TOT]]+Append1[[#This Row],[DAY_LTC]] -> 6752 | AT34: 2338 | AU34: 452 | AV34: 48 | AW34: 871 | AX34: 0 | AY34: 0 | AZ34: 1217 | BA34: 0 | BB34: 0 | BC34: 343 | BD34: 5269 | BE34: 40411518 | BF34: 6197908 | BG34: 1278455 | BH34: 6665868 | BI34: 0 | BJ34: 0 | BK34: 10002296 | BL34: 0 | BM34: 0 | BN34: 1661135 | BO34: 66217180 | BP34: 21654627 | BQ34: 4189059 | BR34: 445344 | BS34: 8071522 | BT34: 0 | BU34: 0 | BV34: 11270133 | BW34: 0 | BX34: 0 | BY34: 3180770 | BZ34: 48811455 | CA34: 0 | CB34: 57046538 | CC34: 305591 | CD34: -6252271 | CE34: 12010041 | CF34: 0 | CG34: 0 | CH34: 0 | CI34: 30532033 | CJ34: 0 | CK34: 0 | CL34: 29250 | CM34: 0 | CN34: 0 | CO34: 0 | CP34: 1440079 | CQ34: 95111261 | CR34: 0 | CS34: 0 | CT34: 0 | CU34: 0 | CV34: 0 | CW34: 5019607 | CX34: 10081376 | CY34: 7976070 | CZ34: 2727349 | DA34: 0 | DB34: 0 | DC34: -9259605 | DD34: 0 | DE34: 0 | DF34: 3372577 | DG34: 19917374 | DH34: 167313 | DI34: 17328122 | DJ34: 133662 | DK34: 9312 | DL34: 0 | DM34: 0 | DN34: 0 | DO34: 0 | DP34: 1117896 | DQ34: 41828416 | DR34: 0 | DS34: 0 | DT34: 0 | DU34: 0 | DV34: 0 | DW34: 0 | DX34: 0 | DY34: 0 | DZ34: 0 | EA34: 0 | EB34: 0 | EC34: 0 | ED34: 0
A35: 106150722 | B35: BAKERSFIELD MEMORIAL HOSPITAL | C35: 20174 | D35: 43009 | E35: 43100 | F35: Open | G35: Kern | H35: 9 | I35: 617 | J35: Non Profit Corp. | K35: Comparable | M35: 661-327-4647 | N35: 420 34TH STREET | O35: BAKERSFIELD | P35: 93301 | Q35: JON VAN BOENING | R35: 421 | S35: 398 | T35: 398 | U35: 862 | V35: 431 | W35: 410 | X35: 1353 | Y35: 0 | Z35: 0 | AA35: 59 | AB35: 735 | AC35: 14 | AD35: 3 | AE35: 3867 | AF35: 0 | AG35: 4031 | AH35: 1629 | AI35: 2301 | AJ35: 4189 | AK35: 0 | AL35: 0 | AM35: 238 | AN35: 2502 | AO35: 29 | AP35: 6 | AQ35: 14925 | AR35: 0 | AS35: =Append1[[#This Row],[DAY_MCAR]]+Append1[[#This Row],[DAY_MCAR_MC]]+Append1[[#This Row],[DAY_MCAL]]+Append1[[#This Row],[DAY_MCAL_MC]]+Append1[[#This Row],[DAY_CNTY]]+Append1[[#This Row],[DAY_CNTY_MC]]+Append1[[#This Row],[DAY_THRD]]+Append1[[#This Row],[DAY_THRD_MC]]+Append1[[#This Row],[DAY_INDGNT]]+Append1[[#This Row],[DAY_OTH]]+Append1[[#This Row],[DAY_TOT]]+Append1[[#This Row],[DAY_LTC]] -> 29850 | AT35: 7381 | AU35: 1720 | AV35: 2520 | AW35: 16321 | AX35: 0 | AY35: 0 | AZ35: 459 | BA35: 6627 | BB35: 1735 | BC35: 888 | BD35: 37651 | BE35: 99149074 | BF35: 36481077 | BG35: 33170981 | BH35: 70182954 | BI35: 0 | BJ35: 0 | BK35: 5757186 | BL35: 58204118 | BM35: 528452 | BN35: 112877 | BO35: 303586719 | BP35: 23568755 | BQ35: 16785664 | BR35: 8196998 | BS35: 51476040 | BT35: 0 | BU35: 0 | BV35: 2060856 | BW35: 32113748 | BX35: 2415544 | BY35: 1237061 | BZ35: 137854666 | CA35: 1954807 | CB35: 100557154 | CC35: 46076132 | CD35: -21914610 | CE35: 104201699 | CF35: 0 | CG35: 0 | CH35: 0 | CI35: 5761249 | CJ35: 55772547 | CK35: 0 | CL35: 3107192 | CM35: 0 | CN35: 0 | CO35: 0 | CP35: 406424 | CQ35: 295922594 | CR35: 5645553 | CS35: 0 | CT35: 0 | CU35: 4856048 | CV35: 10501601 | CW35: 21924296 | CX35: 12791948 | CY35: 63119679 | CZ35: 17395661 | DA35: 0 | DB35: 0 | DC35: 2030697 | DD35: 38682199 | DE35: 0 | DF35: 75912 | DG35: 156020392 | DH35: 977593 | DI35: 128031749 | DJ35: 0 | DK35: 6093774 | DL35: 0 | DM35: 0 | DN35: 0 | DO35: 0 | DP35: 4247296 | DQ35: 155306861 | DR35: 0 | DS35: 0 | DT35: 0 | DU35: 0 | DV35: 0 | DW35: 0 | DX35: 0 | DY35: 0 | DZ35: 0 | EA35: 0 | EB35: 0 | EC35: 0 | ED35: 0
A36: 106364121 | B36: BALLARD REHABILITATION HOSPITAL | C36: 20174 | D36: 43009 | E36: 43100 | F36: Open | G36: San Bernardino | H36: 12 | I36: 1209 | J36: Investor - Ptnr. | K36: Comparable | M36: 909-473-1200 | N36: 1760 WEST 16TH STREET | O36: SAN BERNARDINO | P36: 92411 | Q36: MARY HUNT | R36: 60 | S36: 60 | T36: 60 | U36: 95 | V36: 32 | W36: 28 | X36: 55 | Y36: 0 | Z36: 0 | AA36: 0 | AB36: 0 | AC36: 0 | AD36: 41 | AE36: 251 | AF36: 0 | AG36: 1210 | AH36: 547 | AI36: 551 | AJ36: 641 | AK36: 0 | AL36: 0 | AM36: 0 | AN36: 0 | AO36: 0 | AP36: 682 | AQ36: 3631 | AR36: 0 | AS36: =Append1[[#This Row],[DAY_MCAR]]+Append1[[#This Row],[DAY_MCAR_MC]]+Append1[[#This Row],[DAY_MCAL]]+Append1[[#This Row],[DAY_MCAL_MC]]+Append1[[#This Row],[DAY_CNTY]]+Append1[[#This Row],[DAY_CNTY_MC]]+Append1[[#This Row],[DAY_THRD]]+Append1[[#This Row],[DAY_THRD_MC]]+Append1[[#This Row],[DAY_INDGNT]]+Append1[[#This Row],[DAY_OTH]]+Append1[[#This Row],[DAY_TOT]]+Append1[[#This Row],[DAY_LTC]] -> 7262 | AT36: 298 | AU36: 174 | AV36: 31 | AW36: 650 | AX36: 0 | AY36: 0 | AZ36: 0 | BA36: 0 | BB36: 0 | BC36: 883 | BD36: 2036 | BE36: 3269340 | BF36: 1400109 | BG36: 1565651 | BH36: 1615305 | BI36: 0 | BJ36: 0 | BK36: 0 | BL36: 0 | BM36: 0 | BN36: 1039694 | BO36: 8890099 | BP36: 122559 | BQ36: 66363 | BR36: 4805 | BS36: 151409 | BT36: 0 | BU36: 0 | BV36: 0 | BW36: 0 | BX36: 0 | BY36: 290485 | BZ36: 635621 | CA36: 31284 | CB36: 767289 | CC36: 248751 | CD36: 491340 | CE36: 944037 | CF36: 0 | CG36: 0 | CH36: 0 | CI36: 0 | CJ36: 0 | CK36: 0 | CL36: 0 | CM36: 0 | CN36: 0 | CO36: 0 | CP36: 794248 | CQ36: 3276949 | CR36: 0 | CS36: 0 | CT36: 0 | CU36: 0 | CV36: 0 | CW36: 2593326 | CX36: 1217721 | CY36: 1079116 | CZ36: 822677 | DA36: 0 | DB36: 0 | DC36: 0 | DD36: 0 | DE36: 0 | DF36: 535931 | DG36: 6248771 | DH36: 12577 | DI36: 4461304 | DJ36: 0 | DK36: 0 | DL36: 0 | DM36: 0 | DN36: 0 | DO36: 0 | DP36: 44540 | DQ36: 494567 | DR36: 0 | DS36: 0 | DT36: 0 | DU36: 0 | DV36: 0 | DW36: 0 | DX36: 0 | DY36: 0 | DZ36: 0 | EA36: 0 | EB36: 0 | EC36: 0 | ED36: 0
A37: 106184008 | B37: BANNER LASSEN MEDICAL CENTER | C37: 20174 | D37: 43009 | E37: 43100 | F37: Open | G37: Lassen | H37: 1 | I37: 213 | J37: Non Profit Corp. | K37: Comparable | L37: Rural | M37: 530-252-2200 | N37: 1800 SPRING RIDGE DRIVE | O37: SUSANVILLE | P37: 96130 | Q37: CATHERINE HARSHBARGER | R37: 25 | S37: 25 | T37: 25 | U37: 87 | V37: 0 | W37: 113 | X37: 0 | Y37: 0 | Z37: 0 | AA37: 84 | AB37: 0 | AC37: 0 | AD37: 0 | AE37: 284 | AF37: 0 | AG37: 380 | AH37: 0 | AI37: 292 | AJ37: 0 | AK37: 0 | AL37: 0 | AM37: 217 | AN37: 0 | AO37: 0 | AP37: 0 | AQ37: 889 | AR37: 0 | AS37: =Append1[[#This Row],[DAY_MCAR]]+Append1[[#This Row],[DAY_MCAR_MC]]+Append1[[#This Row],[DAY_MCAL]]+Append1[[#This Row],[DAY_MCAL_MC]]+Append1[[#This Row],[DAY_CNTY]]+Append1[[#This Row],[DAY_CNTY_MC]]+Append1[[#This Row],[DAY_THRD]]+Append1[[#This Row],[DAY_THRD_MC]]+Append1[[#This Row],[DAY_INDGNT]]+Append1[[#This Row],[DAY_OTH]]+Append1[[#This Row],[DAY_TOT]]+Append1[[#This Row],[DAY_LTC]] -> 1778 | AT37: 2887 | AU37: 0 | AV37: 2311 | AW37: 0 | AX37: 0 | AY37: 0 | AZ37: 3486 | BA37: 0 | BB37: 626 | BC37: 0 | BD37: 9310 | BE37: 2187831 | BF37: 0 | BG37: 1927886 | BH37: 0 | BI37: 0 | BJ37: 0 | BK37: 1396679 | BL37: 0 | BM37: 0 | BN37: 0 | BO37: 5512396 | BP37: 4993050 | BQ37: 0 | BR37: 4269336 | BS37: 0 | BT37: 0 | BU37: 0 | BV37: 5957153 | BW37: 0 | BX37: 196887 | BY37: 0 | BZ37: 15416426 | CA37: 383197 | CB37: 4367263 | CC37: 0 | CD37: 4040227 | CE37: 0 | CF37: 0 | CG37: 0 | CH37: 0 | CI37: 1925940 | CJ37: 0 | CK37: 0 | CL37: 162617 | CM37: 0 | CN37: 0 | CO37: 0 | CP37: 0 | CQ37: 10879244 | CR37: 0 | CS37: 0 | CT37: 0 | CU37: 0 | CV37: 0 | CW37: 2753182 | CX37: 0 | CY37: 2115395 | CZ37: 0 | DA37: 0 | DB37: 0 | DC37: 5164861 | DD37: 0 | DE37: 16140 | DF37: 0 | DG37: 10049578 | DH37: 7181 | DI37: 7213381 | DJ37: 499694 | DK37: 0 | DL37: 0 | DM37: 0 | DN37: 0 | DO37: 0 | DP37: 408290 | DQ37: 14453478 | DR37: 0 | DS37: 0 | DT37: 0 | DU37: 0 | DV37: 0 | DW37: 0 | DX37: 0 | DY37: 0 | DZ37: 0 | EA37: 0 | EB37: 0 | EC37: 0 | ED37: 0
A38: 106190052 | B38: BARLOW RESPIRATORY HOSPITAL | C38: 20174 | D38: 43009 | E38: 43100 | F38: Open | G38: Los Angeles | H38: 11 | I38: 925 | J38: Non Profit Corp. | K38: Comparable | M38: 213-250-4200 | N38: 2000 STADIUM WAY | O38: LOS ANGELES | P38: 90026 | Q38: AMIT MOHAN | R38: 105 | S38: 105 | T38: 105 | U38: 140 | V38: 3 | W38: 16 | X38: 7 | Y38: 0 | Z38: 0 | AA38: 7 | AB38: 10 | AC38: 0 | AD38: 0 | AE38: 183 | AF38: 0 | AG38: 4388 | AH38: 187 | AI38: 757 | AJ38: 401 | AK38: 0 | AL38: 0 | AM38: 271 | AN38: 488 | AO38: 0 | AP38: 0 | AQ38: 6492 | AR38: 0 | AS38: =Append1[[#This Row],[DAY_MCAR]]+Append1[[#This Row],[DAY_MCAR_MC]]+Append1[[#This Row],[DAY_MCAL]]+Append1[[#This Row],[DAY_MCAL_MC]]+Append1[[#This Row],[DAY_CNTY]]+Append1[[#This Row],[DAY_CNTY_MC]]+Append1[[#This Row],[DAY_THRD]]+Append1[[#This Row],[DAY_THRD_MC]]+Append1[[#This Row],[DAY_INDGNT]]+Append1[[#This Row],[DAY_OTH]]+Append1[[#This Row],[DAY_TOT]]+Append1[[#This Row],[DAY_LTC]] -> 12984 | AT38: 0 | AU38: 0 | AV38: 0 | AW38: 0 | AX38: 0 | AY38: 0 | AZ38: 0 | BA38: 0 | BB38: 0 | BC38: 0 | BD38: 0 | BE38: 73119940 | BF38: 3485889 | BG38: 13632646 | BH38: 7146854 | BI38: 0 | BJ38: 0 | BK38: 4216659 | BL38: 8962426 | BM38: 0 | BN38: 0 | BO38: 110564414 | BP38: 0 | BQ38: 0 | BR38: 0 | BS38: 0 | BT38: 0 | BU38: 0 | BV38: 0 | BW38: 0 | BX38: 0 | BY38: 0 | BZ38: 0 | CA38: 221884 | CB38: 61314016 | CC38: 3167385 | CD38: 12431468 | CE38: 6469778 | CF38: 0 | CG38: 0 | CH38: 0 | CI38: 3238180 | CJ38: 7800253 | CK38: 0 | CL38: 0 | CM38: 0 | CN38: 0 | CO38: 0 | CP38: 0 | CQ38: 94642964 | CR38: 0 | CS38: 0 | CT38: 0 | CU38: 0 | CV38: 0 | CW38: 11750453 | CX38: 318504 | CY38: 1201178 | CZ38: 677076 | DA38: 0 | DB38: 0 | DC38: 978479 | DD38: 995760 | DE38: 0 | DF38: 0 | DG38: 15921450 | DH38: 122089 | DI38: 15042602 | DJ38: 0 | DK38: 0 | DL38: 0 | DM38: 0 | DN38: 0 | DO38: 0 | DP38: 240905 | DQ38: 10433902 | DR38: 0 | DS38: 0 | DT38: 0 | DU38: 0 | DV38: 0 | DW38: 0 | DX38: 0 | DY38: 0 | DZ38: 0 | EA38: 0 | EB38: 0 | EC38: 0 | ED38: 0
A39: 106364430 | B39: BARSTOW COMMUNITY HOSPITAL | C39: 20174 | D39: 43009 | E39: 43100 | F39: Open | G39: San Bernardino | H39: 12 | I39: 1213 | J39: Investor - Corp. | K39: Comparable | L39: Rural | M39: 760-957-3221 | N39: 820 EAST MOUNTAIN VIEW STREET | O39: BARSTOW | P39: 92311 | Q39: MATTHEW BLEVINS | R39: 30 | S39: 30 | T39: 30 | U39: 176 | V39: 82 | W39: 62 | X39: 159 | Y39: 0 | Z39: 0 | AA39: 29 | AB39: 57 | AC39: 0 | AD39: 20 | AE39: 585 | AF39: 0 | AG39: 545 | AH39: 261 | AI39: 219 | AJ39: 342 | AK39: 0 | AL39: 0 | AM39: 104 | AN39: 150 | AO39: 0 | AP39: 68 | AQ39: 1689 | AR39: 0 | AS39: =Append1[[#This Row],[DAY_MCAR]]+Append1[[#This Row],[DAY_MCAR_MC]]+Append1[[#This Row],[DAY_MCAL]]+Append1[[#This Row],[DAY_MCAL_MC]]+Append1[[#This Row],[DAY_CNTY]]+Append1[[#This Row],[DAY_CNTY_MC]]+Append1[[#This Row],[DAY_THRD]]+Append1[[#This Row],[DAY_THRD_MC]]+Append1[[#This Row],[DAY_INDGNT]]+Append1[[#This Row],[DAY_OTH]]+Append1[[#This Row],[DAY_TOT]]+Append1[[#This Row],[DAY_LTC]] -> 3378 | AT39: 1469 | AU39: 558 | AV39: 2417 | AW39: 3075 | AX39: 0 | AY39: 0 | AZ39: 725 | BA39: 880 | BB39: 0 | BC39: 1199 | BD39: 10323 | BE39: 16009846 | BF39: 6727865 | BG39: 7529997 | BH39: 7912053 | BI39: 0 | BJ39: 0 | BK39: 3241771 | BL39: 3919461 | BM39: 0 | BN39: 1643981 | BO39: 46984974 | BP39: 13193206 | BQ39: 5454411 | BR39: 15578696 | BS39: 23345777 | BT39: 0 | BU39: 0 | BV39: 7312860 | BW39: 7353954 | BX39: 0 | BY39: 4139652 | BZ39: 76378556 | CA39: 2198638 | CB39: 26477445 | CC39: 10596775 | CD39: 14966588 | CE39: 30186847 | CF39: 0 | CG39: 0 | CH39: 0 | CI39: 6738351 | CJ39: 8644098 | CK39: 0 | CL39: 0 | CM39: 0 | CN39: 0 | CO39: 0 | CP39: 2235940 | CQ39: 102044682 | CR39: 0 | CS39: 0 | CT39: 0 | CU39: 0 | CV39: 0 | CW39: 2723408 | CX39: 1583302 | CY39: 8139906 | CZ39: 1066586 | DA39: 0 | DB39: 0 | DC39: 3794294 | DD39: 2600735 | DE39: 0 | DF39: 1410617 | DG39: 21318848 | DH39: 12247 | DI39: 10295781 | DJ39: 0 | DK39: 0 | DL39: 0 | DM39: 0 | DN39: 0 | DO39: 0 | DP39: 213523 | DQ39: 57764878 | DR39: 0 | DS39: 0 | DT39: 0 | DU39: 0 | DV39: 0 | DW39: 0 | DX39: 0 | DY39: 0 | DZ39: 0 | EA39: 0 | EB39: 0 | EC39: 0 | ED39: 0
A40: 106090793 | B40: BARTON MEMORIAL HOSPITAL | C40: 20174 | D40: 43009 | E40: 43100 | F40: Open | G40: El Dorado | H40: 2 | I40: 306 | J40: Non Profit Corp. | K40: Comparable | L40: Rural | M40: 530-541-3420 | N40: 2170 SOUTH AVENUE | O40: SOUTH LAKE TAHOE | P40: 96150 | Q40: CLINT PURVANCE | R40: 111 | S40: 111 | T40: 111 | U40: 169 | V40: 32 | W40: 36 | X40: 93 | Y40: 0 | Z40: 0 | AA40: 41 | AB40: 117 | AC40: 20 | AD40: 9 | AE40: 517 | AF40: 2 | AG40: 530 | AH40: 124 | AI40: 78 | AJ40: 284 | AK40: 0 | AL40: 0 | AM40: 132 | AN40: 271 | AO40: 53 | AP40: 10 | AQ40: 1482 | AR40: 3046 | AS40: =Append1[[#This Row],[DAY_MCAR]]+Append1[[#This Row],[DAY_MCAR_MC]]+Append1[[#This Row],[DAY_MCAL]]+Append1[[#This Row],[DAY_MCAL_MC]]+Append1[[#This Row],[DAY_CNTY]]+Append1[[#This Row],[DAY_CNTY_MC]]+Append1[[#This Row],[DAY_THRD]]+Append1[[#This Row],[DAY_THRD_MC]]+Append1[[#This Row],[DAY_INDGNT]]+Append1[[#This Row],[DAY_OTH]]+Append1[[#This Row],[DAY_TOT]]+Append1[[#This Row],[DAY_LTC]] -> 6010 | AT40: 2671 | AU40: 195 | AV40: 575 | AW40: 2292 | AX40: 0 | AY40: 0 | AZ40: 819 | BA40: 2857 | BB40: 221 | BC40: 905 | BD40: 10535 | BE40: 12284901 | BF40: 2029440 | BG40: 3481451 | BH40: 5062630 | BI40: 0 | BJ40: 0 | BK40: 3823463 | BL40: 6809278 | BM40: 2227365 | BN40: 160301 | BO40: 35878829 | BP40: 14423486 | BQ40: 1457711 | BR40: 2920159 | BS40: 12391193 | BT40: 0 | BU40: 0 | BV40: 6594599 | BW40: 18409106 | BX40: 2108023 | BY40: 2145611 | BZ40: 60449888 | CA40: 3008905 | CB40: 23503381 | CC40: 2964079 | CD40: 5377353 | CE40: 15184826 | CF40: 0 | CG40: 0 | CH40: 0 | CI40: 4375586 | CJ40: 7439423 | CK40: 0 | CL40: 760455 | CM40: 0 | CN40: 0 | CO40: 0 | CP40: 995520 | CQ40: 63609528 | CR40: 0 | CS40: 0 | CT40: 0 | CU40: 0 | CV40: 0 | CW40: 3205006 | CX40: 523072 | CY40: 1024257 | CZ40: 2268997 | DA40: 0 | DB40: 0 | DC40: 3033571 | DD40: 17778961 | DE40: 4335388 | DF40: 549937 | DG40: 32719189 | DH40: 6794745 | DI40: 39885923 | DJ40: 0 | DK40: 3830087 | DL40: 0 | DM40: 0 | DN40: 0 | DO40: 0 | DP40: 4110524 | DQ40: 86894126 | DR40: 0 | DS40: 0 | DT40: 0 | DU40: 0 | DV40: 0 | DW40: 0 | DX40: 0 | DY40: 0 | DZ40: 0 | EA40: 0 | EB40: 0 | EC40: 0 | ED40: 0
A41: 106361110 | B41: BEAR VALLEY COMMUNITY HOSPITAL | C41: 20174 | D41: 43009 | E41: 43100 | F41: Open | G41: San Bernardino | H41: 12 | I41: 1217 | J41: District | K41: Comparable | L41: Rural | M41: 909-866-6501 | N41: 41870 GARSTIN DRIVE | O41: BIG BEAR LAKE | P41: 92315 | Q41: JOHN P. FRIEL | R41: 30 | S41: 30 | T41: 26 | U41: 13 | V41: 6 | W41: 8 | X41: 1 | Y41: 0 | Z41: 0 | AA41: 6 | AB41: 1 | AC41: 0 | AD41: 1 | AE41: 36 | AF41: 2 | AG41: 413 | AH41: 13 | AI41: 1425 | AJ41: 2 | AK41: 0 | AL41: 0 | AM41: 12 | AN41: 3 | AO41: 0 | AP41: 2 | AQ41: 1870 | AR41: 1774 | AS41: =Append1[[#This Row],[DAY_MCAR]]+Append1[[#This Row],[DAY_MCAR_MC]]+Append1[[#This Row],[DAY_MCAL]]+Append1[[#This Row],[DAY_MCAL_MC]]+Append1[[#This Row],[DAY_CNTY]]+Append1[[#This Row],[DAY_CNTY_MC]]+Append1[[#This Row],[DAY_THRD]]+Append1[[#This Row],[DAY_THRD_MC]]+Append1[[#This Row],[DAY_INDGNT]]+Append1[[#This Row],[DAY_OTH]]+Append1[[#This Row],[DAY_TOT]]+Append1[[#This Row],[DAY_LTC]] -> 5514 | AT41: 2293 | AU41: 867 | AV41: 6693 | AW41: 391 | AX41: 0 | AY41: 0 | AZ41: 2030 | BA41: 145 | BB41: 0 | BC41: 1173 | BD41: 13592 | BE41: 396456 | BF41: 84976 | BG41: 755102 | BH41: 15872 | BI41: 0 | BJ41: 0 | BK41: 73653 | BL41: 15568 | BM41: 0 | BN41: 11622 | BO41: 1353249 | BP41: 2125240 | BQ41: 1400363 | BR41: 3397054 | BS41: 1007499 | BT41: 0 | BU41: 0 | BV41: 2577481 | BW41: 371408 | BX41: 0 | BY41: 573109 | BZ41: 11452154 | CA41: 480410 | CB41: 1550777 | CC41: 653549 | CD41: 2219475 | CE41: 768322 | CF41: 0 | CG41: 0 | CH41: 0 | CI41: 1325567 | CJ41: 170270 | CK41: 0 | CL41: 0 | CM41: 0 | CN41: 0 | CO41: 0 | CP41: 68145 | CQ41: 7236515 | CR41: 0 | CS41: 0 | CT41: 0 | CU41: 0 | CV41: 0 | CW41: 970919 | CX41: 831790 | CY41: 1932681 | CZ41: 255049 | DA41: 0 | DB41: 0 | DC41: 1325567 | DD41: 216706 | DE41: 0 | DF41: 36176 | DG41: 5568888 | DH41: 98200 | DI41: 6079923 | DJ41: 0 | DK41: 588208 | DL41: 0 | DM41: 0 | DN41: 0 | DO41: 0 | DP41: 721586 | DQ41: 8821570 | DR41: 0 | DS41: 0 | DT41: 0 | DU41: 0 | DV41: 0 | DW41: 0 | DX41: 0 | DY41: 0 | DZ41: 0 | EA41: 0 | EB41: 0 | EC41: 0 | ED41: 0
A42: 106190081 | B42: BEVERLY HOSPITAL | C42: 20174 | D42: 43009 | E42: 43100 | F42: Open | G42: Los Angeles | H42: 11 | I42: 919 | J42: Non Profit Corp. | K42: Comparable | M42: 323-726-1222 | N42: 309 WEST BEVERLY BOULEVARD | O42: MONTEBELLO | P42: 90640 | Q42: ALICE CHENG | R42: 224 | S42: 167 | T42: 120 | U42: 529 | V42: 373 | W42: 275 | X42: 966 | Y42: 0 | Z42: 0 | AA42: 19 | AB42: 204 | AC42: 3 | AD42: 45 | AE42: 2414 | AF42: 0 | AG42: 2875 | AH42: 1272 | AI42: 953 | AJ42: 3575 | AK42: 0 | AL42: 0 | AM42: 46 | AN42: 771 | AO42: 12 | AP42: 119 | AQ42: 9623 | AR42: 0 | AS42: =Append1[[#This Row],[DAY_MCAR]]+Append1[[#This Row],[DAY_MCAR_MC]]+Append1[[#This Row],[DAY_MCAL]]+Append1[[#This Row],[DAY_MCAL_MC]]+Append1[[#This Row],[DAY_CNTY]]+Append1[[#This Row],[DAY_CNTY_MC]]+Append1[[#This Row],[DAY_THRD]]+Append1[[#This Row],[DAY_THRD_MC]]+Append1[[#This Row],[DAY_INDGNT]]+Append1[[#This Row],[DAY_OTH]]+Append1[[#This Row],[DAY_TOT]]+Append1[[#This Row],[DAY_LTC]] -> 19246 | AT42: 1438 | AU42: 1449 | AV42: 1367 | AW42: 4361 | AX42: 0 | AY42: 0 | AZ42: 313 | BA42: 1921 | BB42: 51 | BC42: 1006 | BD42: 11906 | BE42: 20792414 | BF42: 13214217 | BG42: 6309552 | BH42: 22278134 | BI42: 0 | BJ42: 0 | BK42: 154852 | BL42: 6554270 | BM42: 93747 | BN42: 418960 | BO42: 69816146 | BP42: 5648360 | BQ42: 8580637 | BR42: 2388896 | BS42: 12940502 | BT42: 0 | BU42: 0 | BV42: 615438 | BW42: 6080248 | BX42: 242749 | BY42: 1649987 | BZ42: 38146817 | CA42: 1526914 | CB42: 18670464 | CC42: 15714374 | CD42: -26524186 | CE42: 29664721 | CF42: 2180927 | CG42: 0 | CH42: 0 | CI42: 692270 | CJ42: 8534153 | CK42: 0 | CL42: 336496 | CM42: 0 | CN42: 0 | CO42: 0 | CP42: 397660 | CQ42: 51193793 | CR42: 206865 | CS42: 15356727 | CT42: 0 | CU42: 0 | CV42: 15563592 | CW42: 7770310 | CX42: 6287345 | CY42: 33041707 | CZ42: 20910642 | DA42: 0 | DB42: 0 | DC42: 78020 | DD42: 4100365 | DE42: 0 | DF42: 144373 | DG42: 72332762 | DH42: 213221 | DI42: 60261283 | DJ42: 1374113 | DK42: 137294 | DL42: 0 | DM42: 0 | DN42: 0 | DO42: 0 | DP42: 4172380 | DQ42: 81203099 | DR42: 0 | DS42: 0 | DT42: 0 | DU42: 0 | DV42: 0 | DW42: 0 | DX42: 0 | DY42: 0 | DZ42: 0 | EA42: 0 | EB42: 0 | EC42: 0 | ED42: 0
A43: 106190020 | B43: BHC ALHAMBRA HOSPITAL | C43: 20174 | D43: 43009 | E43: 43100 | F43: Open | G43: Los Angeles | H43: 11 | I43: 913 | J43: Investor - Corp. | K43: Comparable | M43: 626-286-1191 | N43: 4619 ROSEMEAD BOULEVARD | O43: ROSEMEAD | P43: 91770 | Q43: MARGARET MINNICK | R43: 97 | S43: 97 | T43: 97 | U43: 83 | V43: 23 | W43: 238 | X43: 0 | Y43: 0 | Z43: 0 | AA43: 12 | AB43: 980 | AC43: 7 | AD43: 0 | AE43: 1343 | AF43: 31 | AG43: 913 | AH43: 273 | AI43: 1438 | AJ43: 0 | AK43: 0 | AL43: 0 | AM43: 350 | AN43: 5243 | AO43: 26 | AP43: 0 | AQ43: 8243 | AR43: 957 | AS43: =Append1[[#This Row],[DAY_MCAR]]+Append1[[#This Row],[DAY_MCAR_MC]]+Append1[[#This Row],[DAY_MCAL]]+Append1[[#This Row],[DAY_MCAL_MC]]+Append1[[#This Row],[DAY_CNTY]]+Append1[[#This Row],[DAY_CNTY_MC]]+Append1[[#This Row],[DAY_THRD]]+Append1[[#This Row],[DAY_THRD_MC]]+Append1[[#This Row],[DAY_INDGNT]]+Append1[[#This Row],[DAY_OTH]]+Append1[[#This Row],[DAY_TOT]]+Append1[[#This Row],[DAY_LTC]] -> 17443 | AT43: 3529 | AU43: 0 | AV43: 0 | AW43: 0 | AX43: 0 | AY43: 0 | AZ43: 0 | BA43: 971 | BB43: 0 | BC43: 0 | BD43: 4500 | BE43: 1460800 | BF43: 436800 | BG43: 2299200 | BH43: 0 | BI43: 0 | BJ43: 0 | BK43: 560000 | BL43: 8403950 | BM43: 41600 | BN43: 0 | BO43: 13202350 | BP43: 1789200 | BQ43: 0 | BR43: 0 | BS43: 0 | BT43: 0 | BU43: 0 | BV43: 0 | BW43: 676050 | BX43: 0 | BY43: 0 | BZ43: 2465250 | CA43: 230952 | CB43: 1546334 | CC43: 164651 | CD43: 1245395 | CE43: 0 | CF43: 0 | CG43: 0 | CH43: 0 | CI43: 166384 | CJ43: 3059283 | CK43: 0 | CL43: 41600 | CM43: 0 | CN43: 0 | CO43: 0 | CP43: 0 | CQ43: 6454599 | CR43: 0 | CS43: 0 | CT43: 0 | CU43: 0 | CV43: 0 | CW43: 1661873 | CX43: 265353 | CY43: 1027551 | CZ43: 0 | DA43: 0 | DB43: 0 | DC43: 383530 | DD43: 5874694 | DE43: 0 | DF43: 0 | DG43: 9213001 | DH43: 4215 | DI43: 5854767 | DJ43: 200665 | DK43: 19071 | DL43: 0 | DM43: 0 | DN43: 0 | DO43: 0 | DP43: 106614 | DQ43: 7892297 | DR43: 0 | DS43: 0 | DT43: 0 | DU43: 0 | DV43: 0 | DW43: 0 | DX43: 0 | DY43: 0 | DZ43: 0 | EA43: 0 | EB43: 0 | EC43: 0 | ED43: 0
A44: 106044006 | B44: BUTTE COUNTY MENTAL HEALTH - PHF | C44: 20174 | D44: 43009 | E44: 43100 | F44: Open | G44: Butte | H44: 1 | I44: 219 | J44: City/County | K44: Psychiatric Health Facilities | M44: 530-891-2775 | N44: 592 RIO LINDO AVENUE | O44: CHICO | P44: 95926 | Q44: DORIAN KITTRELL | R44: 16 | S44: 16 | T44: 16 | U44: 0 | V44: 0 | W44: 0 | X44: 0 | Y44: 0 | Z44: 0 | AA44: 90 | AB44: 0 | AC44: 0 | AD44: 0 | AE44: 90 | AF44: 0 | AG44: 0 | AH44: 0 | AI44: 0 | AJ44: 0 | AK44: 0 | AL44: 0 | AM44: 1397 | AN44: 0 | AO44: 0 | AP44: 0 | AQ44: 1397 | AR44: 0 | AS44: =Append1[[#This Row],[DAY_MCAR]]+Append1[[#This Row],[DAY_MCAR_MC]]+Append1[[#This Row],[DAY_MCAL]]+Append1[[#This Row],[DAY_MCAL_MC]]+Append1[[#This Row],[DAY_CNTY]]+Append1[[#This Row],[DAY_CNTY_MC]]+Append1[[#This Row],[DAY_THRD]]+Append1[[#This Row],[DAY_THRD_MC]]+Append1[[#This Row],[DAY_INDGNT]]+Append1[[#This Row],[DAY_OTH]]+Append1[[#This Row],[DAY_TOT]]+Append1[[#This Row],[DAY_LTC]] -> 2794 | AT44: 0 | AU44: 0 | AV44: 0 | AW44: 0 | AX44: 0 | AY44: 0 | AZ44: 0 | BA44: 0 | BB44: 0 | BC44: 0 | BD44: 0 | BE44: 0 | BF44: 0 | BG44: 0 | BH44: 0 | BI44: 0 | BJ44: 0 | BK44: 402669 | BL44: 0 | BM44: 0 | BN44: 0 | BO44: 402669 | BP44: 0 | BQ44: 0 | BR44: 0 | BS44: 0 | BT44: 0 | BU44: 0 | BV44: 0 | BW44: 0 | BX44: 0 | BY44: 0 | BZ44: 0 | CA44: 0 | CB44: 0 | CC44: 0 | CD44: 0 | CE44: 0 | CF44: -5269 | CG44: 0 | CH44: 0 | CI44: 0 | CJ44: 0 | CK44: 0 | CL44: 0 | CM44: 0 | CN44: 0 | CO44: 0 | CP44: 0 | CQ44: -5269 | CR44: 0 | CS44: 0 | CT44: 0 | CU44: 0 | CV44: 0 | CW44: 0 | CX44: 0 | CY44: 0 | CZ44: 0 | DA44: 0 | DB44: 0 | DC44: 407938 | DD44: 0 | DE44: 0 | DF44: 0 | DG44: 407938 | DH44: 0 | DI44: 1317753 | DJ44: 0 | DK44: 0 | DL44: 0 | DM44: 0 | DN44: 0 | DO44: 0 | DP44: 0 | DQ44: 0 | DR44: 0 | DS44: 0 | DT44: 0 | DU44: 0 | DV44: 0 | DW44: 0 | DX44: 0 | DY44: 0 | DZ44: 0 | EA44: 0 | EB44: 0 | EC44: 0 | ED44: 0
A45: 106190125 | B45: CALIFORNIA HOSPITAL MEDICAL CENTER | C45: 20174 | D45: 43009 | E45: 43100 | F45: Open | G45: Los Angeles | H45: 11 | I45: 925 | J45: Non Profit Corp. | K45: Comparable | L45: Teaching | M45: 213-748-2411 | N45: 1401 SOUTH GRAND AVENUE | O45: LOS ANGELES | P45: 90015 | Q45: MARGARET PETERSEN | R45: 318 | S45: 243 | T45: 225 | U45: 449 | V45: 384 | W45: 1028 | X45: 2483 | Y45: 0 | Z45: 0 | AA45: 15 | AB45: 239 | AC45: 13 | AD45: 23 | AE45: 4634 | AF45: 0 | AG45: 2135 | AH45: 1554 | AI45: 4731 | AJ45: 9339 | AK45: 0 | AL45: 0 | AM45: 101 | AN45: 778 | AO45: 83 | AP45: 98 | AQ45: 18819 | AR45: 0 | AS45: =Append1[[#This Row],[DAY_MCAR]]+Append1[[#This Row],[DAY_MCAR_MC]]+Append1[[#This Row],[DAY_MCAL]]+Append1[[#This Row],[DAY_MCAL_MC]]+Append1[[#This Row],[DAY_CNTY]]+Append1[[#This Row],[DAY_CNTY_MC]]+Append1[[#This Row],[DAY_THRD]]+Append1[[#This Row],[DAY_THRD_MC]]+Append1[[#This Row],[DAY_INDGNT]]+Append1[[#This Row],[DAY_OTH]]+Append1[[#This Row],[DAY_TOT]]+Append1[[#This Row],[DAY_LTC]] -> 37638 | AT45: 1380 | AU45: 1054 | AV45: 5295 | AW45: 14724 | AX45: 0 | AY45: 0 | AZ45: 338 | BA45: 1362 | BB45: 652 | BC45: 1222 | BD45: 26027 | BE45: 31485654 | BF45: 22686456 | BG45: 62344163 | BH45: 117241111 | BI45: 0 | BJ45: 0 | BK45: 890791 | BL45: 12118165 | BM45: 306495 | BN45: 533100 | BO45: 247605935 | BP45: 9648056 | BQ45: 6424603 | BR45: 24769271 | BS45: 70271251 | BT45: 0 | BU45: 0 | BV45: 1617977 | BW45: 9445301 | BX45: 3177304 | BY45: 1543974 | BZ45: 126897737 | CA45: 7584924 | CB45: 29847589 | CC45: 20044493 | CD45: -6707199 | CE45: 158894776 | CF45: -10302524 | CG45: -28693 | CH45: 0 | CI45: 1864194 | CJ45: 9432441 | CK45: 0 | CL45: 5919475 | CM45: 0 | CN45: 0 | CO45: 0 | CP45: -513506 | CQ45: 216035970 | CR45: 626992 | CS45: 14149092 | CT45: 0 | CU45: 0 | CV45: 14776084 | CW45: 10669652 | CX45: 9527017 | CY45: 94997656 | CZ45: 46141964 | DA45: 0 | DB45: 0 | DC45: 586866 | DD45: 11142827 | DE45: 0 | DF45: 177804 | DG45: 173243786 | DH45: 6509804 | DI45: 124154847 | DJ45: 0 | DK45: 315480 | DL45: 0 | DM45: 0 | DN45: 0 | DO45: 0 | DP45: 3593343 | DQ45: 74521537 | DR45: 0 | DS45: 0 | DT45: 0 | DU45: 0 | DV45: 0 | DW45: 0 | DX45: 0 | DY45: 0 | DZ45: 0 | EA45: 0 | EB45: 0 | EC45: 0 | ED45: 0
A46: 106380929 | B46: CALIFORNIA PACIFIC MEDICAL CENTER | C46: 20174 | D46: 43009 | E46: 43100 | F46: Open | G46: San Francisco | H46: 4 | I46: 423 | J46: Non Profit Corp. | K46: Comparable | M46: 415-600-6000 | N46: 2333 BUCHANAN STREET | O46: SAN FRANCISCO | P46: 94115 | Q46: WARREN BROWNER, MD | R46: 643 | S46: 643 | T46: 436 | U46: 1866 | V46: 644 | W46: 307 | X46: 757 | Y46: 0 | Z46: 1 | AA46: 141 | AB46: 2265 | AC46: 36 | AD46: 80 | AE46: 6097 | AF46: 0 | AG46: 11560 | AH46: 4307 | AI46: 2322 | AJ46: 4328 | AK46: 0 | AL46: 4 | AM46: 1061 | AN46: 10213 | AO46: 129 | AP46: 257 | AQ46: 34181 | AR46: 0 | AS46: =Append1[[#This Row],[DAY_MCAR]]+Append1[[#This Row],[DAY_MCAR_MC]]+Append1[[#This Row],[DAY_MCAL]]+Append1[[#This Row],[DAY_MCAL_MC]]+Append1[[#This Row],[DAY_CNTY]]+Append1[[#This Row],[DAY_CNTY_MC]]+Append1[[#This Row],[DAY_THRD]]+Append1[[#This Row],[DAY_THRD_MC]]+Append1[[#This Row],[DAY_INDGNT]]+Append1[[#This Row],[DAY_OTH]]+Append1[[#This Row],[DAY_TOT]]+Append1[[#This Row],[DAY_LTC]] -> 68362 | AT46: 5154 | AU46: 1460 | AV46: 384 | AW46: 3586 | AX46: 6 | AY46: 0 | AZ46: 348 | BA46: 8974 | BB46: 699 | BC46: 2629 | BD46: 23240 | BE46: 187515544 | BF46: 65449646 | BG46: 31391622 | BH46: 67686237 | BI46: 0 | BJ46: 63092 | BK46: 17678069 | BL46: 184899187 | BM46: 2833430 | BN46: 6165731 | BO46: 563682558 | BP46: 84648084 | BQ46: 27426435 | BR46: 3428324 | BS46: 32317581 | BT46: 28224 | BU46: 0 | BV46: 5857269 | BW46: 138364271 | BX46: 3787079 | BY46: 14770118 | BZ46: 310627385 | CA46: 6191 | CB46: 214362011 | CC46: 76014782 | CD46: -32976973 | CE46: 84863956 | CF46: 0 | CG46: 0 | CH46: 57929 | CI46: 19214734 | CJ46: 138545093 | CK46: 0 | CL46: 6620509 | CM46: 0 | CN46: 0 | CO46: 0 | CP46: 17397375 | CQ46: 524105607 | CR46: 0 | CS46: 7399112 | CT46: 0 | CU46: 4464463 | CV46: 11863575 | CW46: 57801617 | CX46: 16861299 | CY46: 67796919 | CZ46: 22538974 | DA46: 28224 | DB46: 5163 | DC46: 4320604 | DD46: 189182828 | DE46: 0 | DF46: 3532283 | DG46: 362067911 | DH46: 6499345 | DI46: 319376672 | DJ46: 0 | DK46: 20070940 | DL46: 0 | DM46: 0 | DN46: 0 | DO46: 0 | DP46: 156792982 | DQ46: 2039504383 | DR46: 0 | DS46: 0 | DT46: 0 | DU46: 0 | DV46: 0 | DW46: 0 | DX46: 0 | DY46: 0 | DZ46: 0 | EA46: 0 | EB46: 0 | EC46: 0 | ED46: 0
A47: 106380964 | B47: CALIFORNIA PACIFIC MEDICAL CENTER - ST LUKES CAMPUS | C47: 20174 | D47: 43009 | E47: 43100 | F47: Open | G47: San Francisco | H47: 4 | I47: 423 | J47: Non Profit Corp. | K47: Comparable | M47: 415-600-6000 | N47: 3555 CESAR CHAVEZ STREET | O47: SAN FRANCISCO | P47: 94110 | Q47: WARREN BROWNER | R47: 174 | S47: 174 | T47: 83 | U47: 220 | V47: 96 | W47: 133 | X47: 219 | Y47: 0 | Z47: 0 | AA47: 5 | AB47: 154 | AC47: 16 | AD47: 11 | AE47: 854 | AF47: 0 | AG47: 2660 | AH47: 691 | AI47: 1024 | AJ47: 1105 | AK47: 0 | AL47: 0 | AM47: 29 | AN47: 447 | AO47: 64 | AP47: 23 | AQ47: 6043 | AR47: 0 | AS47: =Append1[[#This Row],[DAY_MCAR]]+Append1[[#This Row],[DAY_MCAR_MC]]+Append1[[#This Row],[DAY_MCAL]]+Append1[[#This Row],[DAY_MCAL_MC]]+Append1[[#This Row],[DAY_CNTY]]+Append1[[#This Row],[DAY_CNTY_MC]]+Append1[[#This Row],[DAY_THRD]]+Append1[[#This Row],[DAY_THRD_MC]]+Append1[[#This Row],[DAY_INDGNT]]+Append1[[#This Row],[DAY_OTH]]+Append1[[#This Row],[DAY_TOT]]+Append1[[#This Row],[DAY_LTC]] -> 12086 | AT47: 1035 | AU47: 316 | AV47: 728 | AW47: 2784 | AX47: 0 | AY47: 0 | AZ47: 108 | BA47: 1608 | BB47: 383 | BC47: 134 | BD47: 7096 | BE47: 29393967 | BF47: 8640413 | BG47: 11921753 | BH47: 12918111 | BI47: 0 | BJ47: 0 | BK47: 349025 | BL47: 7202899 | BM47: 756914 | BN47: 297187 | BO47: 71480269 | BP47: 7243542 | BQ47: 3000584 | BR47: 2198556 | BS47: 11058788 | BT47: 0 | BU47: 0 | BV47: 906508 | BW47: 10034286 | BX47: 1776738 | BY47: 625129 | BZ47: 36844131 | CA47: 840673 | CB47: 32697732 | CC47: 9080682 | CD47: -17794749 | CE47: 21300661 | CF47: 0 | CG47: 0 | CH47: 0 | CI47: 830814 | CJ47: 8493751 | CK47: 0 | CL47: 2533652 | CM47: 0 | CN47: 0 | CO47: 0 | CP47: 81643 | CQ47: 58064859 | CR47: 0 | CS47: 0 | CT47: 0 | CU47: 0 | CV47: 0 | CW47: 3939777 | CX47: 2560315 | CY47: 31915058 | CZ47: 2676238 | DA47: 0 | DB47: 0 | DC47: 424719 | DD47: 8743434 | DE47: 0 | DF47: 0 | DG47: 50259541 | DH47: 660898 | DI47: 52369909 | DJ47: 0 | DK47: 31746 | DL47: 0 | DM47: 0 | DN47: 0 | DO47: 0 | DP47: 46639077 | DQ47: 450561762 | DR47: 0 | DS47: 0 | DT47: 0 | DU47: 0 | DV47: 0 | DW47: 0 | DX47: 0 | DY47: 0 | DZ47: 0 | EA47: 0 | EB47: 0 | EC47: 0 | ED47: 0
A48: 106190155 | B48: CALIFORNIA REHABILITATION INSTITUTE | C48: 20174 | D48: 43009 | E48: 43100 | F48: Open | G48: Los Angeles | H48: 11 | I48: 927 | J48: Investor - Corp. | K48: Comparable | M48: 424-522-7100 | N48: 2070 CENTURY PARK EAST | O48: LOS ANGELES | P48: 90067 | Q48: SCOTT ROTSTED | R48: 138 | S48: 138 | T48: 87 | U48: 415 | V48: 16 | W48: 2 | X48: 1 | Y48: 0 | Z48: 0 | AA48: 150 | AB48: 0 | AC48: 0 | AD48: 6 | AE48: 590 | AF48: 590 | AG48: 5204 | AH48: 287 | AI48: 17 | AJ48: 13 | AK48: 0 | AL48: 0 | AM48: 1967 | AN48: 0 | AO48: 0 | AP48: 95 | AQ48: 7583 | AR48: 7583 | AS48: =Append1[[#This Row],[DAY_MCAR]]+Append1[[#This Row],[DAY_MCAR_MC]]+Append1[[#This Row],[DAY_MCAL]]+Append1[[#This Row],[DAY_MCAL_MC]]+Append1[[#This Row],[DAY_CNTY]]+Append1[[#This Row],[DAY_CNTY_MC]]+Append1[[#This Row],[DAY_THRD]]+Append1[[#This Row],[DAY_THRD_MC]]+Append1[[#This Row],[DAY_INDGNT]]+Append1[[#This Row],[DAY_OTH]]+Append1[[#This Row],[DAY_TOT]]+Append1[[#This Row],[DAY_LTC]] -> 22749 | AT48: 0 | AU48: 0 | AV48: 0 | AW48: 0 | AX48: 0 | AY48: 0 | AZ48: 0 | BA48: 0 | BB48: 0 | BC48: 0 | BD48: 0 | BE48: 29336576 | BF48: 1618962 | BG48: 99033 | BH48: 68594 | BI48: 0 | BJ48: 0 | BK48: 10925884 | BL48: 0 | BM48: 0 | BN48: 551704 | BO48: 42600753 | BP48: 0 | BQ48: 0 | BR48: 0 | BS48: 0 | BT48: 0 | BU48: 0 | BV48: 0 | BW48: 0 | BX48: 0 | BY48: 0 | BZ48: 0 | CA48: 509174 | CB48: 13487520 | CC48: 1136730 | CD48: 78436 | CE48: 63679 | CF48: 0 | CG48: 0 | CH48: 0 | CI48: 2092514 | CJ48: 0 | CK48: 0 | CL48: 0 | CM48: 0 | CN48: 0 | CO48: 0 | CP48: 283170 | CQ48: 17651223 | CR48: 0 | CS48: 0 | CT48: 0 | CU48: 0 | CV48: 0 | CW48: 15849056 | CX48: 482232 | CY48: 20597 | CZ48: 4915 | DA48: 0 | DB48: 0 | DC48: 8324196 | DD48: 0 | DE48: 0 | DF48: 268534 | DG48: 24949530 | DH48: 17480 | DI48: 19077266 | DJ48: 0 | DK48: 0 | DL48: 0 | DM48: 0 | DN48: 0 | DO48: 0 | DP48: 37340 | DQ48: 7962685 | DR48: 0 | DS48: 0 | DT48: 0 | DU48: 0 | DV48: 0 | DW48: 0 | DX48: 0 | DY48: 0 | DZ48: 0 | EA48: 0 | EB48: 0 | EC48: 0 | ED48: 0
A49: 106364050 | B49: CANYON RIDGE HOSPITAL | C49: 20174 | D49: 43009 | E49: 43100 | F49: Open | G49: San Bernardino | H49: 12 | I49: 1207 | J49: Investor - Corp. | K49: Comparable | M49: 909-590-3700 | N49: 5353 G STREET | O49: CHINO | P49: 91710 | Q49: STEPHANIE BERNIER | R49: 106 | S49: 106 | T49: 103 | U49: 191 | V49: 118 | W49: 0 | X49: 200 | Y49: 0 | Z49: 93 | AA49: 36 | AB49: 791 | AC49: 16 | AD49: 0 | AE49: 1445 | AF49: 0 | AG49: 1799 | AH49: 902 | AI49: 0 | AJ49: 946 | AK49: 0 | AL49: 386 | AM49: 188 | AN49: 4411 | AO49: 59 | AP49: 0 | AQ49: 8691 | AR49: 0 | AS49: =Append1[[#This Row],[DAY_MCAR]]+Append1[[#This Row],[DAY_MCAR_MC]]+Append1[[#This Row],[DAY_MCAL]]+Append1[[#This Row],[DAY_MCAL_MC]]+Append1[[#This Row],[DAY_CNTY]]+Append1[[#This Row],[DAY_CNTY_MC]]+Append1[[#This Row],[DAY_THRD]]+Append1[[#This Row],[DAY_THRD_MC]]+Append1[[#This Row],[DAY_INDGNT]]+Append1[[#This Row],[DAY_OTH]]+Append1[[#This Row],[DAY_TOT]]+Append1[[#This Row],[DAY_LTC]] -> 17382 | AT49: 1667 | AU49: 0 | AV49: 0 | AW49: 0 | AX49: 0 | AY49: 0 | AZ49: 0 | BA49: 1142 | BB49: 0 | BC49: 0 | BD49: 2809 | BE49: 3238200 | BF49: 1623600 | BG49: 0 | BH49: 1702800 | BI49: 0 | BJ49: 694800 | BK49: 338400 | BL49: 7945833 | BM49: 106200 | BN49: 0 | BO49: 15649833 | BP49: 1275540 | BQ49: 0 | BR49: 0 | BS49: 0 | BT49: 0 | BU49: 0 | BV49: 0 | BW49: 795780 | BX49: 0 | BY49: 0 | BZ49: 2071320 | CA49: 271801 | CB49: 2479159 | CC49: 806643 | CD49: 0 | CE49: 977862 | CF49: 0 | CG49: 0 | CH49: 398553 | CI49: 215811 | CJ49: 4301988 | CK49: 0 | CL49: 106200 | CM49: 0 | CN49: 0 | CO49: 0 | CP49: 0 | CQ49: 9558017 | CR49: 0 | CS49: 0 | CT49: 0 | CU49: 0 | CV49: 0 | CW49: 1968986 | CX49: 790648 | CY49: 0 | CZ49: 700984 | DA49: 0 | DB49: 286749 | DC49: 118555 | DD49: 4297214 | DE49: 0 | DF49: 0 | DG49: 8163136 | DH49: 3966 | DI49: 4837969 | DJ49: 159685 | DK49: 6782 | DL49: 0 | DM49: 0 | DN49: 0 | DO49: 0 | DP49: 113157 | DQ49: 12822215 | DR49: 0 | DS49: 0 | DT49: 0 | DU49: 0 | DV49: 0 | DW49: 0 | DX49: 0 | DY49: 0 | DZ49: 0 | EA49: 0 | EB49: 0 | EC49: 0 | ED49: 0
A50: 106190137 | B50: CASA COLINA HOSPITAL AND CENTER FOR HEALTH CARE | C50: 20174 | D50: 43009 | E50: 43100 | F50: Open | G50: Los Angeles | H50: 11 | I50: 917 | J50: Non Profit Corp. | K50: Comparable | M50: 909-596-7733 | N50: 255 EAST BONITA AVENUE | O50: POMONA | P50: 91767 | Q50: FELICE L LOVERSO | R50: 99 | S50: 99 | T50: 99 | U50: 349 | V50: 74 | W50: 11 | X50: 33 | Y50: 0 | Z50: 0 | AA50: 117 | AB50: 83 | AC50: 0 | AD50: 3 | AE50: 670 | AF50: 0 | AG50: 3261 | AH50: 511 | AI50: 186 | AJ50: 263 | AK50: 0 | AL50: 0 | AM50: 1321 | AN50: 899 | AO50: 0 | AP50: 54 | AQ50: 6495 | AR50: 0 | AS50: =Append1[[#This Row],[DAY_MCAR]]+Append1[[#This Row],[DAY_MCAR_MC]]+Append1[[#This Row],[DAY_MCAL]]+Append1[[#This Row],[DAY_MCAL_MC]]+Append1[[#This Row],[DAY_CNTY]]+Append1[[#This Row],[DAY_CNTY_MC]]+Append1[[#This Row],[DAY_THRD]]+Append1[[#This Row],[DAY_THRD_MC]]+Append1[[#This Row],[DAY_INDGNT]]+Append1[[#This Row],[DAY_OTH]]+Append1[[#This Row],[DAY_TOT]]+Append1[[#This Row],[DAY_LTC]] -> 12990 | AT50: 8585 | AU50: 1160 | AV50: 138 | AW50: 1696 | AX50: 0 | AY50: 0 | AZ50: 8947 | BA50: 3850 | BB50: 0 | BC50: 2170 | BD50: 26546 | BE50: 17757278 | BF50: 4529432 | BG50: 652118 | BH50: 1589419 | BI50: 0 | BJ50: 0 | BK50: 9362151 | BL50: 5253812 | BM50: 0 | BN50: 307156 | BO50: 39451366 | BP50: 2582138 | BQ50: 477366 | BR50: 41212 | BS50: 661003 | BT50: 0 | BU50: 0 | BV50: 2971215 | BW50: 1151820 | BX50: 0 | BY50: 922750 | BZ50: 8807504 | CA50: 336616 | CB50: 12429284 | CC50: 935544 | CD50: 658202 | CE50: 1604248 | CF50: 0 | CG50: 0 | CH50: 0 | CI50: 7125605 | CJ50: 4757746 | CK50: 0 | CL50: 0 | CM50: 0 | CN50: 0 | CO50: 0 | CP50: 3409963 | CQ50: 31257208 | CR50: 0 | CS50: 0 | CT50: 0 | CU50: 0 | CV50: 0 | CW50: 7573516 | CX50: 4071254 | CY50: 35128 | CZ50: 646174 | DA50: 0 | DB50: 0 | DC50: 5207761 | DD50: 1647886 | DE50: 0 | DF50: -2180057 | DG50: 17001662 | DH50: 327397 | DI50: 18230718 | DJ50: 0 | DK50: 1185093 | DL50: 0 | DM50: 0 | DN50: 0 | DO50: 0 | DP50: 664756 | DQ50: 86561107 | DR50: 0 | DS50: 0 | DT50: 0 | DU50: 0 | DV50: 0 | DW50: 0 | DX50: 0 | DY50: 0 | DZ50: 0 | EA50: 0 | EB50: 0 | EC50: 0 | ED50: 0
A51: 106190045 | B51: CATALINA ISLAND MEDICAL CENTER | C51: 20174 | D51: 43009 | E51: 43100 | F51: Open | G51: Los Angeles | H51: 11 | I51: 933 | J51: Non Profit Corp. | K51: Comparable | L51: Rural | M51: 310-510-0700 | N51: 100 FALLS CANYON ROAD | O51: AVALON | P51: 90704 | Q51: JASON PARET | R51: 12 | S51: 12 | T51: 12 | U51: 5 | V51: 0 | W51: 0 | X51: 0 | Y51: 0 | Z51: 0 | AA51: 0 | AB51: 0 | AC51: 0 | AD51: 0 | AE51: 5 | AF51: 0 | AG51: 153 | AH51: 0 | AI51: 552 | AJ51: 0 | AK51: 0 | AL51: 0 | AM51: 0 | AN51: 0 | AO51: 0 | AP51: 0 | AQ51: 705 | AR51: 0 | AS51: =Append1[[#This Row],[DAY_MCAR]]+Append1[[#This Row],[DAY_MCAR_MC]]+Append1[[#This Row],[DAY_MCAL]]+Append1[[#This Row],[DAY_MCAL_MC]]+Append1[[#This Row],[DAY_CNTY]]+Append1[[#This Row],[DAY_CNTY_MC]]+Append1[[#This Row],[DAY_THRD]]+Append1[[#This Row],[DAY_THRD_MC]]+Append1[[#This Row],[DAY_INDGNT]]+Append1[[#This Row],[DAY_OTH]]+Append1[[#This Row],[DAY_TOT]]+Append1[[#This Row],[DAY_LTC]] -> 1410 | AT51: 952 | AU51: 0 | AV51: 986 | AW51: 0 | AX51: 0 | AY51: 0 | AZ51: 1251 | BA51: 0 | BB51: 0 | BC51: 255 | BD51: 3444 | BE51: 485181 | BF51: 0 | BG51: 339480 | BH51: 0 | BI51: 0 | BJ51: 0 | BK51: 0 | BL51: 0 | BM51: 0 | BN51: 0 | BO51: 824661 | BP51: 1030258 | BQ51: 0 | BR51: 995147 | BS51: 0 | BT51: 0 | BU51: 0 | BV51: 1365615 | BW51: 0 | BX51: 0 | BY51: 198254 | BZ51: 3589274 | CA51: 312623 | CB51: 312541 | CC51: 0 | CD51: 565127 | CE51: 0 | CF51: 0 | CG51: 0 | CH51: 0 | CI51: 732954 | CJ51: 0 | CK51: 0 | CL51: 27095 | CM51: 0 | CN51: 0 | CO51: 0 | CP51: 43863 | CQ51: 1994203 | CR51: 0 | CS51: 0 | CT51: 0 | CU51: 0 | CV51: 0 | CW51: 1202898 | CX51: 0 | CY51: 769500 | CZ51: 0 | DA51: 0 | DB51: 0 | DC51: 632661 | DD51: 0 | DE51: 0 | DF51: -185327 | DG51: 2419732 | DH51: 269106 | DI51: 2482551 | DJ51: 0 | DK51: 0 | DL51: 0 | DM51: 0 | DN51: 0 | DO51: 0 | DP51: 120096 | DQ51: 2240202 | DR51: 0 | DS51: 0 | DT51: 0 | DU51: 0 | DV51: 0 | DW51: 0 | DX51: 0 | DY51: 0 | DZ51: 0 | EA51: 0 | EB51: 0 | EC51: 0 | ED51: 0
A52: 106190555 | B52: CEDARS-SINAI MEDICAL CENTER | C52: 20174 | D52: 43009 | E52: 43100 | F52: Open | G52: Los Angeles | H52: 11 | I52: 925 | J52: Non Profit Corp. | K52: Comparable | L52: Teaching | M52: 310-423-5000 | N52: 8700 BEVERLY BOULEVARD | O52: LOS ANGELES | P52: 90048 | Q52: THOMAS M. PRISELAC | R52: 886 | S52: 885 | T52: 885 | U52: 5265 | V52: 458 | W52: 698 | X52: 802 | Y52: 0 | Z52: 0 | AA52: 277 | AB52: 4786 | AC52: 0 | AD52: 430 | AE52: 12716 | AF52: 0 | AG52: 30310 | AH52: 2822 | AI52: 4223 | AJ52: 4260 | AK52: 0 | AL52: 0 | AM52: 999 | AN52: 21452 | AO52: 0 | AP52: 1756 | AQ52: 65822 | AR52: 0 | AS52: =Append1[[#This Row],[DAY_MCAR]]+Append1[[#This Row],[DAY_MCAR_MC]]+Append1[[#This Row],[DAY_MCAL]]+Append1[[#This Row],[DAY_MCAL_MC]]+Append1[[#This Row],[DAY_CNTY]]+Append1[[#This Row],[DAY_CNTY_MC]]+Append1[[#This Row],[DAY_THRD]]+Append1[[#This Row],[DAY_THRD_MC]]+Append1[[#This Row],[DAY_INDGNT]]+Append1[[#This Row],[DAY_OTH]]+Append1[[#This Row],[DAY_TOT]]+Append1[[#This Row],[DAY_LTC]] -> 131644 | AT52: 70045 | AU52: 6030 | AV52: 6238 | AW52: 7203 | AX52: 0 | AY52: 0 | AZ52: 5016 | BA52: 94822 | BB52: 279 | BC52: 28775 | BD52: 218408 | BE52: 1288611708 | BF52: 142554822 | BG52: 147415396 | BH52: 172204599 | BI52: 0 | BJ52: 0 | BK52: 39983252 | BL52: 847484762 | BM52: 0 | BN52: 85548936 | BO52: 2723803475 | BP52: 571070580 | BQ52: 46661976 | BR52: 44256076 | BS52: 52356172 | BT52: 0 | BU52: 0 | BV52: 24367610 | BW52: 636548964 | BX52: 292162 | BY52: 83099901 | BZ52: 1458653441 | CA52: -12894307 | CB52: 1678079670 | CC52: 166998739 | CD52: 179113665 | CE52: 197083235 | CF52: 0 | CG52: 0 | CH52: 0 | CI52: 53489454 | CJ52: 1046313327 | CK52: 0 | CL52: 6710814 | CM52: 0 | CN52: 0 | CO52: 0 | CP52: 138566134 | CQ52: 3453460731 | CR52: 4109097 | CS52: 0 | CT52: 0 | CU52: 0 | CV52: 4109097 | CW52: 182634163 | CX52: 26327156 | CY52: 13460408 | CZ52: 27477536 | DA52: 0 | DB52: 0 | DC52: 14020514 | DD52: 442942593 | DE52: 0 | DF52: 26242912 | DG52: 733105282 | DH52: 95491354 | DI52: 754940957 | DJ52: 0 | DK52: 68751825 | DL52: 0 | DM52: 0 | DN52: 0 | DO52: 0 | DP52: 66698727 | DQ52: 2138795097 | DR52: 0 | DS52: 0 | DT52: 0 | DU52: 0 | DV52: 0 | DW52: 0 | DX52: 0 | DY52: 0 | DZ52: 0 | EA52: 0 | EB52: 0 | EC52: 0 | ED52: 0
A53: 106190148 | B53: CENTINELA HOSPITAL MEDICAL CENTER | C53: 20174 | D53: 43009 | E53: 43100 | F53: Open | G53: Los Angeles | H53: 11 | I53: 929 | J53: Investor - Corp. | K53: Comparable | M53: 310-673-4660 | N53: 555 EAST HARDY STREET | O53: INGLEWOOD | P53: 90301 | Q53: LINDA BRADLEY | R53: 369 | S53: 369 | T53: 178 | U53: 1362 | V53: 588 | W53: 335 | X53: 1347 | Y53: 0 | Z53: 0 | AA53: 325 | AB53: 0 | AC53: 0 | AD53: 161 | AE53: 4118 | AF53: 0 | AG53: 6341 | AH53: 1851 | AI53: 2288 | AJ53: 4406 | AK53: 0 | AL53: 0 | AM53: 1003 | AN53: 0 | AO53: 0 | AP53: 292 | AQ53: 16181 | AR53: 0 | AS53: =Append1[[#This Row],[DAY_MCAR]]+Append1[[#This Row],[DAY_MCAR_MC]]+Append1[[#This Row],[DAY_MCAL]]+Append1[[#This Row],[DAY_MCAL_MC]]+Append1[[#This Row],[DAY_CNTY]]+Append1[[#This Row],[DAY_CNTY_MC]]+Append1[[#This Row],[DAY_THRD]]+Append1[[#This Row],[DAY_THRD_MC]]+Append1[[#This Row],[DAY_INDGNT]]+Append1[[#This Row],[DAY_OTH]]+Append1[[#This Row],[DAY_TOT]]+Append1[[#This Row],[DAY_LTC]] -> 32362 | AT53: 1526 | AU53: 747 | AV53: 1273 | AW53: 5706 | AX53: 0 | AY53: 0 | AZ53: 1961 | BA53: 0 | BB53: 0 | BC53: 1813 | BD53: 13026 | BE53: 98928393 | BF53: 29415304 | BG53: 31141869 | BH53: 64361028 | BI53: 0 | BJ53: 0 | BK53: 15897324 | BL53: 0 | BM53: 0 | BN53: 4028826 | BO53: 243772744 | BP53: 9317001 | BQ53: 4510595 | BR53: 3782633 | BS53: 19520798 | BT53: 0 | BU53: 0 | BV53: 5635014 | BW53: 0 | BX53: 0 | BY53: 4921630 | BZ53: 47687671 | CA53: 6747795 | CB53: 81071058 | CC53: 27532753 | CD53: 7412838 | CE53: 54555755 | CF53: -732863 | CG53: 0 | CH53: 0 | CI53: 14936843 | CJ53: 0 | CK53: 0 | CL53: 0 | CM53: 0 | CN53: 0 | CO53: 0 | CP53: 2202663 | CQ53: 193726842 | CR53: 0 | CS53: 0 | CT53: 0 | CU53: 0 | CV53: 0 | CW53: 27174336 | CX53: 6393145 | CY53: 28244527 | CZ53: 29326071 | DA53: 0 | DB53: 0 | DC53: 6595494 | DD53: 0 | DE53: 0 | DF53: 0 | DG53: 97733573 | DH53: 770678 | DI53: 78724036 | DJ53: 0 | DK53: -526959 | DL53: 0 | DM53: 0 | DN53: 0 | DO53: 0 | DP53: 4035849 | DQ53: 151835279 | DR53: 0 | DS53: 0 | DT53: 0 | DU53: 0 | DV53: 0 | DW53: 0 | DX53: 0 | DY53: 0 | DZ53: 0 | EA53: 0 | EB53: 0 | EC53: 0 | ED53: 0
A54: 106105125 | B54: CENTRAL STAR - PHF | C54: 20174 | D54: 43009 | E54: 43100 | F54: Open | G54: Fresno | H54: 9 | I54: 605 | J54: Investor - Corp. | K54: Psychiatric Health Facilities | M54: 559-892-1128 | N54: 4411 E. KINGS CANYON ROAD | O54: FRESNO | P54: 93702 | Q54: DEBORAH TOBIAS-GATEWOOD | R54: 16 | S54: 16 | T54: 13 | U54: 0 | V54: 0 | W54: 148 | X54: 0 | Y54: 0 | Z54: 0 | AA54: 0 | AB54: 0 | AC54: 0 | AD54: 26 | AE54: 174 | AF54: 0 | AG54: 0 | AH54: 0 | AI54: 1006 | AJ54: 0 | AK54: 0 | AL54: 0 | AM54: 0 | AN54: 0 | AO54: 0 | AP54: 180 | AQ54: 1186 | AR54: 0 | AS54: =Append1[[#This Row],[DAY_MCAR]]+Append1[[#This Row],[DAY_MCAR_MC]]+Append1[[#This Row],[DAY_MCAL]]+Append1[[#This Row],[DAY_MCAL_MC]]+Append1[[#This Row],[DAY_CNTY]]+Append1[[#This Row],[DAY_CNTY_MC]]+Append1[[#This Row],[DAY_THRD]]+Append1[[#This Row],[DAY_THRD_MC]]+Append1[[#This Row],[DAY_INDGNT]]+Append1[[#This Row],[DAY_OTH]]+Append1[[#This Row],[DAY_TOT]]+Append1[[#This Row],[DAY_LTC]] -> 2372 | AT54: 0 | AU54: 0 | AV54: 0 | AW54: 0 | AX54: 0 | AY54: 0 | AZ54: 0 | BA54: 0 | BB54: 0 | BC54: 0 | BD54: 0 | BE54: 0 | BF54: 0 | BG54: 755739 | BH54: 0 | BI54: 0 | BJ54: 0 | BK54: 0 | BL54: 0 | BM54: 0 | BN54: 167220 | BO54: 922959 | BP54: 0 | BQ54: 0 | BR54: 0 | BS54: 0 | BT54: 0 | BU54: 0 | BV54: 0 | BW54: 0 | BX54: 0 | BY54: 0 | BZ54: 0 | CA54: 0 | CB54: 0 | CC54: 0 | CD54: 0 | CE54: 0 | CF54: 0 | CG54: 0 | CH54: 0 | CI54: 0 | CJ54: 0 | CK54: 0 | CL54: 0 | CM54: 0 | CN54: 0 | CO54: 0 | CP54: 0 | CQ54: 0 | CR54: 0 | CS54: 0 | CT54: 0 | CU54: 0 | CV54: 0 | CW54: 0 | CX54: 0 | CY54: 755739 | CZ54: 0 | DA54: 0 | DB54: 0 | DC54: 0 | DD54: 0 | DE54: 0 | DF54: 167220 | DG54: 922959 | DH54: 0 | DI54: 2205441 | DJ54: 184879 | DK54: 0 | DL54: 0 | DM54: 0 | DN54: 0 | DO54: 0 | DP54: 0 | DQ54: 0 | DR54: 0 | DS54: 0 | DT54: 0 | DU54: 0 | DV54: 0 | DW54: 0 | DX54: 0 | DY54: 0 | DZ54: 0 | EA54: 0 | EB54: 0 | EC54: 0 | ED54: 0
A55: 106500954 | B55: CENTRAL VALLEY SPECIALTY HOSPITAL | C55: 20174 | D55: 43009 | E55: 43100 | F55: Open | G55: Stanislaus | H55: 6 | I55: 511 | J55: Investor - Corp. | K55: Comparable | M55: 209-248-7700 | N55: 730 17TH STREET | O55: MODESTO | P55: 95354 | Q55: GIA SMITH | R55: 100 | S55: 100 | T55: 100 | U55: 127 | V55: 0 | W55: 5 | X55: 0 | Y55: 0 | Z55: 0 | AA55: 103 | AB55: 0 | AC55: 0 | AD55: 0 | AE55: 235 | AF55: 0 | AG55: 3172 | AH55: 0 | AI55: 252 | AJ55: 0 | AK55: 0 | AL55: 0 | AM55: 3197 | AN55: 0 | AO55: 0 | AP55: 0 | AQ55: 6621 | AR55: 0 | AS55: =Append1[[#This Row],[DAY_MCAR]]+Append1[[#This Row],[DAY_MCAR_MC]]+Append1[[#This Row],[DAY_MCAL]]+Append1[[#This Row],[DAY_MCAL_MC]]+Append1[[#This Row],[DAY_CNTY]]+Append1[[#This Row],[DAY_CNTY_MC]]+Append1[[#This Row],[DAY_THRD]]+Append1[[#This Row],[DAY_THRD_MC]]+Append1[[#This Row],[DAY_INDGNT]]+Append1[[#This Row],[DAY_OTH]]+Append1[[#This Row],[DAY_TOT]]+Append1[[#This Row],[DAY_LTC]] -> 13242 | AT55: 0 | AU55: 0 | AV55: 0 | AW55: 0 | AX55: 0 | AY55: 0 | AZ55: 0 | BA55: 0 | BB55: 0 | BC55: 0 | BD55: 0 | BE55: 21601041 | BF55: 0 | BG55: 884137 | BH55: 0 | BI55: 0 | BJ55: 0 | BK55: 18634660 | BL55: 0 | BM55: 0 | BN55: 0 | BO55: 41119838 | BP55: 0 | BQ55: 0 | BR55: 0 | BS55: 0 | BT55: 0 | BU55: 0 | BV55: 0 | BW55: 0 | BX55: 0 | BY55: 0 | BZ55: 0 | CA55: 0 | CB55: 16179255 | CC55: 0 | CD55: 662222 | CE55: 0 | CF55: 0 | CG55: 0 | CH55: 0 | CI55: 13957424 | CJ55: 0 | CK55: 0 | CL55: 0 | CM55: 0 | CN55: 0 | CO55: 0 | CP55: 0 | CQ55: 30798901 | CR55: 0 | CS55: 0 | CT55: 0 | CU55: 0 | CV55: 0 | CW55: 5421787 | CX55: 0 | CY55: 221915 | CZ55: 0 | DA55: 0 | DB55: 0 | DC55: 4677235 | DD55: 0 | DE55: 0 | DF55: 0 | DG55: 10320937 | DH55: 47425 | DI55: 9902284 | DJ55: 0 | DK55: 0 | DL55: 0 | DM55: 0 | DN55: 0 | DO55: 0 | DP55: 0 | DQ55: 587432 | DR55: 0 | DS55: 0 | DT55: 0 | DU55: 0 | DV55: 0 | DW55: 0 | DX55: 0 | DY55: 0 | DZ55: 0 | EA55: 0 | EB55: 0 | EC55: 0 | ED55: 0
A56: 106301140 | B56: CHAPMAN GLOBAL MEDICAL CENTER | C56: 20174 | D56: 43009 | E56: 43100 | F56: Open | G56: Orange | H56: 13 | I56: 1015 | J56: Investor - Corp. | K56: Comparable | M56: 714-633-0011 | N56: 2601 EAST CHAPMAN AVENUE | O56: ORANGE | P56: 92869 | Q56: SUZANNE RICHARDS | R56: 114 | S56: 100 | T56: 100 | U56: 112 | V56: 80 | W56: 13 | X56: 42 | Y56: 0 | Z56: 0 | AA56: 88 | AB56: 142 | AC56: 0 | AD56: 9 | AE56: 486 | AF56: 0 | AG56: 848 | AH56: 807 | AI56: 35 | AJ56: 2292 | AK56: 0 | AL56: 0 | AM56: 216 | AN56: 431 | AO56: 0 | AP56: 26 | AQ56: 4655 | AR56: 0 | AS56: =Append1[[#This Row],[DAY_MCAR]]+Append1[[#This Row],[DAY_MCAR_MC]]+Append1[[#This Row],[DAY_MCAL]]+Append1[[#This Row],[DAY_MCAL_MC]]+Append1[[#This Row],[DAY_CNTY]]+Append1[[#This Row],[DAY_CNTY_MC]]+Append1[[#This Row],[DAY_THRD]]+Append1[[#This Row],[DAY_THRD_MC]]+Append1[[#This Row],[DAY_INDGNT]]+Append1[[#This Row],[DAY_OTH]]+Append1[[#This Row],[DAY_TOT]]+Append1[[#This Row],[DAY_LTC]] -> 9310 | AT56: 358 | AU56: 252 | AV56: 193 | AW56: 686 | AX56: 0 | AY56: 0 | AZ56: 887 | BA56: 864 | BB56: 0 | BC56: 235 | BD56: 3475 | BE56: 7382895 | BF56: 4127364 | BG56: 482404 | BH56: 12331870 | BI56: 0 | BJ56: 0 | BK56: 5224640 | BL56: 7594349 | BM56: 0 | BN56: 626830 | BO56: 37770352 | BP56: 1408723 | BQ56: 1029220 | BR56: 733389 | BS56: 2216412 | BT56: 0 | BU56: 0 | BV56: 1516374 | BW56: 3619573 | BX56: 0 | BY56: 655476 | BZ56: 11179167 | CA56: 1346527 | CB56: 7160261 | CC56: 4017565 | CD56: 1151839 | CE56: 12458665 | CF56: -44320 | CG56: 0 | CH56: 0 | CI56: 3423049 | CJ56: 8592107 | CK56: 0 | CL56: 0 | CM56: 0 | CN56: 0 | CO56: 0 | CP56: 773964 | CQ56: 38879657 | CR56: 0 | CS56: 0 | CT56: 0 | CU56: 0 | CV56: 0 | CW56: 1631356 | CX56: 1139019 | CY56: 108274 | CZ56: 2089616 | DA56: 0 | DB56: 0 | DC56: 3317966 | DD56: 2621815 | DE56: 0 | DF56: -838184 | DG56: 10069862 | DH56: 28035 | DI56: 10190788 | DJ56: 156675 | DK56: 0 | DL56: 0 | DM56: 0 | DN56: 0 | DO56: 0 | DP56: 0 | DQ56: 2399905 | DR56: 0 | DS56: 0 | DT56: 0 | DU56: 0 | DV56: 0 | DW56: 0 | DX56: 0 | DY56: 0 | DZ56: 0 | EA56: 0 | EB56: 0 | EC56: 0 | ED56: 0
A57: 106010776 | B57: CHILDREN'S HOSPITAL AND RESEARCH CENTER AT OAKLAND | C57: 20174 | D57: 43009 | E57: 43100 | F57: Open | G57: Alameda | H57: 5 | I57: 417 | J57: Non Profit Corp. | K57: Comparable | M57: 510-428-3885 | N57: 747 52ND STREET | O57: OAKLAND | P57: 94609 | Q57: MICHAEL ANDERSON, MD | R57: 190 | S57: 190 | T57: 190 | U57: 8 | V57: 0 | W57: 825 | X57: 760 | Y57: 0 | Z57: 0 | AA57: 0 | AB57: 588 | AC57: 0 | AD57: 16 | AE57: 2197 | AF57: 0 | AG57: 47 | AH57: 0 | AI57: 6118 | AJ57: 1877 | AK57: 0 | AL57: 0 | AM57: 0 | AN57: 2514 | AO57: 0 | AP57: 40 | AQ57: 10596 | AR57: 0 | AS57: =Append1[[#This Row],[DAY_MCAR]]+Append1[[#This Row],[DAY_MCAR_MC]]+Append1[[#This Row],[DAY_MCAL]]+Append1[[#This Row],[DAY_MCAL_MC]]+Append1[[#This Row],[DAY_CNTY]]+Append1[[#This Row],[DAY_CNTY_MC]]+Append1[[#This Row],[DAY_THRD]]+Append1[[#This Row],[DAY_THRD_MC]]+Append1[[#This Row],[DAY_INDGNT]]+Append1[[#This Row],[DAY_OTH]]+Append1[[#This Row],[DAY_TOT]]+Append1[[#This Row],[DAY_LTC]] -> 21192 | AT57: 235 | AU57: 0 | AV57: 15406 | AW57: 31778 | AX57: 0 | AY57: 0 | AZ57: 0 | BA57: 18497 | BB57: 151 | BC57: 2863 | BD57: 68930 | BE57: 641635 | BF57: 0 | BG57: 103309982 | BH57: 29620188 | BI57: 0 | BJ57: 0 | BK57: 0 | BL57: 55312855 | BM57: 0 | BN57: 1001177 | BO57: 189885837 | BP57: 1786779 | BQ57: 0 | BR57: 37055405 | BS57: 54136885 | BT57: 0 | BU57: 0 | BV57: 0 | BW57: 49941140 | BX57: 111040 | BY57: 2477590 | BZ57: 145508839 | CA57: 824882 | CB57: 1458916 | CC57: 0 | CD57: 64648907 | CE57: 70911911 | CF57: -15047654 | CG57: 0 | CH57: 0 | CI57: 0 | CJ57: 58391639 | CK57: 0 | CL57: -1934537 | CM57: 0 | CN57: 0 | CO57: 0 | CP57: 0 | CQ57: 179254064 | CR57: 0 | CS57: 0 | CT57: 0 | CU57: 0 | CV57: 0 | CW57: 969498 | CX57: 0 | CY57: 90764134 | CZ57: 12845162 | DA57: 0 | DB57: 0 | DC57: 0 | DD57: 46862356 | DE57: 111040 | DF57: 4588422 | DG57: 156140612 | DH57: 13446318 | DI57: 157642752 | DJ57: 0 | DK57: 14450000 | DL57: 0 | DM57: 0 | DN57: 0 | DO57: 0 | DP57: 17840000 | DQ57: 312161000 | DR57: 0 | DS57: 0 | DT57: 0 | DU57: 0 | DV57: 0 | DW57: 0 | DX57: 0 | DY57: 0 | DZ57: 0 | EA57: 0 | EB57: 0 | EC57: 0 | ED57: 0
A58: 106304113 | B58: CHILDREN'S HOSPITAL - MISSION | C58: 20174 | D58: 43009 | E58: 43100 | F58: Open | G58: Orange | H58: 13 | I58: 1017 | J58: Non Profit Corp. | K58: Comparable | M58: 714-997-3000 | N58: 27700 MEDICAL CENTER ROAD., 5TH FL | O58: MISSION VIEJO | P58: 92691 | Q58: KIMBERLY CRIPE | R58: 54 | S58: 54 | T58: 19 | U58: 0 | V58: 0 | W58: 62 | X58: 113 | Y58: 0 | Z58: 0 | AA58: 15 | AB58: 268 | AC58: 0 | AD58: 9 | AE58: 467 | AF58: 0 | AG58: 0 | AH58: 0 | AI58: 567 | AJ58: 274 | AK58: 0 | AL58: 0 | AM58: 47 | AN58: 811 | AO58: 0 | AP58: 7 | AQ58: 1706 | AR58: 0 | AS58: =Append1[[#This Row],[DAY_MCAR]]+Append1[[#This Row],[DAY_MCAR_MC]]+Append1[[#This Row],[DAY_MCAL]]+Append1[[#This Row],[DAY_MCAL_MC]]+Append1[[#This Row],[DAY_CNTY]]+Append1[[#This Row],[DAY_CNTY_MC]]+Append1[[#This Row],[DAY_THRD]]+Append1[[#This Row],[DAY_THRD_MC]]+Append1[[#This Row],[DAY_INDGNT]]+Append1[[#This Row],[DAY_OTH]]+Append1[[#This Row],[DAY_TOT]]+Append1[[#This Row],[DAY_LTC]] -> 3412 | AT58: 0 | AU58: 0 | AV58: 221 | AW58: 2074 | AX58: 0 | AY58: 0 | AZ58: 118 | BA58: 3047 | BB58: 0 | BC58: 151 | BD58: 5611 | BE58: 0 | BF58: 0 | BG58: 9087712 | BH58: 4422558 | BI58: 0 | BJ58: 0 | BK58: 1109790 | BL58: 16091392 | BM58: 0 | BN58: 280235 | BO58: 30991687 | BP58: 0 | BQ58: 0 | BR58: 877531 | BS58: 6941023 | BT58: 0 | BU58: 0 | BV58: 517517 | BW58: 11523025 | BX58: 0 | BY58: 364118 | BZ58: 20223214 | CA58: 1208867 | CB58: 0 | CC58: 0 | CD58: 6728800 | CE58: 10503425 | CF58: -330516 | CG58: 0 | CH58: 0 | CI58: 918277 | CJ58: 15582612 | CK58: 0 | CL58: 34893 | CM58: 0 | CN58: 0 | CO58: 0 | CP58: 43459 | CQ58: 34689817 | CR58: 0 | CS58: 0 | CT58: 0 | CU58: 0 | CV58: 0 | CW58: 0 | CX58: 0 | CY58: 3390867 | CZ58: 1036248 | DA58: 0 | DB58: 0 | DC58: 709030 | DD58: 10822938 | DE58: 0 | DF58: 566001 | DG58: 16525084 | DH58: 42996 | DI58: 14216451 | DJ58: 0 | DK58: -5351 | DL58: 0 | DM58: 0 | DN58: 0 | DO58: 0 | DP58: 59526 | DQ58: 7506340 | DR58: 0 | DS58: 0 | DT58: 0 | DU58: 0 | DV58: 0 | DW58: 0 | DX58: 0 | DY58: 0 | DZ58: 0 | EA58: 0 | EB58: 0 | EC58: 2482133 | ED58: 0
A59: 106190170 | B59: CHILDREN'S HOSPITAL - LOS ANGELES | C59: 20174 | D59: 43009 | E59: 43100 | F59: Open | G59: Los Angeles | H59: 11 | I59: 925 | J59: Non Profit Corp. | K59: Comparable | L59: Teaching | M59: 323-669-2450 | N59: 4650 W. SUNSET BOULEVARD | O59: LOS ANGELES | P59: 90027 | Q59: PAUL VIVIANO | R59: 495 | S59: 374 | T59: 374 | U59: 6 | V59: 0 | W59: 2072 | X59: 1042 | Y59: 0 | Z59: 0 | AA59: 82 | AB59: 1071 | AC59: 10 | AD59: 12 | AE59: 4295 | AF59: 0 | AG59: 25 | AH59: 0 | AI59: 17202 | AJ59: 2663 | AK59: 0 | AL59: 0 | AM59: 1461 | AN59: 6899 | AO59: 63 | AP59: 78 | AQ59: 28391 | AR59: 0 | AS59: =Append1[[#This Row],[DAY_MCAR]]+Append1[[#This Row],[DAY_MCAR_MC]]+Append1[[#This Row],[DAY_MCAL]]+Append1[[#This Row],[DAY_MCAL_MC]]+Append1[[#This Row],[DAY_CNTY]]+Append1[[#This Row],[DAY_CNTY_MC]]+Append1[[#This Row],[DAY_THRD]]+Append1[[#This Row],[DAY_THRD_MC]]+Append1[[#This Row],[DAY_INDGNT]]+Append1[[#This Row],[DAY_OTH]]+Append1[[#This Row],[DAY_TOT]]+Append1[[#This Row],[DAY_LTC]] -> 56782 | AT59: 481 | AU59: 0 | AV59: 42138 | AW59: 32105 | AX59: 0 | AY59: 0 | AZ59: 3851 | BA59: 24862 | BB59: 435 | BC59: 2140 | BD59: 106012 | BE59: 633592 | BF59: 0 | BG59: 299412932 | BH59: 39033439 | BI59: 0 | BJ59: 0 | BK59: 29114183 | BL59: 135798980 | BM59: 594092 | BN59: 741096 | BO59: 505328314 | BP59: 909596 | BQ59: 0 | BR59: 75927935 | BS59: 46523133 | BT59: 0 | BU59: 0 | BV59: 9279253 | BW59: 50365704 | BX59: 215187 | BY59: 2370912 | BZ59: 185591720 | CA59: 1848473 | CB59: 1183803 | CC59: 0 | CD59: 38401855 | CE59: 70065639 | CF59: -3875000 | CG59: 0 | CH59: 0 | CI59: 9430999 | CJ59: 117148409 | CK59: 0 | CL59: 809279 | CM59: -450000 | CN59: 0 | CO59: 0 | CP59: 2420373 | CQ59: 236983830 | CR59: 0 | CS59: 0 | CT59: 0 | CU59: 0 | CV59: 0 | CW59: 357067 | CX59: 0 | CY59: 339718771 | CZ59: 15348150 | DA59: 0 | DB59: 0 | DC59: 28855938 | DD59: 68519527 | DE59: 0 | DF59: 1136751 | DG59: 453936204 | DH59: 29856649 | DI59: 316073185 | DJ59: 0 | DK59: 9981353 | DL59: 0 | DM59: 0 | DN59: 0 | DO59: 0 | DP59: 14361989 | DQ59: 875391280 | DR59: 0 | DS59: 0 | DT59: 0 | DU59: 0 | DV59: 0 | DW59: 0 | DX59: 0 | DY59: 0 | DZ59: 0 | EA59: 0 | EB59: 0 | EC59: 0 | ED59: 0
A60: 106300032 | B60: CHILDREN'S HOSPITAL - ORANGE COUNTY | C60: 20174 | D60: 43009 | E60: 43100 | F60: Open | G60: Orange | H60: 13 | I60: 1015 | J60: Non Profit Corp. | K60: Comparable | M60: 714-997-3000 | N60: 1201 WEST LA VETA AVENUE | O60: ORANGE | P60: 92868 | Q60: KIM CRIPE | R60: 315 | S60: 315 | T60: 315 | U60: 8 | V60: 0 | W60: 1106 | X60: 706 | Y60: 0 | Z60: 0 | AA60: 25 | AB60: 1200 | AC60: 0 | AD60: 32 | AE60: 3077 | AF60: 0 | AG60: 51 | AH60: 0 | AI60: 7794 | AJ60: 1877 | AK60: 0 | AL60: 0 | AM60: 386 | AN60: 6035 | AO60: 0 | AP60: 72 | AQ60: 16215 | AR60: 0 | AS60: =Append1[[#This Row],[DAY_MCAR]]+Append1[[#This Row],[DAY_MCAR_MC]]+Append1[[#This Row],[DAY_MCAL]]+Append1[[#This Row],[DAY_MCAL_MC]]+Append1[[#This Row],[DAY_CNTY]]+Append1[[#This Row],[DAY_CNTY_MC]]+Append1[[#This Row],[DAY_THRD]]+Append1[[#This Row],[DAY_THRD_MC]]+Append1[[#This Row],[DAY_INDGNT]]+Append1[[#This Row],[DAY_OTH]]+Append1[[#This Row],[DAY_TOT]]+Append1[[#This Row],[DAY_LTC]] -> 32430 | AT60: 36 | AU60: 0 | AV60: 10036 | AW60: 21363 | AX60: 0 | AY60: 0 | AZ60: 284 | BA60: 11352 | BB60: 1 | BC60: 412 | BD60: 43484 | BE60: 1194353 | BF60: 0 | BG60: 174651588 | BH60: 41050302 | BI60: 0 | BJ60: 0 | BK60: 6080108 | BL60: 148642376 | BM60: 0 | BN60: 1410424 | BO60: 373029151 | BP60: 547807 | BQ60: 0 | BR60: 56553609 | BS60: 68685182 | BT60: 0 | BU60: 0 | BV60: 1319297 | BW60: 76510948 | BX60: 756 | BY60: 367845 | BZ60: 203985444 | CA60: 4206387 | CB60: 1471798 | CC60: 0 | CD60: 183687874 | CE60: 87182632 | CF60: -3765514 | CG60: 0 | CH60: 0 | CI60: 4191126 | CJ60: 127529980 | CK60: 0 | CL60: 2413 | CM60: 0 | CN60: 0 | CO60: 0 | CP60: 787388 | CQ60: 405294084 | CR60: 0 | CS60: 7908907 | CT60: 0 | CU60: 0 | CV60: 7908907 | CW60: 270361 | CX60: 0 | CY60: 50070866 | CZ60: 31673731 | DA60: 0 | DB60: 0 | DC60: 3208279 | DD60: 93416957 | DE60: 0 | DF60: 989224 | DG60: 179629418 | DH60: 16115841 | DI60: 145770045 | DJ60: 0 | DK60: -6710072 | DL60: 0 | DM60: 0 | DN60: 0 | DO60: 0 | DP60: 6503854 | DQ60: 623146716 | DR60: 0 | DS60: 0 | DT60: 0 | DU60: 0 | DV60: 0 | DW60: 0 | DX60: 0 | DY60: 0 | DZ60: 0 | EA60: 0 | EB60: 0 | EC60: 0 | ED60: 0
A61: 106434051 | B61: CHILDRENS RECOVERY CENTER OF NORTHERN CALIFORNIA | C61: 20174 | D61: 43009 | E61: 43100 | F61: Open | G61: Santa Clara | H61: 7 | I61: 431 | J61: Investor - Corp. | K61: Comparable | M61: 408-378-8875 | N61: 3777 SOUTH BASCOM AVENUE | O61: CAMPBELL | P61: 95008 | Q61: KEN MC GUIRE | R61: 29 | S61: 27 | T61: 25 | U61: 0 | V61: 0 | W61: 2 | X61: 3 | Y61: 0 | Z61: 0 | AA61: 0 | AB61: 1 | AC61: 0 | AD61: 0 | AE61: 6 | AF61: 0 | AG61: 0 | AH61: 0 | AI61: 1786 | AJ61: 450 | AK61: 0 | AL61: 0 | AM61: 0 | AN61: 41 | AO61: 0 | AP61: 0 | AQ61: 2277 | AR61: 0 | AS61: =Append1[[#This Row],[DAY_MCAR]]+Append1[[#This Row],[DAY_MCAR_MC]]+Append1[[#This Row],[DAY_MCAL]]+Append1[[#This Row],[DAY_MCAL_MC]]+Append1[[#This Row],[DAY_CNTY]]+Append1[[#This Row],[DAY_CNTY_MC]]+Append1[[#This Row],[DAY_THRD]]+Append1[[#This Row],[DAY_THRD_MC]]+Append1[[#This Row],[DAY_INDGNT]]+Append1[[#This Row],[DAY_OTH]]+Append1[[#This Row],[DAY_TOT]]+Append1[[#This Row],[DAY_LTC]] -> 4554 | AT61: 0 | AU61: 0 | AV61: 0 | AW61: 0 | AX61: 0 | AY61: 0 | AZ61: 0 | BA61: 0 | BB61: 0 | BC61: 0 | BD61: 0 | BE61: 0 | BF61: 0 | BG61: 3013036 | BH61: 803848 | BI61: 0 | BJ61: 0 | BK61: 0 | BL61: 77900 | BM61: 0 | BN61: 0 | BO61: 3894784 | BP61: 0 | BQ61: 0 | BR61: 0 | BS61: 0 | BT61: 0 | BU61: 0 | BV61: 0 | BW61: 0 | BX61: 0 | BY61: 0 | BZ61: 0 | CA61: 0 | CB61: 0 | CC61: 0 | CD61: 1176964 | CE61: 302971 | CF61: 0 | CG61: 0 | CH61: 0 | CI61: 0 | CJ61: 29971 | CK61: 0 | CL61: 0 | CM61: 0 | CN61: 0 | CO61: 0 | CP61: 0 | CQ61: 1509906 | CR61: 0 | CS61: 0 | CT61: 0 | CU61: 0 | CV61: 0 | CW61: 0 | CX61: 0 | CY61: 1836072 | CZ61: 500877 | DA61: 0 | DB61: 0 | DC61: 0 | DD61: 47929 | DE61: 0 | DF61: 0 | DG61: 2384878 | DH61: 0 | DI61: 2459787 | DJ61: 0 | DK61: 0 | DL61: 0 | DM61: 0 | DN61: 0 | DO61: 0 | DP61: 3595 | DQ61: 643963 | DR61: 0 | DS61: 0 | DT61: 0 | DU61: 0 | DV61: 0 | DW61: 0 | DX61: 0 | DY61: 0 | DZ61: 0 | EA61: 0 | EB61: 0 | EC61: 0 | ED61: 0
A62: 106382715 | B62: CHINESE HOSPITAL | C62: 20174 | D62: 43009 | E62: 43100 | F62: Open | G62: San Francisco | H62: 4 | I62: 423 | J62: Non Profit Corp. | K62: Comparable | M62: 415-982-2400 | N62: 845 JACKSON STREET | O62: SAN FRANCISCO | P62: 94133 | Q62: JIAN ZHANG | R62: 65 | S62: 60 | T62: 15 | U62: 96 | V62: 60 | W62: 15 | X62: 14 | Y62: 0 | Z62: 0 | AA62: 48 | AB62: 0 | AC62: 0 | AD62: 5 | AE62: 238 | AF62: 0 | AG62: 535 | AH62: 227 | AI62: 47 | AJ62: 53 | AK62: 0 | AL62: 0 | AM62: 221 | AN62: 0 | AO62: 0 | AP62: 78 | AQ62: 1161 | AR62: 0 | AS62: =Append1[[#This Row],[DAY_MCAR]]+Append1[[#This Row],[DAY_MCAR_MC]]+Append1[[#This Row],[DAY_MCAL]]+Append1[[#This Row],[DAY_MCAL_MC]]+Append1[[#This Row],[DAY_CNTY]]+Append1[[#This Row],[DAY_CNTY_MC]]+Append1[[#This Row],[DAY_THRD]]+Append1[[#This Row],[DAY_THRD_MC]]+Append1[[#This Row],[DAY_INDGNT]]+Append1[[#This Row],[DAY_OTH]]+Append1[[#This Row],[DAY_TOT]]+Append1[[#This Row],[DAY_LTC]] -> 2322 | AT62: 4182 | AU62: 4069 | AV62: 995 | AW62: 1771 | AX62: 0 | AY62: 0 | AZ62: 6727 | BA62: 9 | BB62: 61 | BC62: 67 | BD62: 17881 | BE62: 5405263 | BF62: 2149681 | BG62: 398527 | BH62: 738235 | BI62: 0 | BJ62: 0 | BK62: 2351800 | BL62: 0 | BM62: 0 | BN62: 408094 | BO62: 11451600 | BP62: 9960982 | BQ62: 6266672 | BR62: 1061892 | BS62: 2952538 | BT62: 0 | BU62: 0 | BV62: 11789041 | BW62: 8472 | BX62: 44052 | BY62: 134754 | BZ62: 32218403 | CA62: 147894 | CB62: 11130770 | CC62: 15390561 | CD62: 995876 | CE62: 3690773 | CF62: 0 | CG62: 0 | CH62: 0 | CI62: 12964030 | CJ62: 8472 | CK62: 0 | CL62: 69809 | CM62: 0 | CN62: 0 | CO62: 0 | CP62: 178987 | CQ62: 44577172 | CR62: 7910768 | CS62: 3012206 | CT62: 0 | CU62: 757530 | CV62: 11680504 | CW62: 4235475 | CX62: 936559 | CY62: 464544 | CZ62: 3012206 | DA62: 0 | DB62: 0 | DC62: 1176812 | DD62: 757530 | DE62: -25757 | DF62: 215966 | DG62: 10773335 | DH62: 11572107 | DI62: 31642513 | DJ62: 1484678 | DK62: -2187 | DL62: 0 | DM62: 0 | DN62: 0 | DO62: 0 | DP62: 4855753 | DQ62: 251424762 | DR62: 0 | DS62: 0 | DT62: 0 | DU62: 0 | DV62: 0 | DW62: 0 | DX62: 0 | DY62: 0 | DZ62: 0 | EA62: 0 | EB62: 0 | EC62: 0 | ED62: 0
A63: 106361144 | B63: CHINO VALLEY MEDICAL CENTER | C63: 20174 | D63: 43009 | E63: 43100 | F63: Open | G63: San Bernardino | H63: 12 | I63: 1207 | J63: Investor - Corp. | K63: Comparable | M63: 909-464-8600 | N63: 5451 WALNUT AVENUE | O63: CHINO | P63: 91710 | Q63: MIKE SARIAN | R63: 112 | S63: 112 | T63: 112 | U63: 211 | V63: 298 | W63: 190 | X63: 463 | Y63: 0 | Z63: 0 | AA63: 209 | AB63: 34 | AC63: 0 | AD63: 20 | AE63: 1425 | AF63: 0 | AG63: 740 | AH63: 860 | AI63: 611 | AJ63: 1284 | AK63: 0 | AL63: 0 | AM63: 471 | AN63: 86 | AO63: 0 | AP63: 42 | AQ63: 4094 | AR63: 0 | AS63: =Append1[[#This Row],[DAY_MCAR]]+Append1[[#This Row],[DAY_MCAR_MC]]+Append1[[#This Row],[DAY_MCAL]]+Append1[[#This Row],[DAY_MCAL_MC]]+Append1[[#This Row],[DAY_CNTY]]+Append1[[#This Row],[DAY_CNTY_MC]]+Append1[[#This Row],[DAY_THRD]]+Append1[[#This Row],[DAY_THRD_MC]]+Append1[[#This Row],[DAY_INDGNT]]+Append1[[#This Row],[DAY_OTH]]+Append1[[#This Row],[DAY_TOT]]+Append1[[#This Row],[DAY_LTC]] -> 8188 | AT63: 523 | AU63: 520 | AV63: 1476 | AW63: 5143 | AX63: 0 | AY63: 0 | AZ63: 2172 | BA63: 108 | BB63: 0 | BC63: 1074 | BD63: 11016 | BE63: 11171140 | BF63: 13119043 | BG63: 8572919 | BH63: 18210713 | BI63: 0 | BJ63: 0 | BK63: 8097154 | BL63: 1155119 | BM63: 0 | BN63: 756341 | BO63: 61082429 | BP63: 2809751 | BQ63: 4014579 | BR63: 5350892 | BS63: 15760233 | BT63: 0 | BU63: 0 | BV63: 7374124 | BW63: 300324 | BX63: 0 | BY63: 2852045 | BZ63: 38461948 | CA63: 3294545 | CB63: 9955995 | CC63: 13428956 | CD63: 13451822 | CE63: 22546220 | CF63: 0 | CG63: 0 | CH63: 0 | CI63: 10521180 | CJ63: 642983 | CK63: 0 | CL63: 71722 | CM63: 0 | CN63: 0 | CO63: 0 | CP63: 116594 | CQ63: 74030017 | CR63: 694291 | CS63: 0 | CT63: 0 | CU63: 0 | CV63: 694291 | CW63: 4024896 | CX63: 4398957 | CY63: 471989 | CZ63: 11424726 | DA63: 0 | DB63: 0 | DC63: 4950098 | DD63: 812460 | DE63: 0 | DF63: 125525 | DG63: 26208651 | DH63: 147113 | DI63: 22594521 | DJ63: 0 | DK63: -12300 | DL63: 0 | DM63: 0 | DN63: 0 | DO63: 0 | DP63: 185696 | DQ63: 48816298 | DR63: 0 | DS63: 11 | DT63: 33 | DU63: 31 | DV63: 369581 | DW63: 120745 | DX63: 48367 | DY63: 0 | DZ63: 0 | EA63: 441960 | EB63: 2228851 | EC63: 711362 | ED63: 5614877
A64: 106190636 | B64: CITRUS VALLEY MEDICAL CENTER - QV CAMPUS | C64: 20174 | D64: 43009 | E64: 43100 | F64: Open | G64: Los Angeles | H64: 11 | I64: 915 | J64: Non Profit Corp. | K64: Comparable | M64: 626-858-8541 | N64: 1115 SOUTH SUNSET AVENUE | O64: WEST COVINA | P64: 91790 | Q64: ROB CURRY | R64: 516 | S64: 516 | T64: 320 | U64: 1268 | V64: 1063 | W64: 1017 | X64: 1675 | Y64: 0 | Z64: 0 | AA64: 29 | AB64: 922 | AC64: 35 | AD64: 173 | AE64: 6182 | AF64: 0 | AG64: 7902 | AH64: 4425 | AI64: 4380 | AJ64: 6262 | AK64: 0 | AL64: 0 | AM64: 84 | AN64: 3654 | AO64: 86 | AP64: 478 | AQ64: 27271 | AR64: 0 | AS64: =Append1[[#This Row],[DAY_MCAR]]+Append1[[#This Row],[DAY_MCAR_MC]]+Append1[[#This Row],[DAY_MCAL]]+Append1[[#This Row],[DAY_MCAL_MC]]+Append1[[#This Row],[DAY_CNTY]]+Append1[[#This Row],[DAY_CNTY_MC]]+Append1[[#This Row],[DAY_THRD]]+Append1[[#This Row],[DAY_THRD_MC]]+Append1[[#This Row],[DAY_INDGNT]]+Append1[[#This Row],[DAY_OTH]]+Append1[[#This Row],[DAY_TOT]]+Append1[[#This Row],[DAY_LTC]] -> 54542 | AT64: 8283 | AU64: 6067 | AV64: 4164 | AW64: 16886 | AX64: 0 | AY64: 0 | AZ64: 538 | BA64: 9434 | BB64: 1481 | BC64: 1582 | BD64: 48435 | BE64: 58220868 | BF64: 48785124 | BG64: 26555605 | BH64: 50889557 | BI64: 0 | BJ64: 0 | BK64: 1255152 | BL64: 33888387 | BM64: 534525 | BN64: 3162639 | BO64: 223291857 | BP64: 19090278 | BQ64: 19098191 | BR64: 7592383 | BS64: 35344442 | BT64: 0 | BU64: 0 | BV64: 927581 | BW64: 23921450 | BX64: 225744 | BY64: 4612360 | BZ64: 110812429 | CA64: 2753015 | CB64: 55933214 | CC64: 46973460 | CD64: -25440162 | CE64: 73390377 | CF64: -942357 | CG64: 0 | CH64: 0 | CI64: 1680196 | CJ64: 32700165 | CK64: 0 | CL64: 760269 | CM64: 0 | CN64: 0 | CO64: 0 | CP64: 4830844 | CQ64: 192639021 | CR64: 0 | CS64: 5173381 | CT64: 0 | CU64: 0 | CV64: 5173381 | CW64: 21377932 | CX64: 20909855 | CY64: 60530507 | CZ64: 18017003 | DA64: 0 | DB64: 0 | DC64: 502537 | DD64: 25109672 | DE64: 0 | DF64: 191140 | DG64: 146638646 | DH64: 1722091 | DI64: 128177544 | DJ64: 2418945 | DK64: 8663445 | DL64: 0 | DM64: 0 | DN64: 3466165 | DO64: 1707216 | DP64: 11035167 | DQ64: 122727723 | DR64: 0 | DS64: 0 | DT64: 0 | DU64: 0 | DV64: 0 | DW64: 0 | DX64: 0 | DY64: 0 | DZ64: 0 | EA64: 0 | EB64: 0 | EC64: 0 | ED64: 0
A65: 106190176 | B65: CITY OF HOPE HELFORD CLINICAL RESEARCH HOSPITAL | C65: 20174 | D65: 43009 | E65: 43100 | F65: Open | G65: Los Angeles | H65: 11 | I65: 913 | J65: Non Profit Corp. | K65: Comparable | M65: 626-256-4673 | N65: 1500 DUARTE ROAD | O65: DUARTE | P65: 91010 | Q65: ROBERT STONE | R65: 217 | S65: 217 | T65: 217 | U65: 611 | V65: 38 | W65: 164 | X65: 120 | Y65: 0 | Z65: 0 | AA65: 17 | AB65: 795 | AC65: 0 | AD65: 3 | AE65: 1748 | AF65: 0 | AG65: 5468 | AH65: 260 | AI65: 2313 | AJ65: 898 | AK65: 0 | AL65: 0 | AM65: 319 | AN65: 8976 | AO65: 0 | AP65: 43 | AQ65: 18277 | AR65: 0 | AS65: =Append1[[#This Row],[DAY_MCAR]]+Append1[[#This Row],[DAY_MCAR_MC]]+Append1[[#This Row],[DAY_MCAL]]+Append1[[#This Row],[DAY_MCAL_MC]]+Append1[[#This Row],[DAY_CNTY]]+Append1[[#This Row],[DAY_CNTY_MC]]+Append1[[#This Row],[DAY_THRD]]+Append1[[#This Row],[DAY_THRD_MC]]+Append1[[#This Row],[DAY_INDGNT]]+Append1[[#This Row],[DAY_OTH]]+Append1[[#This Row],[DAY_TOT]]+Append1[[#This Row],[DAY_LTC]] -> 36554 | AT65: 15030 | AU65: 611 | AV65: 2600 | AW65: 2087 | AX65: 0 | AY65: 0 | AZ65: 176 | BA65: 15517 | BB65: 5 | BC65: 347 | BD65: 36373 | BE65: 123852150 | BF65: 7746453 | BG65: 54656447 | BH65: 19648905 | BI65: 0 | BJ65: 0 | BK65: 51774526 | BL65: 134222990 | BM65: 0 | BN65: 1142284 | BO65: 393043755 | BP65: 203631310 | BQ65: 9540228 | BR65: 30950900 | BS65: 27152425 | BT65: 0 | BU65: 0 | BV65: 53107920 | BW65: 156803062 | BX65: 680336 | BY65: 6711550 | BZ65: 488577731 | CA65: 13100320 | CB65: 264979901 | CC65: 15867151 | CD65: 73838736 | CE65: 33700516 | CF65: 0 | CG65: 0 | CH65: 0 | CI65: 60210089 | CJ65: 187070301 | CK65: 0 | CL65: 668327 | CM65: 0 | CN65: 0 | CO65: 0 | CP65: 0 | CQ65: 649435341 | CR65: 0 | CS65: 0 | CT65: 0 | CU65: 0 | CV65: 0 | CW65: 62496141 | CX65: 1419530 | CY65: 11772523 | CZ65: 13100814 | DA65: 0 | DB65: 0 | DC65: 44672357 | DD65: 97687159 | DE65: 19947 | DF65: 1017674 | DG65: 232186145 | DH65: 9387581 | DI65: 286625059 | DJ65: 0 | DK65: 24204891 | DL65: 0 | DM65: 0 | DN65: 0 | DO65: 0 | DP65: 21286909 | DQ65: 487985205 | DR65: 0 | DS65: 0 | DT65: 0 | DU65: 0 | DV65: 0 | DW65: 0 | DX65: 0 | DY65: 0 | DZ65: 0 | EA65: 0 | EB65: 0 | EC65: 0 | ED65: 0
A66: 106100005 | B66: CLOVIS COMMUNITY MEDICAL CENTER | C66: 20174 | D66: 43009 | E66: 43100 | F66: Open | G66: Fresno | H66: 9 | I66: 605 | J66: Non Profit Corp. | K66: Comparable | M66: 559-324-4000 | N66: 2755 HERNDON AVENUE | O66: CLOVIS | P66: 93611 | Q66: CRAIG WAGNER | R66: 208 | S66: 208 | T66: 185 | U66: 1027 | V66: 306 | W66: 163 | X66: 896 | Y66: 0 | Z66: 0 | AA66: 20 | AB66: 1342 | AC66: 18 | AD66: 30 | AE66: 3802 | AF66: 0 | AG66: 6054 | AH66: 1805 | AI66: 640 | AJ66: 3386 | AK66: 0 | AL66: 0 | AM66: 68 | AN66: 4561 | AO66: 44 | AP66: 77 | AQ66: 16635 | AR66: 0 | AS66: =Append1[[#This Row],[DAY_MCAR]]+Append1[[#This Row],[DAY_MCAR_MC]]+Append1[[#This Row],[DAY_MCAL]]+Append1[[#This Row],[DAY_MCAL_MC]]+Append1[[#This Row],[DAY_CNTY]]+Append1[[#This Row],[DAY_CNTY_MC]]+Append1[[#This Row],[DAY_THRD]]+Append1[[#This Row],[DAY_THRD_MC]]+Append1[[#This Row],[DAY_INDGNT]]+Append1[[#This Row],[DAY_OTH]]+Append1[[#This Row],[DAY_TOT]]+Append1[[#This Row],[DAY_LTC]] -> 33270 | AT66: 8485 | AU66: 2530 | AV66: 897 | AW66: 4745 | AX66: 0 | AY66: 0 | AZ66: 245 | BA66: 6235 | BB66: 92 | BC66: 85 | BD66: 23314 | BE66: 78485027 | BF66: 23306391 | BG66: 7504661 | BH66: 39972840 | BI66: 0 | BJ66: 0 | BK66: 1452440 | BL66: 60149539 | BM66: 577087 | BN66: 941564 | BO66: 212389549 | BP66: 33379422 | BQ66: 9646337 | BR66: 3258174 | BS66: 27723640 | BT66: 0 | BU66: 0 | BV66: 4995825 | BW66: 68031290 | BX66: 1669715 | BY66: 3100900 | BZ66: 151805303 | CA66: 7108282 | CB66: 91142844 | CC66: 27659664 | CD66: 11490612 | CE66: 60354124 | CF66: 0 | CG66: 0 | CH66: 0 | CI66: 4121906 | CJ66: 81936659 | CK66: 0 | CL66: 846002 | CM66: 0 | CN66: 0 | CO66: 0 | CP66: 0 | CQ66: 284660093 | CR66: 0 | CS66: 0 | CT66: 0 | CU66: 1119396 | CV66: 1119396 | CW66: 18541711 | CX66: 4650917 | CY66: -937512 | CZ66: 6023160 | DA66: 0 | DB66: 0 | DC66: 2200702 | DD66: 44865717 | DE66: 2017595 | DF66: 3291865 | DG66: 80654155 | DH66: 925613 | DI66: 73320550 | DJ66: 3817997 | DK66: -811202 | DL66: 0 | DM66: 0 | DN66: 0 | DO66: 0 | DP66: 4887228 | DQ66: 384544163 | DR66: 0 | DS66: 0 | DT66: 0 | DU66: 0 | DV66: 0 | DW66: 0 | DX66: 0 | DY66: 0 | DZ66: 0 | EA66: 0 | EB66: 0 | EC66: 0 | ED66: 0
A67: 106100697 | B67: COALINGA REGIONAL MEDICAL CENTER | C67: 20174 | D67: 43009 | E67: 43100 | F67: Open | G67: Fresno | H67: 9 | I67: 609 | J67: District | K67: Comparable | L67: Rural | M67: 559-935-6400 | N67: 1191 PHELPS AVENUE | O67: COALINGA | P67: 93210 | Q67: SHARON A. SPURGEON | R67: 123 | S67: 116 | T67: 90 | U67: 14 | V67: 5 | W67: 10 | X67: 16 | Y67: 0 | Z67: 0 | AA67: 2 | AB67: 6 | AC67: 0 | AD67: 2 | AE67: 55 | AF67: 9 | AG67: 136 | AH67: 11 | AI67: 6000 | AJ67: 45 | AK67: 0 | AL67: 0 | AM67: 5 | AN67: 19 | AO67: 0 | AP67: 4 | AQ67: 6220 | AR67: 6075 | AS67: =Append1[[#This Row],[DAY_MCAR]]+Append1[[#This Row],[DAY_MCAR_MC]]+Append1[[#This Row],[DAY_MCAL]]+Append1[[#This Row],[DAY_MCAL_MC]]+Append1[[#This Row],[DAY_CNTY]]+Append1[[#This Row],[DAY_CNTY_MC]]+Append1[[#This Row],[DAY_THRD]]+Append1[[#This Row],[DAY_THRD_MC]]+Append1[[#This Row],[DAY_INDGNT]]+Append1[[#This Row],[DAY_OTH]]+Append1[[#This Row],[DAY_TOT]]+Append1[[#This Row],[DAY_LTC]] -> 18515 | AT67: 806 | AU67: 119 | AV67: 449 | AW67: 2594 | AX67: 0 | AY67: 0 | AZ67: 300 | BA67: 2070 | BB67: 3 | BC67: 307 | BD67: 6648 | BE67: 240912 | BF67: 40393 | BG67: 2625291 | BH67: 214626 | BI67: 0 | BJ67: 0 | BK67: 27295 | BL67: 102403 | BM67: 0 | BN67: 36591 | BO67: 3287511 | BP67: 547457 | BQ67: 83503 | BR67: 424256 | BS67: 1962621 | BT67: 0 | BU67: 0 | BV67: 219385 | BW67: 1155124 | BX67: 8655 | BY67: 243192 | BZ67: 4644193 | CA67: 133237 | CB67: 419707 | CC67: 59470 | CD67: 1173123 | CE67: 1763570 | CF67: -30166 | CG67: 0 | CH67: 0 | CI67: 143074 | CJ67: 289589 | CK67: 0 | CL67: 8655 | CM67: 0 | CN67: 0 | CO67: 0 | CP67: 0 | CQ67: 3960259 | CR67: 0 | CS67: 0 | CT67: 0 | CU67: 0 | CV67: 0 | CW67: 368662 | CX67: 64426 | CY67: 1906590 | CZ67: 413677 | DA67: 0 | DB67: 0 | DC67: 103606 | DD67: 967938 | DE67: 0 | DF67: 146546 | DG67: 3971445 | DH67: 308539 | DI67: 6068528 | DJ67: 0 | DK67: 370871 | DL67: 0 | DM67: 0 | DN67: 0 | DO67: 0 | DP67: 51926 | DQ67: 7628072 | DR67: 0 | DS67: 0 | DT67: 0 | DU67: 0 | DV67: 0 | DW67: 0 | DX67: 0 | DY67: 0 | DZ67: 0 | EA67: 0 | EB67: 0 | EC67: 0 | ED67: 0
A68: 106105051 | B68: COALINGA STATE HOSPITAL | C68: 20174 | D68: 43009 | E68: 43100 | F68: Open | G68: Fresno | H68: 9 | I68: 609 | J68: State | K68: State Hospitals | M68: 559-935-4300 | N68: 24511 WEST JAYNE AVENUE | O68: COALINGA | P68: 93210 | Q68: TOM VOSS | R68: 1500 | S68: 1310 | T68: 1310 | U68: 2 | V68: 0 | W68: 0 | X68: 0 | Y68: 0 | Z68: 0 | AA68: 0 | AB68: 0 | AC68: 0 | AD68: 54 | AE68: 56 | AF68: 0 | AG68: 86618 | AH68: 0 | AI68: 0 | AJ68: 0 | AK68: 0 | AL68: 0 | AM68: 0 | AN68: 0 | AO68: 0 | AP68: 22472 | AQ68: 109090 | AR68: 0 | AS68: =Append1[[#This Row],[DAY_MCAR]]+Append1[[#This Row],[DAY_MCAR_MC]]+Append1[[#This Row],[DAY_MCAL]]+Append1[[#This Row],[DAY_MCAL_MC]]+Append1[[#This Row],[DAY_CNTY]]+Append1[[#This Row],[DAY_CNTY_MC]]+Append1[[#This Row],[DAY_THRD]]+Append1[[#This Row],[DAY_THRD_MC]]+Append1[[#This Row],[DAY_INDGNT]]+Append1[[#This Row],[DAY_OTH]]+Append1[[#This Row],[DAY_TOT]]+Append1[[#This Row],[DAY_LTC]] -> 218180 | AT68: 0 | AU68: 0 | AV68: 0 | AW68: 0 | AX68: 0 | AY68: 0 | AZ68: 0 | BA68: 0 | BB68: 0 | BC68: 0 | BD68: 0 | BE68: 51177767 | BF68: 0 | BG68: 0 | BH68: 0 | BI68: 0 | BJ68: 0 | BK68: 0 | BL68: 0 | BM68: 0 | BN68: 13277229 | BO68: 64454996 | BP68: 0 | BQ68: 0 | BR68: 0 | BS68: 0 | BT68: 0 | BU68: 0 | BV68: 0 | BW68: 0 | BX68: 0 | BY68: 0 | BZ68: 0 | CA68: 0 | CB68: 0 | CC68: 0 | CD68: 0 | CE68: 0 | CF68: 0 | CG68: 0 | CH68: 0 | CI68: 0 | CJ68: 0 | CK68: 0 | CL68: 0 | CM68: 0 | CN68: 0 | CO68: 0 | CP68: 0 | CQ68: 0 | CR68: 0 | CS68: 0 | CT68: 0 | CU68: 0 | CV68: 0 | CW68: 51177767 | CX68: 0 | CY68: 0 | CZ68: 0 | DA68: 0 | DB68: 0 | DC68: 0 | DD68: 0 | DE68: 0 | DF68: 13277229 | DG68: 64454996 | DH68: 0 | DI68: 69932604 | DJ68: 0 | DK68: 5477608 | DL68: 0 | DM68: 0 | DN68: 0 | DO68: 0 | DP68: 0 | DQ68: 0 | DR68: 0 | DS68: 0 | DT68: 0 | DU68: 0 | DV68: 0 | DW68: 0 | DX68: 0 | DY68: 0 | DZ68: 0 | EA68: 0 | EB68: 0 | EC68: 0 | ED68: 0
A69: 106190766 | B69: COAST PLAZA HOSPITAL | C69: 20174 | D69: 43009 | E69: 43100 | F69: Open | G69: Los Angeles | H69: 11 | I69: 921 | J69: Investor - Ptnr. | K69: Comparable | M69: 562-868-3751 | N69: 13100 SOUTH STUDEBAKER ROAD | O69: NORWALK | P69: 90650 | Q69: RICK ROWE | R69: 117 | S69: 105 | T69: 105 | U69: 204 | V69: 102 | W69: 58 | X69: 209 | Y69: 0 | Z69: 0 | AA69: 18 | AB69: 26 | AC69: 20 | AD69: 18 | AE69: 655 | AF69: 0 | AG69: 975 | AH69: 428 | AI69: 174 | AJ69: 1033 | AK69: 0 | AL69: 0 | AM69: 43 | AN69: 64 | AO69: 81 | AP69: 35 | AQ69: 2833 | AR69: 0 | AS69: =Append1[[#This Row],[DAY_MCAR]]+Append1[[#This Row],[DAY_MCAR_MC]]+Append1[[#This Row],[DAY_MCAL]]+Append1[[#This Row],[DAY_MCAL_MC]]+Append1[[#This Row],[DAY_CNTY]]+Append1[[#This Row],[DAY_CNTY_MC]]+Append1[[#This Row],[DAY_THRD]]+Append1[[#This Row],[DAY_THRD_MC]]+Append1[[#This Row],[DAY_INDGNT]]+Append1[[#This Row],[DAY_OTH]]+Append1[[#This Row],[DAY_TOT]]+Append1[[#This Row],[DAY_LTC]] -> 5666 | AT69: 414 | AU69: 241 | AV69: 451 | AW69: 1809 | AX69: 0 | AY69: 0 | AZ69: 184 | BA69: 240 | BB69: 112 | BC69: 451 | BD69: 3902 | BE69: 14573995 | BF69: 6234723 | BG69: 2824553 | BH69: 13005912 | BI69: 0 | BJ69: 0 | BK69: 842151 | BL69: 971260 | BM69: 863353 | BN69: 496341 | BO69: 39812288 | BP69: 2599624 | BQ69: 1685633 | BR69: 1770000 | BS69: 7473996 | BT69: 0 | BU69: 0 | BV69: 1196762 | BW69: 1698533 | BX69: 283470 | BY69: 1139183 | BZ69: 17847201 | CA69: 1105422 | CB69: 14230325 | CC69: 6120520 | CD69: 3829176 | CE69: 18779081 | CF69: -209981 | CG69: 0 | CH69: 0 | CI69: 1472369 | CJ69: 2682908 | CK69: 0 | CL69: 327039 | CM69: 0 | CN69: 0 | CO69: 0 | CP69: 641654 | CQ69: 48978513 | CR69: 0 | CS69: 0 | CT69: 0 | CU69: 0 | CV69: 0 | CW69: 2943294 | CX69: 1799836 | CY69: 975358 | CZ69: 1700827 | DA69: 0 | DB69: 0 | DC69: 566544 | DD69: -13115 | DE69: 819784 | DF69: -111552 | DG69: 8680976 | DH69: 0 | DI69: 9255619 | DJ69: 0 | DK69: -31650 | DL69: 0 | DM69: 0 | DN69: 0 | DO69: 0 | DP69: 20534 | DQ69: 12304918 | DR69: 0 | DS69: 0 | DT69: 0 | DU69: 0 | DV69: 0 | DW69: 0 | DX69: 0 | DY69: 0 | DZ69: 0 | EA69: 0 | EB69: 0 | EC69: 0 | ED69: 0
A70: 106190184 | B70: COLLEGE HOSPITAL | C70: 20174 | D70: 43009 | E70: 43100 | F70: Open | G70: Los Angeles | H70: 11 | I70: 921 | J70: Investor - Corp. | K70: Comparable | M70: 562-924-9581 | N70: 10802 COLLEGE PLACE | O70: CERRITOS | P70: 90703 | Q70: STEVE WITT | R70: 187 | S70: 187 | T70: 187 | U70: 246 | V70: 0 | W70: 99 | X70: 0 | Y70: 46 | Z70: 0 | AA70: 0 | AB70: 814 | AC70: 3 | AD70: 99 | AE70: 1307 | AF70: 0 | AG70: 3944 | AH70: 0 | AI70: 535 | AJ70: 0 | AK70: 241 | AL70: 0 | AM70: 0 | AN70: 10474 | AO70: 9 | AP70: 431 | AQ70: 15634 | AR70: 0 | AS70: =Append1[[#This Row],[DAY_MCAR]]+Append1[[#This Row],[DAY_MCAR_MC]]+Append1[[#This Row],[DAY_MCAL]]+Append1[[#This Row],[DAY_MCAL_MC]]+Append1[[#This Row],[DAY_CNTY]]+Append1[[#This Row],[DAY_CNTY_MC]]+Append1[[#This Row],[DAY_THRD]]+Append1[[#This Row],[DAY_THRD_MC]]+Append1[[#This Row],[DAY_INDGNT]]+Append1[[#This Row],[DAY_OTH]]+Append1[[#This Row],[DAY_TOT]]+Append1[[#This Row],[DAY_LTC]] -> 31268 | AT70: 11378 | AU70: 0 | AV70: 0 | AW70: 0 | AX70: 0 | AY70: 0 | AZ70: 0 | BA70: 3071 | BB70: 0 | BC70: 13 | BD70: 14462 | BE70: 7822222 | BF70: 0 | BG70: 1035111 | BH70: 0 | BI70: 446718 | BJ70: 0 | BK70: 0 | BL70: 24884482 | BM70: 8992 | BN70: 925745 | BO70: 35123270 | BP70: 4907509 | BQ70: 0 | BR70: 0 | BS70: 0 | BT70: 0 | BU70: 0 | BV70: 0 | BW70: 1549968 | BX70: 0 | BY70: 4000 | BZ70: 6461477 | CA70: 724868 | CB70: 6870472 | CC70: 0 | CD70: 667390 | CE70: 0 | CF70: 0 | CG70: 264534 | CH70: 0 | CI70: 0 | CJ70: 14229311 | CK70: 0 | CL70: 866752 | CM70: 0 | CN70: 0 | CO70: 0 | CP70: 0 | CQ70: 23623327 | CR70: 0 | CS70: 0 | CT70: 0 | CU70: 0 | CV70: 0 | CW70: 5859259 | CX70: 0 | CY70: 367721 | CZ70: 0 | DA70: 182184 | DB70: 0 | DC70: 0 | DD70: 11480271 | DE70: 0 | DF70: 71985 | DG70: 17961420 | DH70: 2457 | DI70: 15281498 | DJ70: 0 | DK70: 3290 | DL70: 0 | DM70: 0 | DN70: 0 | DO70: 0 | DP70: 125101 | DQ70: 7428073 | DR70: 0 | DS70: 0 | DT70: 0 | DU70: 0 | DV70: 0 | DW70: 0 | DX70: 0 | DY70: 0 | DZ70: 0 | EA70: 0 | EB70: 0 | EC70: 0 | ED70: 0
A71: 106301155 | B71: COLLEGE HOSPITAL COSTA MESA | C71: 20174 | D71: 43009 | E71: 43100 | F71: Open | G71: Orange | H71: 13 | I71: 1016 | J71: Investor - Corp. | K71: Comparable | M71: 949-642-2734 | N71: 301 VICTORIA STREET | O71: COSTA MESA | P71: 92627 | Q71: SUSAN TAYLOR | R71: 122 | S71: 122 | T71: 112 | U71: 29 | V71: 18 | W71: 623 | X71: 9 | Y71: 33 | Z71: 0 | AA71: 3 | AB71: 211 | AC71: 0 | AD71: 7 | AE71: 933 | AF71: 0 | AG71: 213 | AH71: 75 | AI71: 8483 | AJ71: 40 | AK71: 377 | AL71: 0 | AM71: 21 | AN71: 925 | AO71: 0 | AP71: 18 | AQ71: 10152 | AR71: 0 | AS71: =Append1[[#This Row],[DAY_MCAR]]+Append1[[#This Row],[DAY_MCAR_MC]]+Append1[[#This Row],[DAY_MCAL]]+Append1[[#This Row],[DAY_MCAL_MC]]+Append1[[#This Row],[DAY_CNTY]]+Append1[[#This Row],[DAY_CNTY_MC]]+Append1[[#This Row],[DAY_THRD]]+Append1[[#This Row],[DAY_THRD_MC]]+Append1[[#This Row],[DAY_INDGNT]]+Append1[[#This Row],[DAY_OTH]]+Append1[[#This Row],[DAY_TOT]]+Append1[[#This Row],[DAY_LTC]] -> 20304 | AT71: 2884 | AU71: 278 | AV71: 0 | AW71: 0 | AX71: 0 | AY71: 0 | AZ71: 37 | BA71: 1111 | BB71: 1 | BC71: 20 | BD71: 4331 | BE71: 507751 | BF71: 450505 | BG71: 19442906 | BH71: 84695 | BI71: 873996 | BJ71: 0 | BK71: 48666 | BL71: 2104432 | BM71: 0 | BN71: 51468 | BO71: 23564419 | BP71: 1198700 | BQ71: 544631 | BR71: 0 | BS71: 0 | BT71: 0 | BU71: 0 | BV71: 23578 | BW71: 525224 | BX71: 2913 | BY71: 119271 | BZ71: 2414317 | CA71: 67259 | CB71: 863453 | CC71: 536754 | CD71: 13479643 | CE71: 59095 | CF71: -4167915 | CG71: 594262 | CH71: 0 | CI71: 34951 | CJ71: 1593027 | CK71: 0 | CL71: 250153 | CM71: 0 | CN71: 0 | CO71: 0 | CP71: 46501 | CQ71: 13357183 | CR71: 0 | CS71: 0 | CT71: 0 | CU71: 0 | CV71: 0 | CW71: 783244 | CX71: 458382 | CY71: 9890015 | CZ71: 25600 | DA71: 279734 | DB71: 0 | DC71: 36975 | DD71: 1018436 | DE71: 0 | DF71: 129167 | DG71: 12621553 | DH71: 244271 | DI71: 13218392 | DJ71: 464138 | DK71: 0 | DL71: 0 | DM71: 0 | DN71: 0 | DO71: 0 | DP71: 94183 | DQ71: 3291203 | DR71: 0 | DS71: 0 | DT71: 0 | DU71: 0 | DV71: 0 | DW71: 0 | DX71: 0 | DY71: 0 | DZ71: 0 | EA71: 0 | EB71: 0 | EC71: 0 | ED71: 0
A72: 106190587 | B72: COLLEGE MEDICAL CENTER | C72: 20174 | D72: 43009 | E72: 43100 | F72: Open | G72: Los Angeles | H72: 11 | I72: 933 | J72: Investor - Corp. | K72: Comparable | M72: 562-997-2500 | N72: 2776 PACIFIC AVENUE | O72: LONG BEACH | P72: 90806 | Q72: JOE AVELINO | R72: 221 | S72: 221 | T72: 221 | U72: 259 | V72: 120 | W72: 1645 | X72: 238 | Y72: 0 | Z72: 0 | AA72: 50 | AB72: 0 | AC72: 2 | AD72: 19 | AE72: 2333 | AF72: 0 | AG72: 1626 | AH72: 664 | AI72: 12151 | AJ72: 862 | AK72: 0 | AL72: 0 | AM72: 209 | AN72: 0 | AO72: 9 | AP72: 87 | AQ72: 15608 | AR72: 0 | AS72: =Append1[[#This Row],[DAY_MCAR]]+Append1[[#This Row],[DAY_MCAR_MC]]+Append1[[#This Row],[DAY_MCAL]]+Append1[[#This Row],[DAY_MCAL_MC]]+Append1[[#This Row],[DAY_CNTY]]+Append1[[#This Row],[DAY_CNTY_MC]]+Append1[[#This Row],[DAY_THRD]]+Append1[[#This Row],[DAY_THRD_MC]]+Append1[[#This Row],[DAY_INDGNT]]+Append1[[#This Row],[DAY_OTH]]+Append1[[#This Row],[DAY_TOT]]+Append1[[#This Row],[DAY_LTC]] -> 31216 | AT72: 649 | AU72: 291 | AV72: 346 | AW72: 1562 | AX72: 0 | AY72: 0 | AZ72: 486 | BA72: 0 | BB72: 2 | BC72: 451 | BD72: 3787 | BE72: 10343784 | BF72: 4384687 | BG72: 27118592 | BH72: 7342118 | BI72: 0 | BJ72: 0 | BK72: 1700648 | BL72: 0 | BM72: 21171 | BN72: 167973 | BO72: 51078973 | BP72: 3919199 | BQ72: 573739 | BR72: 1053575 | BS72: 4735394 | BT72: 0 | BU72: 0 | BV72: 1626038 | BW72: 0 | BX72: 11608 | BY72: 1506545 | BZ72: 13426098 | CA72: 1272215 | CB72: 12103425 | CC72: 3597428 | CD72: 15777998 | CE72: 10901528 | CF72: -2220000 | CG72: 0 | CH72: 0 | CI72: 2414882 | CJ72: 0 | CK72: 0 | CL72: 32779 | CM72: 0 | CN72: 0 | CO72: 0 | CP72: 0 | CQ72: 43880255 | CR72: 0 | CS72: 0 | CT72: 0 | CU72: 0 | CV72: 0 | CW72: 2159558 | CX72: 1360998 | CY72: 14614169 | CZ72: 1175984 | DA72: 0 | DB72: 0 | DC72: 911804 | DD72: 0 | DE72: 0 | DF72: 402303 | DG72: 20624816 | DH72: 36894 | DI72: 21583252 | DJ72: 0 | DK72: 0 | DL72: 0 | DM72: 0 | DN72: 0 | DO72: 0 | DP72: 537468 | DQ72: 7999967 | DR72: 0 | DS72: 0 | DT72: 0 | DU72: 0 | DV72: 0 | DW72: 0 | DX72: 0 | DY72: 0 | DZ72: 0 | EA72: 0 | EB72: 0 | EC72: 0 | ED72: 0
A73: 106361458 | B73: COLORADO RIVER MEDICAL CENTER | C73: 20174 | D73: 43009 | E73: 43100 | F73: Open | G73: San Bernardino | H73: 12 | I73: 1215 | J73: Investor - Corp. | K73: Comparable | L73: Rural | M73: 760-326-7267 | N73: 1401 BAILEY AVENUE | O73: NEEDLES | P73: 92363 | Q73: STEVE LOPEEZ | R73: 25 | S73: 25 | T73: 10 | U73: 72 | V73: 0 | W73: 52 | X73: 0 | Y73: 0 | Z73: 0 | AA73: 20 | AB73: 0 | AC73: 0 | AD73: 5 | AE73: 149 | AF73: 0 | AG73: 192 | AH73: 0 | AI73: 152 | AJ73: 0 | AK73: 0 | AL73: 0 | AM73: 50 | AN73: 0 | AO73: 0 | AP73: 16 | AQ73: 410 | AR73: 0 | AS73: =Append1[[#This Row],[DAY_MCAR]]+Append1[[#This Row],[DAY_MCAR_MC]]+Append1[[#This Row],[DAY_MCAL]]+Append1[[#This Row],[DAY_MCAL_MC]]+Append1[[#This Row],[DAY_CNTY]]+Append1[[#This Row],[DAY_CNTY_MC]]+Append1[[#This Row],[DAY_THRD]]+Append1[[#This Row],[DAY_THRD_MC]]+Append1[[#This Row],[DAY_INDGNT]]+Append1[[#This Row],[DAY_OTH]]+Append1[[#This Row],[DAY_TOT]]+Append1[[#This Row],[DAY_LTC]] -> 820 | AT73: 750 | AU73: 0 | AV73: 1161 | AW73: 0 | AX73: 0 | AY73: 0 | AZ73: 364 | BA73: 0 | BB73: 0 | BC73: 132 | BD73: 2407 | BE73: 963329 | BF73: 0 | BG73: 595809 | BH73: 0 | BI73: 0 | BJ73: 0 | BK73: 532107 | BL73: 0 | BM73: 0 | BN73: 98080 | BO73: 2189325 | BP73: 1895755 | BQ73: 0 | BR73: 2931371 | BS73: 0 | BT73: 0 | BU73: 0 | BV73: 806494 | BW73: 0 | BX73: 0 | BY73: 315687 | BZ73: 5949307 | CA73: 351176 | CB73: 1135944 | CC73: 0 | CD73: 3027302 | CE73: 0 | CF73: 0 | CG73: 0 | CH73: 0 | CI73: 663343 | CJ73: 0 | CK73: 0 | CL73: 124157 | CM73: 0 | CN73: 0 | CO73: 0 | CP73: 446467 | CQ73: 5748389 | CR73: 0 | CS73: 0 | CT73: 0 | CU73: 0 | CV73: 0 | CW73: 1121097 | CX73: 0 | CY73: 358536 | CZ73: 0 | DA73: 0 | DB73: 0 | DC73: 671585 | DD73: 0 | DE73: 0 | DF73: 239025 | DG73: 2390243 | DH73: 48478 | DI73: 2475759 | DJ73: 0 | DK73: 0 | DL73: 0 | DM73: 0 | DN73: 0 | DO73: 0 | DP73: 318797 | DQ73: 3759994 | DR73: 0 | DS73: 0 | DT73: 0 | DU73: 0 | DV73: 0 | DW73: 0 | DX73: 0 | DY73: 0 | DZ73: 0 | EA73: 0 | EB73: 0 | EC73: 0 | ED73: 0
A74: 106060870 | B74: COLUSA REGIONAL MEDICAL CENTER | C74: 20174 | D74: 43009 | E74: 43100 | F74: Open | G74: Colusa | H74: 1 | I74: 225 | J74: Investor - Corp. | K74: Comparable | L74: Rural | M74: 530-458-5821 | N74: 199 E WEBSTER STREET | O74: COLUSA | P74: 95932 | Q74: MARIA ZAMORA | R74: 48 | S74: 48 | T74: 48 | U74: 18 | V74: 0 | W74: 11 | X74: 0 | Y74: 0 | Z74: 0 | AA74: 8 | AB74: 0 | AC74: 0 | AD74: 0 | AE74: 37 | AF74: 0 | AG74: 39 | AH74: 0 | AI74: 18 | AJ74: 0 | AK74: 0 | AL74: 0 | AM74: 11 | AN74: 0 | AO74: 0 | AP74: 0 | AQ74: 68 | AR74: 0 | AS74: =Append1[[#This Row],[DAY_MCAR]]+Append1[[#This Row],[DAY_MCAR_MC]]+Append1[[#This Row],[DAY_MCAL]]+Append1[[#This Row],[DAY_MCAL_MC]]+Append1[[#This Row],[DAY_CNTY]]+Append1[[#This Row],[DAY_CNTY_MC]]+Append1[[#This Row],[DAY_THRD]]+Append1[[#This Row],[DAY_THRD_MC]]+Append1[[#This Row],[DAY_INDGNT]]+Append1[[#This Row],[DAY_OTH]]+Append1[[#This Row],[DAY_TOT]]+Append1[[#This Row],[DAY_LTC]] -> 136 | AT74: 958 | AU74: 0 | AV74: 594 | AW74: 0 | AX74: 0 | AY74: 0 | AZ74: 437 | BA74: 0 | BB74: 0 | BC74: 0 | BD74: 1989 | BE74: 184648 | BF74: 0 | BG74: 123099 | BH74: 0 | BI74: 0 | BJ74: 0 | BK74: 102582 | BL74: 0 | BM74: 0 | BN74: 0 | BO74: 410329 | BP74: 379824 | BQ74: 0 | BR74: 253216 | BS74: 0 | BT74: 0 | BU74: 0 | BV74: 211014 | BW74: 0 | BX74: 0 | BY74: 0 | BZ74: 844054 | CA74: 0 | CB74: 564472 | CC74: 0 | CD74: 376315 | CE74: 0 | CF74: 0 | CG74: 0 | CH74: 0 | CI74: 313596 | CJ74: 0 | CK74: 0 | CL74: 0 | CM74: 0 | CN74: 0 | CO74: 0 | CP74: 0 | CQ74: 1254383 | CR74: 0 | CS74: 0 | CT74: 0 | CU74: 0 | CV74: 0 | CW74: 0 | CX74: 0 | CY74: 0 | CZ74: 0 | DA74: 0 | DB74: 0 | DC74: 0 | DD74: 0 | DE74: 0 | DF74: 0 | DG74: 0 | DH74: 0 | DI74: 1380917 | DJ74: 0 | DK74: 0 | DL74: 0 | DM74: 0 | DN74: 0 | DO74: 0 | DP74: 218070 | DQ74: 1564402 | DR74: 0 | DS74: 0 | DT74: 0 | DU74: 0 | DV74: 0 | DW74: 0 | DX74: 0 | DY74: 0 | DZ74: 0 | EA74: 0 | EB74: 0 | EC74: 0 | ED74: 0
A75: 106190197 | B75: COMMUNITY HOSPITAL OF HUNTINGTON PARK | C75: 20174 | D75: 43009 | E75: 43100 | F75: Open | G75: Los Angeles | H75: 11 | I75: 923 | J75: Investor - Corp. | K75: Comparable | M75: 310-532-4200 | N75: 2623 EAST SLAUSON AVENUE | O75: HUNTINGTON PARK | P75: 90255 | Q75: ARACELI LONERGAN | R75: 81 | S75: 81 | T75: 81 | U75: 176 | V75: 144 | W75: 236 | X75: 310 | Y75: 0 | Z75: 0 | AA75: 5 | AB75: 27 | AC75: 0 | AD75: 11 | AE75: 909 | AF75: 0 | AG75: 836 | AH75: 631 | AI75: 950 | AJ75: 1310 | AK75: 0 | AL75: 0 | AM75: 15 | AN75: 93 | AO75: 0 | AP75: 29 | AQ75: 3864 | AR75: 0 | AS75: =Append1[[#This Row],[DAY_MCAR]]+Append1[[#This Row],[DAY_MCAR_MC]]+Append1[[#This Row],[DAY_MCAL]]+Append1[[#This Row],[DAY_MCAL_MC]]+Append1[[#This Row],[DAY_CNTY]]+Append1[[#This Row],[DAY_CNTY_MC]]+Append1[[#This Row],[DAY_THRD]]+Append1[[#This Row],[DAY_THRD_MC]]+Append1[[#This Row],[DAY_INDGNT]]+Append1[[#This Row],[DAY_OTH]]+Append1[[#This Row],[DAY_TOT]]+Append1[[#This Row],[DAY_LTC]] -> 7728 | AT75: 428 | AU75: 372 | AV75: 2848 | AW75: 5703 | AX75: 0 | AY75: 0 | AZ75: 196 | BA75: 273 | BB75: 27 | BC75: 849 | BD75: 10696 | BE75: 13232956 | BF75: 9950244 | BG75: 12371875 | BH75: 19041820 | BI75: 0 | BJ75: 0 | BK75: 330923 | BL75: 1217410 | BM75: 0 | BN75: 191416 | BO75: 56336644 | BP75: 2441974 | BQ75: 2157735 | BR75: 10516300 | BS75: 18320993 | BT75: 0 | BU75: 0 | BV75: 884678 | BW75: 1294763 | BX75: 145280 | BY75: 1678848 | BZ75: 37440571 | CA75: 1645896 | CB75: 13495441 | CC75: 10323160 | CD75: 20481251 | CE75: 33760130 | CF75: -714415 | CG75: 0 | CH75: 0 | CI75: 995003 | CJ75: 2163536 | CK75: 0 | CL75: 278289 | CM75: 0 | CN75: 0 | CO75: 0 | CP75: 255023 | CQ75: 82683314 | CR75: 0 | CS75: 0 | CT75: 0 | CU75: 0 | CV75: 0 | CW75: 2179489 | CX75: 1784819 | CY75: 3121339 | CZ75: 3494193 | DA75: 0 | DB75: 0 | DC75: 220598 | DD75: 348637 | DE75: -24519 | DF75: -30655 | DG75: 11093901 | DH75: 0 | DI75: 10972586 | DJ75: 0 | DK75: 0 | DL75: 0 | DM75: 0 | DN75: 0 | DO75: 0 | DP75: 91747 | DQ75: 2559886 | DR75: 0 | DS75: 0 | DT75: 0 | DU75: 0 | DV75: 0 | DW75: 0 | DX75: 0 | DY75: 0 | DZ75: 0 | EA75: 0 | EB75: 0 | EC75: 0 | ED75: 0
A76: 106190475 | B76: COMMUNITY HOSPITAL OF LONG BEACH | C76: 20174 | D76: 43009 | E76: 43100 | F76: Open | G76: Los Angeles | H76: 11 | I76: 933 | J76: Non Profit Corp. | K76: Comparable | M76: 562-498-1000 | N76: 1720 TERMINO AVENUE | O76: LONG BEACH | P76: 90804 | Q76: JOHN BISHOP | R76: 158 | S76: 158 | T76: 75 | U76: 432 | V76: 212 | W76: 107 | X76: 426 | Y76: 0 | Z76: 0 | AA76: 15 | AB76: 224 | AC76: 36 | AD76: 55 | AE76: 1507 | AF76: 0 | AG76: 2180 | AH76: 903 | AI76: 359 | AJ76: 1850 | AK76: 0 | AL76: 0 | AM76: 35 | AN76: 678 | AO76: 122 | AP76: 130 | AQ76: 6257 | AR76: 0 | AS76: =Append1[[#This Row],[DAY_MCAR]]+Append1[[#This Row],[DAY_MCAR_MC]]+Append1[[#This Row],[DAY_MCAL]]+Append1[[#This Row],[DAY_MCAL_MC]]+Append1[[#This Row],[DAY_CNTY]]+Append1[[#This Row],[DAY_CNTY_MC]]+Append1[[#This Row],[DAY_THRD]]+Append1[[#This Row],[DAY_THRD_MC]]+Append1[[#This Row],[DAY_INDGNT]]+Append1[[#This Row],[DAY_OTH]]+Append1[[#This Row],[DAY_TOT]]+Append1[[#This Row],[DAY_LTC]] -> 12514 | AT76: 644 | AU76: 511 | AV76: 425 | AW76: 2885 | AX76: 0 | AY76: 0 | AZ76: 136 | BA76: 1421 | BB76: 266 | BC76: 348 | BD76: 6636 | BE76: 23167101 | BF76: 12075774 | BG76: 3779929 | BH76: 15635147 | BI76: 0 | BJ76: 0 | BK76: 329695 | BL76: 6812556 | BM76: 711426 | BN76: 1385623 | BO76: 63897251 | BP76: 2320991 | BQ76: 2726687 | BR76: 1252873 | BS76: 7593403 | BT76: 0 | BU76: 0 | BV76: 355257 | BW76: 4707287 | BX76: 751994 | BY76: 1773818 | BZ76: 21482310 | CA76: 1748418 | CB76: 22136262 | CC76: 12490054 | CD76: 1473190 | CE76: 19422751 | CF76: 0 | CG76: 0 | CH76: 0 | CI76: 443793 | CJ76: 5951851 | CK76: 0 | CL76: 1496340 | CM76: 0 | CN76: 0 | CO76: 0 | CP76: 1744064 | CQ76: 66906723 | CR76: 0 | CS76: 164626 | CT76: 0 | CU76: 0 | CV76: 164626 | CW76: 3186238 | CX76: 2220481 | CY76: 3559612 | CZ76: 3827685 | DA76: 0 | DB76: 0 | DC76: 236602 | DD76: 5436216 | DE76: 39366 | DF76: 131264 | DG76: 18637464 | DH76: 103219 | DI76: 19877074 | DJ76: 0 | DK76: 147510 | DL76: 0 | DM76: 0 | DN76: 0 | DO76: 0 | DP76: 88851 | DQ76: 4806464 | DR76: 0 | DS76: 0 | DT76: 0 | DU76: 0 | DV76: 0 | DW76: 0 | DX76: 0 | DY76: 0 | DZ76: 0 | EA76: 0 | EB76: 0 | EC76: 0 | ED76: 0
A77: 106361323 | B77: COMMUNITY HOSPITAL OF SAN BERNARDINO | C77: 20174 | D77: 43009 | E77: 43100 | F77: Open | G77: San Bernardino | H77: 12 | I77: 1209 | J77: Non Profit Corp. | K77: Comparable | M77: 909-887-6333 | N77: 1805 MEDICAL CENTER DRIVE | O77: SAN BERNARDINO | P77: 92411 | Q77: JUNE COLLISON | R77: 347 | S77: 345 | T77: 306 | U77: 247 | V77: 229 | W77: 1268 | X77: 1049 | Y77: 0 | Z77: 0 | AA77: 19 | AB77: 116 | AC77: 15 | AD77: 29 | AE77: 2972 | AF77: 6 | AG77: 1269 | AH77: 1017 | AI77: 9841 | AJ77: 5392 | AK77: 0 | AL77: 0 | AM77: 63 | AN77: 332 | AO77: 97 | AP77: 127 | AQ77: 18138 | AR77: 8009 | AS77: =Append1[[#This Row],[DAY_MCAR]]+Append1[[#This Row],[DAY_MCAR_MC]]+Append1[[#This Row],[DAY_MCAL]]+Append1[[#This Row],[DAY_MCAL_MC]]+Append1[[#This Row],[DAY_CNTY]]+Append1[[#This Row],[DAY_CNTY_MC]]+Append1[[#This Row],[DAY_THRD]]+Append1[[#This Row],[DAY_THRD_MC]]+Append1[[#This Row],[DAY_INDGNT]]+Append1[[#This Row],[DAY_OTH]]+Append1[[#This Row],[DAY_TOT]]+Append1[[#This Row],[DAY_LTC]] -> 44285 | AT77: 1315 | AU77: 1298 | AV77: 4431 | AW77: 10723 | AX77: 0 | AY77: 0 | AZ77: 145 | BA77: 1158 | BB77: 343 | BC77: 1069 | BD77: 20482 | BE77: 14597961 | BF77: 11111848 | BG77: 93512528 | BH77: 53756656 | BI77: 0 | BJ77: 0 | BK77: 840941 | BL77: 4517073 | BM77: 952758 | BN77: 974021 | BO77: 180263786 | BP77: 4069135 | BQ77: 5450383 | BR77: 9903060 | BS77: 42236539 | BT77: 0 | BU77: 0 | BV77: 693972 | BW77: 6303702 | BX77: 1290088 | BY77: 2715570 | BZ77: 72662449 | CA77: 1410805 | CB77: 14558875 | CC77: 12977129 | CD77: 63274433 | CE77: 48779097 | CF77: -3996083 | CG77: 0 | CH77: 0 | CI77: 1096514 | CJ77: 4871765 | CK77: 0 | CL77: 2242846 | CM77: 0 | CN77: 0 | CO77: 0 | CP77: 742703 | CQ77: 145958084 | CR77: 11926 | CS77: 0 | CT77: 0 | CU77: 0 | CV77: 11926 | CW77: 4108221 | CX77: 3597028 | CY77: 44137238 | CZ77: 47214098 | DA77: 0 | DB77: 0 | DC77: 438399 | DD77: 5949010 | DE77: 0 | DF77: 1536083 | DG77: 106980077 | DH77: 381574 | DI77: 79500032 | DJ77: 2682714 | DK77: 14683 | DL77: 0 | DM77: 0 | DN77: 0 | DO77: 0 | DP77: 549841 | DQ77: 39389744 | DR77: 0 | DS77: 0 | DT77: 0 | DU77: 0 | DV77: 0 | DW77: 0 | DX77: 0 | DY77: 0 | DZ77: 0 | EA77: 0 | EB77: 0 | EC77: 0 | ED77: 0
A78: 106270744 | B78: COMMUNITY HOSPITAL OF THE MONTEREY PENINSULA | C78: 20174 | D78: 43009 | E78: 43100 | F78: Open | G78: Monterey | H78: 8 | I78: 707 | J78: Non Profit Corp. | K78: Comparable | M78: 831-624-5311 | N78: 23625 W. R. HOLMAN HIGHWAY | O78: MONTEREY | P78: 93940 | Q78: STEVEN PACKER | R78: 258 | S78: 220 | T78: 220 | U78: 1515 | V78: 87 | W78: 501 | X78: 0 | Y78: 0 | Z78: 0 | AA78: 282 | AB78: 749 | AC78: 4 | AD78: 20 | AE78: 3158 | AF78: 0 | AG78: 8193 | AH78: 393 | AI78: 2517 | AJ78: 0 | AK78: 0 | AL78: 0 | AM78: 1050 | AN78: 3293 | AO78: 24 | AP78: 101 | AQ78: 15571 | AR78: 0 | AS78: =Append1[[#This Row],[DAY_MCAR]]+Append1[[#This Row],[DAY_MCAR_MC]]+Append1[[#This Row],[DAY_MCAL]]+Append1[[#This Row],[DAY_MCAL_MC]]+Append1[[#This Row],[DAY_CNTY]]+Append1[[#This Row],[DAY_CNTY_MC]]+Append1[[#This Row],[DAY_THRD]]+Append1[[#This Row],[DAY_THRD_MC]]+Append1[[#This Row],[DAY_INDGNT]]+Append1[[#This Row],[DAY_OTH]]+Append1[[#This Row],[DAY_TOT]]+Append1[[#This Row],[DAY_LTC]] -> 31142 | AT78: 38920 | AU78: 2644 | AV78: 11994 | AW78: 0 | AX78: 0 | AY78: 0 | AZ78: 4222 | BA78: 26016 | BB78: 911 | BC78: 1260 | BD78: 85967 | BE78: 158814705 | BF78: 9589984 | BG78: 42592686 | BH78: 0 | BI78: 0 | BJ78: 0 | BK78: 18124769 | BL78: 54660275 | BM78: 849822 | BN78: 1854834 | BO78: 286487075 | BP78: 67218910 | BQ78: 3964082 | BR78: 24275356 | BS78: 0 | BT78: 0 | BU78: 0 | BV78: 8326585 | BW78: 42563895 | BX78: 1039356 | BY78: 3691333 | BZ78: 151079517 | CA78: 338618 | CB78: 188889400 | CC78: 10481052 | CD78: 58564463 | CE78: 0 | CF78: 0 | CG78: 0 | CH78: 0 | CI78: 22401514 | CJ78: 13591342 | CK78: 0 | CL78: 3203176 | CM78: 0 | CN78: 0 | CO78: 0 | CP78: 4903290 | CQ78: 302372855 | CR78: 841183 | CS78: 0 | CT78: 0 | CU78: 0 | CV78: 841183 | CW78: 37141168 | CX78: 3914197 | CY78: 8301547 | CZ78: 0 | DA78: 0 | DB78: 0 | DC78: 3118215 | DD78: 79630010 | DE78: 0 | DF78: 3929783 | DG78: 136034920 | DH78: 8243175 | DI78: 128590040 | DJ78: 0 | DK78: 666538 | DL78: 0 | DM78: 0 | DN78: 0 | DO78: 0 | DP78: 2733102 | DQ78: 249695135 | DR78: 0 | DS78: 0 | DT78: 0 | DU78: 0 | DV78: 0 | DW78: 0 | DX78: 0 | DY78: 0 | DZ78: 0 | EA78: 0 | EB78: 0 | EC78: 0 | ED78: 0
A79: 106560473 | B79: COMMUNITY MEMORIAL HOSPITAL OF SAN BUENAVENTURA | C79: 20174 | D79: 43009 | E79: 43100 | F79: Open | G79: Ventura | H79: 10 | I79: 809 | J79: Non Profit Corp. | K79: Comparable | M79: 805-652-5001 | N79: 147 N. BRENT STREET | O79: VENTURA | P79: 93003 | Q79: GARY WILDE | R79: 242 | S79: 242 | T79: 121 | U79: 663 | V79: 567 | W79: 146 | X79: 582 | Y79: 0 | Z79: 0 | AA79: 54 | AB79: 976 | AC79: 5 | AD79: 4 | AE79: 2997 | AF79: 0 | AG79: 3309 | AH79: 2224 | AI79: 743 | AJ79: 1236 | AK79: 0 | AL79: 0 | AM79: 150 | AN79: 3353 | AO79: 23 | AP79: 53 | AQ79: 11091 | AR79: 0 | AS79: =Append1[[#This Row],[DAY_MCAR]]+Append1[[#This Row],[DAY_MCAR_MC]]+Append1[[#This Row],[DAY_MCAL]]+Append1[[#This Row],[DAY_MCAL_MC]]+Append1[[#This Row],[DAY_CNTY]]+Append1[[#This Row],[DAY_CNTY_MC]]+Append1[[#This Row],[DAY_THRD]]+Append1[[#This Row],[DAY_THRD_MC]]+Append1[[#This Row],[DAY_INDGNT]]+Append1[[#This Row],[DAY_OTH]]+Append1[[#This Row],[DAY_TOT]]+Append1[[#This Row],[DAY_LTC]] -> 22182 | AT79: 20004 | AU79: 5945 | AV79: 6185 | AW79: 29374 | AX79: 0 | AY79: 0 | AZ79: 6460 | BA79: 31293 | BB79: 1065 | BC79: 784 | BD79: 101110 | BE79: 47355612 | BF79: 39215239 | BG79: 7207685 | BH79: 17321525 | BI79: 0 | BJ79: 0 | BK79: 2895406 | BL79: 52869809 | BM79: 568262 | BN79: 894269 | BO79: 168327807 | BP79: 41409709 | BQ79: 26624833 | BR79: 4149856 | BS79: 34319792 | BT79: 0 | BU79: 0 | BV79: 5464284 | BW79: 65934762 | BX79: 1233834 | BY79: 787225 | BZ79: 179924295 | CA79: 559937 | CB79: 67495364 | CC79: 49853530 | CD79: -16878036 | CE79: 47845049 | CF79: 0 | CG79: 0 | CH79: 0 | CI79: 6911687 | CJ79: 73717669 | CK79: 0 | CL79: 1802096 | CM79: 0 | CN79: 0 | CO79: 0 | CP79: 1684521 | CQ79: 232991817 | CR79: 0 | CS79: 1093206 | CT79: 0 | CU79: 0 | CV79: 1093206 | CW79: 21138372 | CX79: 15887706 | CY79: 28212454 | CZ79: 4810338 | DA79: 0 | DB79: 0 | DC79: 1408800 | DD79: 44587589 | DE79: 0 | DF79: 308232 | DG79: 116353491 | DH79: 2121967 | DI79: 107017515 | DJ79: 0 | DK79: 4761286 | DL79: 0 | DM79: 0 | DN79: 0 | DO79: 0 | DP79: 14971383 | DQ79: 504432837 | DR79: 0 | DS79: 0 | DT79: 0 | DU79: 0 | DV79: 0 | DW79: 0 | DX79: 0 | DY79: 0 | DZ79: 0 | EA79: 0 | EB79: 0 | EC79: 0 | ED79: 0
A80: 106100717 | B80: COMMUNITY REGIONAL MEDICAL CENTER - FRESNO | C80: 20174 | D80: 43009 | E80: 43100 | F80: Open | G80: Fresno | H80: 9 | I80: 605 | J80: Non Profit Corp. | K80: Comparable | L80: Teaching | M80: 559-459-6000 | N80: 2823 FRESNO STREET | O80: FRESNO | P80: 93721 | Q80: TIM A JOSLIN | R80: 909 | S80: 909 | T80: 741 | U80: 2420 | V80: 627 | W80: 1875 | X80: 3463 | Y80: 0 | Z80: 0 | AA80: 227 | AB80: 1370 | AC80: 272 | AD80: 0 | AE80: 10254 | AF80: 72 | AG80: 17665 | AH80: 4173 | AI80: 18416 | AJ80: 17393 | AK80: 0 | AL80: 0 | AM80: 1389 | AN80: 8385 | AO80: 703 | AP80: 0 | AQ80: 68124 | AR80: 9399 | AS80: =Append1[[#This Row],[DAY_MCAR]]+Append1[[#This Row],[DAY_MCAR_MC]]+Append1[[#This Row],[DAY_MCAL]]+Append1[[#This Row],[DAY_MCAL_MC]]+Append1[[#This Row],[DAY_CNTY]]+Append1[[#This Row],[DAY_CNTY_MC]]+Append1[[#This Row],[DAY_THRD]]+Append1[[#This Row],[DAY_THRD_MC]]+Append1[[#This Row],[DAY_INDGNT]]+Append1[[#This Row],[DAY_OTH]]+Append1[[#This Row],[DAY_TOT]]+Append1[[#This Row],[DAY_LTC]] -> 145647 | AT80: 17659 | AU80: 7516 | AV80: 14966 | AW80: 56883 | AX80: 0 | AY80: 0 | AZ80: 2241 | BA80: 11435 | BB80: 6680 | BC80: 0 | BD80: 117380 | BE80: 241692014 | BF80: 58891970 | BG80: 156935821 | BH80: 223595060 | BI80: 0 | BJ80: 0 | BK80: 24721082 | BL80: 138444810 | BM80: 9593301 | BN80: 0 | BO80: 853874058 | BP80: 99524037 | BQ80: 24156209 | BR80: 19050115 | BS80: 106133418 | BT80: 0 | BU80: 0 | BV80: 4560132 | BW80: 76240443 | BX80: 9376165 | BY80: 0 | BZ80: 339040519 | CA80: 27910594 | CB80: 254195734 | CC80: 68142015 | CD80: 160340446 | CE80: 282999949 | CF80: -13153498 | CG80: 0 | CH80: 0 | CI80: 7865905 | CJ80: 131322146 | CK80: 0 | CL80: 3420831 | CM80: 0 | CN80: 0 | CO80: 0 | CP80: 0 | CQ80: 923044122 | CR80: 0 | CS80: 0 | CT80: 0 | CU80: 140314 | CV80: 140314 | CW80: 85815594 | CX80: 14612948 | CY80: 28798988 | CZ80: 46728529 | DA80: 0 | DB80: 0 | DC80: 20059458 | DD80: 73562532 | DE80: 432720 | DF80: 0 | DG80: 270010769 | DH80: 7348023 | DI80: 264964357 | DJ80: 29804815 | DK80: 5398007 | DL80: 0 | DM80: 0 | DN80: 0 | DO80: 0 | DP80: 47199809 | DQ80: 430401441 | DR80: 0 | DS80: 0 | DT80: 0 | DU80: 0 | DV80: 0 | DW80: 0 | DX80: 0 | DY80: 0 | DZ80: 0 | EA80: 0 | EB80: 0 | EC80: 0 | ED80: 0
A81: 106070924 | B81: CONTRA COSTA REGIONAL MEDICAL CENTER | C81: 20174 | D81: 43009 | E81: 43100 | F81: Open | G81: Contra Costa | H81: 5 | I81: 411 | J81: City/County | K81: Comparable | M81: 925-370-5000 | N81: 2500 ALHAMBRA AVENUE | O81: MARTINEZ | P81: 94553 | Q81: PATRICK GODLEY | R81: 146 | S81: 146 | T81: 116 | U81: 408 | V81: 2 | W81: 545 | X81: 731 | Y81: 31 | Z81: 0 | AA81: 117 | AB81: 44 | AC81: 0 | AD81: 2 | AE81: 1880 | AF81: 0 | AG81: 3075 | AH81: 2 | AI81: 3002 | AJ81: 3177 | AK81: 269 | AL81: 0 | AM81: 776 | AN81: 277 | AO81: 0 | AP81: 6 | AQ81: 10584 | AR81: 0 | AS81: =Append1[[#This Row],[DAY_MCAR]]+Append1[[#This Row],[DAY_MCAR_MC]]+Append1[[#This Row],[DAY_MCAL]]+Append1[[#This Row],[DAY_MCAL_MC]]+Append1[[#This Row],[DAY_CNTY]]+Append1[[#This Row],[DAY_CNTY_MC]]+Append1[[#This Row],[DAY_THRD]]+Append1[[#This Row],[DAY_THRD_MC]]+Append1[[#This Row],[DAY_INDGNT]]+Append1[[#This Row],[DAY_OTH]]+Append1[[#This Row],[DAY_TOT]]+Append1[[#This Row],[DAY_LTC]] -> 21168 | AT81: 19396 | AU81: 989 | AV81: 22955 | AW81: 70207 | AX81: 2093 | AY81: 0 | AZ81: 2941 | BA81: 7254 | BB81: 0 | BC81: 45 | BD81: 125880 | BE81: 26792243 | BF81: 28381 | BG81: 22976229 | BH81: 30701750 | BI81: 1449284 | BJ81: 0 | BK81: 5376130 | BL81: 1814064 | BM81: 0 | BN81: 141325 | BO81: 89279406 | BP81: 18801064 | BQ81: 773483 | BR81: 16171012 | BS81: 52928338 | BT81: 3369465 | BU81: 0 | BV81: 3768218 | BW81: 8917859 | BX81: 0 | BY81: 117520 | BZ81: 104846959 | CA81: 20242 | CB81: 32140114 | CC81: 389822 | CD81: 4575431 | CE81: 25057553 | CF81: 0 | CG81: 3504067 | CH81: 0 | CI81: 5509447 | CJ81: 9350482 | CK81: 0 | CL81: 0 | CM81: 0 | CN81: 0 | CO81: 0 | CP81: 0 | CQ81: 80547158 | CR81: 0 | CS81: 0 | CT81: 0 | CU81: 0 | CV81: 0 | CW81: 13453193 | CX81: 412042 | CY81: 34571810 | CZ81: 58572535 | DA81: 1314682 | DB81: 0 | DC81: 3634901 | DD81: 1381441 | DE81: 0 | DF81: 238603 | DG81: 113579207 | DH81: 19429683 | DI81: 150071821 | DJ81: 27570630 | DK81: 8170542 | DL81: 0 | DM81: 0 | DN81: 0 | DO81: 0 | DP81: 1597015 | DQ81: 145119291 | DR81: 0 | DS81: 0 | DT81: 0 | DU81: 0 | DV81: 0 | DW81: 0 | DX81: 0 | DY81: 0 | DZ81: 0 | EA81: 0 | EB81: 0 | EC81: 0 | ED81: 0
A82: 106331152 | B82: CORONA REGIONAL MEDICAL CENTER - MAIN | C82: 20174 | D82: 43009 | E82: 43100 | F82: Open | G82: Riverside | H82: 12 | I82: 1111 | J82: Non Profit Corp. | K82: Comparable | M82: 951-737-4343 | N82: 800 SOUTH MAIN STREET | O82: CORONA | P82: 92882 | Q82: MARK UFFER | R82: 238 | S82: 238 | T82: 141 | U82: 636 | V82: 458 | W82: 335 | X82: 594 | Y82: 0 | Z82: 0 | AA82: 31 | AB82: 246 | AC82: 10 | AD82: 53 | AE82: 2363 | AF82: 0 | AG82: 2078 | AH82: 2555 | AI82: 2442 | AJ82: 4083 | AK82: 0 | AL82: 0 | AM82: 128 | AN82: 1398 | AO82: 23 | AP82: 228 | AQ82: 12935 | AR82: 0 | AS82: =Append1[[#This Row],[DAY_MCAR]]+Append1[[#This Row],[DAY_MCAR_MC]]+Append1[[#This Row],[DAY_MCAL]]+Append1[[#This Row],[DAY_MCAL_MC]]+Append1[[#This Row],[DAY_CNTY]]+Append1[[#This Row],[DAY_CNTY_MC]]+Append1[[#This Row],[DAY_THRD]]+Append1[[#This Row],[DAY_THRD_MC]]+Append1[[#This Row],[DAY_INDGNT]]+Append1[[#This Row],[DAY_OTH]]+Append1[[#This Row],[DAY_TOT]]+Append1[[#This Row],[DAY_LTC]] -> 25870 | AT82: 14681 | AU82: 5220 | AV82: 1170 | AW82: 4824 | AX82: 0 | AY82: 0 | AZ82: 577 | BA82: 3970 | BB82: 190 | BC82: 1150 | BD82: 31782 | BE82: 27249389 | BF82: 26687178 | BG82: 19012735 | BH82: 35885705 | BI82: 0 | BJ82: 0 | BK82: 2247132 | BL82: 14473351 | BM82: 259378 | BN82: 2203870 | BO82: 128018738 | BP82: 16599055 | BQ82: 18637993 | BR82: 3990111 | BS82: 27457983 | BT82: 0 | BU82: 0 | BV82: 1964260 | BW82: 21953895 | BX82: 420647 | BY82: 4632094 | BZ82: 95656038 | CA82: 1738571 | CB82: 34807039 | CC82: 38731288 | CD82: 11593902 | CE82: 54413589 | CF82: 0 | CG82: 0 | CH82: 0 | CI82: 3062768 | CJ82: 28173893 | CK82: 0 | CL82: 680025 | CM82: 0 | CN82: 0 | CO82: 0 | CP82: 3797759 | CQ82: 176998834 | CR82: 0 | CS82: 0 | CT82: 0 | CU82: 0 | CV82: 0 | CW82: 9041405 | CX82: 6593883 | CY82: 11408944 | CZ82: 8930099 | DA82: 0 | DB82: 0 | DC82: 1148624 | DD82: 8253353 | DE82: 0 | DF82: 1299634 | DG82: 46675942 | DH82: 126951 | DI82: 48167705 | DJ82: 0 | DK82: 94528 | DL82: 0 | DM82: 0 | DN82: 0 | DO82: 0 | DP82: 3664881 | DQ82: 95259870 | DR82: 0 | DS82: 43 | DT82: 169 | DU82: 327 | DV82: 1850083 | DW82: 1338094 | DX82: 2450767 | DY82: 0 | DZ82: 0 | EA82: 737410 | EB82: 5457390 | EC82: 7442975 | ED82: 0
A83: 106154160 | B83: CRESTWOOD BAKERSFIELD - PHF | C83: 20174 | D83: 43009 | E83: 43100 | F83: Open | G83: Kern | H83: 9 | I83: 617 | J83: Investor - Corp. | K83: Psychiatric Health Facilities | M83: 209-478-5291 | N83: 6700 EUCALYPTUS DRIVE, SUITE C | O83: BAKERSFIELD | P83: 93306 | Q83: LORI BLACKBURN | R83: 16 | S83: 16 | T83: 16 | U83: 0 | V83: 0 | W83: 0 | X83: 0 | Y83: 123 | Z83: 0 | AA83: 0 | AB83: 0 | AC83: 0 | AD83: 0 | AE83: 123 | AF83: 0 | AG83: 0 | AH83: 0 | AI83: 0 | AJ83: 0 | AK83: 1108 | AL83: 0 | AM83: 0 | AN83: 0 | AO83: 0 | AP83: 0 | AQ83: 1108 | AR83: 0 | AS83: =Append1[[#This Row],[DAY_MCAR]]+Append1[[#This Row],[DAY_MCAR_MC]]+Append1[[#This Row],[DAY_MCAL]]+Append1[[#This Row],[DAY_MCAL_MC]]+Append1[[#This Row],[DAY_CNTY]]+Append1[[#This Row],[DAY_CNTY_MC]]+Append1[[#This Row],[DAY_THRD]]+Append1[[#This Row],[DAY_THRD_MC]]+Append1[[#This Row],[DAY_INDGNT]]+Append1[[#This Row],[DAY_OTH]]+Append1[[#This Row],[DAY_TOT]]+Append1[[#This Row],[DAY_LTC]] -> 2216 | AT83: 0 | AU83: 0 | AV83: 0 | AW83: 0 | AX83: 0 | AY83: 0 | AZ83: 0 | BA83: 0 | BB83: 0 | BC83: 0 | BD83: 0 | BE83: 0 | BF83: 0 | BG83: 0 | BH83: 0 | BI83: 993416 | BJ83: 0 | BK83: 0 | BL83: 0 | BM83: 0 | BN83: 0 | BO83: 993416 | BP83: 0 | BQ83: 0 | BR83: 0 | BS83: 0 | BT83: 0 | BU83: 0 | BV83: 0 | BW83: 0 | BX83: 0 | BY83: 0 | BZ83: 0 | CA83: 0 | CB83: 0 | CC83: 0 | CD83: 0 | CE83: 0 | CF83: 0 | CG83: 0 | CH83: 0 | CI83: 0 | CJ83: 0 | CK83: 0 | CL83: 0 | CM83: 0 | CN83: 0 | CO83: 0 | CP83: 0 | CQ83: 0 | CR83: 0 | CS83: 0 | CT83: 0 | CU83: 0 | CV83: 0 | CW83: 0 | CX83: 0 | CY83: 0 | CZ83: 0 | DA83: 993416 | DB83: 0 | DC83: 0 | DD83: 0 | DE83: 0 | DF83: 0 | DG83: 993416 | DH83: 6108 | DI83: 890224 | DJ83: 114150 | DK83: 0 | DL83: 0 | DM83: 0 | DN83: 0 | DO83: 0 | DP83: 27449 | DQ83: 115876 | DR83: 0 | DS83: 0 | DT83: 0 | DU83: 0 | DV83: 0 | DW83: 0 | DX83: 0 | DY83: 0 | DZ83: 0 | EA83: 0 | EB83: 0 | EC83: 0 | ED83: 0
A84: 106344170 | B84: CRESTWOOD CARMICHAEL - PHF | C84: 20174 | D84: 43009 | E84: 43100 | F84: Open | G84: Sacramento | H84: 2 | I84: 311 | J84: Investor - Corp. | K84: Psychiatric Health Facilities | M84: 209-478-5291 | N84: 4741 ENGLE ROAD | O84: CARMICHAEL | P84: 95608 | Q84: LORI BLACKBURN | R84: 16 | S84: 16 | T84: 16 | U84: 0 | V84: 0 | W84: 0 | X84: 0 | Y84: 164 | Z84: 0 | AA84: 0 | AB84: 0 | AC84: 0 | AD84: 0 | AE84: 164 | AF84: 0 | AG84: 0 | AH84: 0 | AI84: 0 | AJ84: 0 | AK84: 1466 | AL84: 0 | AM84: 0 | AN84: 0 | AO84: 0 | AP84: 0 | AQ84: 1466 | AR84: 0 | AS84: =Append1[[#This Row],[DAY_MCAR]]+Append1[[#This Row],[DAY_MCAR_MC]]+Append1[[#This Row],[DAY_MCAL]]+Append1[[#This Row],[DAY_MCAL_MC]]+Append1[[#This Row],[DAY_CNTY]]+Append1[[#This Row],[DAY_CNTY_MC]]+Append1[[#This Row],[DAY_THRD]]+Append1[[#This Row],[DAY_THRD_MC]]+Append1[[#This Row],[DAY_INDGNT]]+Append1[[#This Row],[DAY_OTH]]+Append1[[#This Row],[DAY_TOT]]+Append1[[#This Row],[DAY_LTC]] -> 2932 | AT84: 0 | AU84: 0 | AV84: 0 | AW84: 0 | AX84: 0 | AY84: 0 | AZ84: 0 | BA84: 0 | BB84: 0 | BC84: 0 | BD84: 0 | BE84: 0 | BF84: 0 | BG84: 0 | BH84: 0 | BI84: 1189116 | BJ84: 0 | BK84: 0 | BL84: 0 | BM84: 0 | BN84: 0 | BO84: 1189116 | BP84: 0 | BQ84: 0 | BR84: 0 | BS84: 0 | BT84: 0 | BU84: 0 | BV84: 0 | BW84: 0 | BX84: 0 | BY84: 0 | BZ84: 0 | CA84: 0 | CB84: 0 | CC84: 0 | CD84: 0 | CE84: 0 | CF84: 0 | CG84: 0 | CH84: 0 | CI84: 0 | CJ84: 0 | CK84: 0 | CL84: 0 | CM84: 0 | CN84: 0 | CO84: 0 | CP84: 0 | CQ84: 0 | CR84: 0 | CS84: 0 | CT84: 0 | CU84: 0 | CV84: 0 | CW84: 0 | CX84: 0 | CY84: 0 | CZ84: 0 | DA84: 1189116 | DB84: 0 | DC84: 0 | DD84: 0 | DE84: 0 | DF84: 0 | DG84: 1189116 | DH84: 4866 | DI84: 983622 | DJ84: 158464 | DK84: 0 | DL84: 0 | DM84: 0 | DN84: 0 | DO84: 0 | DP84: 9311 | DQ84: 203397 | DR84: 0 | DS84: 0 | DT84: 0 | DU84: 0 | DV84: 0 | DW84: 0 | DX84: 0 | DY84: 0 | DZ84: 0 | EA84: 0 | EB84: 0 | EC84: 0 | ED84: 0
A85: 106344188 | B85: CRESTWOOD SACRAMENTO - PHF | C85: 20174 | D85: 43009 | E85: 43100 | F85: Open | G85: Sacramento | H85: 2 | I85: 311 | J85: Investor - Corp. | K85: Psychiatric Health Facilities | M85: 209-478-5291 | N85: 2600 STOCKTON BOULEVARD, SUITE B | O85: SACRAMENTO | P85: 95817 | Q85: LORI BLACKBURN | R85: 16 | S85: 16 | T85: 16 | U85: 0 | V85: 0 | W85: 0 | X85: 0 | Y85: 116 | Z85: 0 | AA85: 0 | AB85: 0 | AC85: 0 | AD85: 0 | AE85: 116 | AF85: 0 | AG85: 0 | AH85: 0 | AI85: 0 | AJ85: 0 | AK85: 1467 | AL85: 0 | AM85: 0 | AN85: 0 | AO85: 0 | AP85: 0 | AQ85: 1467 | AR85: 0 | AS85: =Append1[[#This Row],[DAY_MCAR]]+Append1[[#This Row],[DAY_MCAR_MC]]+Append1[[#This Row],[DAY_MCAL]]+Append1[[#This Row],[DAY_MCAL_MC]]+Append1[[#This Row],[DAY_CNTY]]+Append1[[#This Row],[DAY_CNTY_MC]]+Append1[[#This Row],[DAY_THRD]]+Append1[[#This Row],[DAY_THRD_MC]]+Append1[[#This Row],[DAY_INDGNT]]+Append1[[#This Row],[DAY_OTH]]+Append1[[#This Row],[DAY_TOT]]+Append1[[#This Row],[DAY_LTC]] -> 2934 | AT85: 0 | AU85: 0 | AV85: 0 | AW85: 0 | AX85: 0 | AY85: 0 | AZ85: 0 | BA85: 0 | BB85: 0 | BC85: 0 | BD85: 0 | BE85: 0 | BF85: 0 | BG85: 0 | BH85: 0 | BI85: 1199434 | BJ85: 0 | BK85: 0 | BL85: 0 | BM85: 0 | BN85: 0 | BO85: 1199434 | BP85: 0 | BQ85: 0 | BR85: 0 | BS85: 0 | BT85: 0 | BU85: 0 | BV85: 0 | BW85: 0 | BX85: 0 | BY85: 0 | BZ85: 0 | CA85: 0 | CB85: 0 | CC85: 0 | CD85: 0 | CE85: 0 | CF85: 0 | CG85: 0 | CH85: 0 | CI85: 0 | CJ85: 0 | CK85: 0 | CL85: 0 | CM85: 0 | CN85: 0 | CO85: 0 | CP85: 0 | CQ85: 0 | CR85: 0 | CS85: 0 | CT85: 0 | CU85: 0 | CV85: 0 | CW85: 0 | CX85: 0 | CY85: 0 | CZ85: 0 | DA85: 1199434 | DB85: 0 | DC85: 0 | DD85: 0 | DE85: 0 | DF85: 0 | DG85: 1199434 | DH85: 4088 | DI85: 967489 | DJ85: 145700 | DK85: 0 | DL85: 0 | DM85: 0 | DN85: 0 | DO85: 0 | DP85: 8371 | DQ85: 144789 | DR85: 0 | DS85: 0 | DT85: 0 | DU85: 0 | DV85: 0 | DW85: 0 | DX85: 0 | DY85: 0 | DZ85: 0 | EA85: 0 | EB85: 0 | EC85: 0 | ED85: 0
A86: 106434220 | B86: CRESTWOOD SAN JOSE - PHF | C86: 20174 | D86: 43009 | E86: 43100 | F86: Open | G86: Santa Clara | H86: 7 | I86: 431 | J86: Investor - Corp. | K86: Psychiatric Health Facilities | M86: 209-478-5291 | N86: 1425 FRUITDALE AVENUE | O86: SAN JOSE | P86: 95128 | Q86: LORI BLACKBURN | R86: 16 | S86: 16 | T86: 16 | U86: 0 | V86: 0 | W86: 0 | X86: 0 | Y86: 34 | Z86: 0 | AA86: 0 | AB86: 0 | AC86: 0 | AD86: 0 | AE86: 34 | AF86: 0 | AG86: 0 | AH86: 0 | AI86: 0 | AJ86: 0 | AK86: 642 | AL86: 0 | AM86: 0 | AN86: 0 | AO86: 0 | AP86: 0 | AQ86: 642 | AR86: 0 | AS86: =Append1[[#This Row],[DAY_MCAR]]+Append1[[#This Row],[DAY_MCAR_MC]]+Append1[[#This Row],[DAY_MCAL]]+Append1[[#This Row],[DAY_MCAL_MC]]+Append1[[#This Row],[DAY_CNTY]]+Append1[[#This Row],[DAY_CNTY_MC]]+Append1[[#This Row],[DAY_THRD]]+Append1[[#This Row],[DAY_THRD_MC]]+Append1[[#This Row],[DAY_INDGNT]]+Append1[[#This Row],[DAY_OTH]]+Append1[[#This Row],[DAY_TOT]]+Append1[[#This Row],[DAY_LTC]] -> 1284 | AT86: 0 | AU86: 0 | AV86: 0 | AW86: 0 | AX86: 0 | AY86: 0 | AZ86: 0 | BA86: 0 | BB86: 0 | BC86: 0 | BD86: 0 | BE86: 0 | BF86: 0 | BG86: 0 | BH86: 0 | BI86: 616320 | BJ86: 0 | BK86: 0 | BL86: 0 | BM86: 0 | BN86: 0 | BO86: 616320 | BP86: 0 | BQ86: 0 | BR86: 0 | BS86: 0 | BT86: 0 | BU86: 0 | BV86: 0 | BW86: 0 | BX86: 0 | BY86: 0 | BZ86: 0 | CA86: 0 | CB86: 0 | CC86: 0 | CD86: 0 | CE86: 0 | CF86: 0 | CG86: 0 | CH86: 0 | CI86: 0 | CJ86: 0 | CK86: 0 | CL86: 0 | CM86: 0 | CN86: 0 | CO86: 0 | CP86: 0 | CQ86: 0 | CR86: 0 | CS86: 0 | CT86: 0 | CU86: 0 | CV86: 0 | CW86: 0 | CX86: 0 | CY86: 0 | CZ86: 0 | DA86: 616320 | DB86: 0 | DC86: 0 | DD86: 0 | DE86: 0 | DF86: 0 | DG86: 616320 | DH86: 796800 | DI86: 1077013 | DJ86: 155775 | DK86: 0 | DL86: 0 | DM86: 0 | DN86: 0 | DO86: 0 | DP86: 12005 | DQ86: 591178 | DR86: 0 | DS86: 0 | DT86: 0 | DU86: 0 | DV86: 0 | DW86: 0 | DX86: 0 | DY86: 0 | DZ86: 0 | EA86: 0 | EB86: 0 | EC86: 0 | ED86: 0
A87: 106484062 | B87: CRESTWOOD SOLANO - PHF | C87: 20174 | D87: 43009 | E87: 43100 | F87: Open | G87: Solano | H87: 3 | I87: 408 | J87: Investor - Corp. | K87: Psychiatric Health Facilities | M87: 209-478-5291 | N87: 2201 TUOLUMNE STREET | O87: VALLEJO | P87: 94589 | Q87: LORI BLACKBURN | R87: 16 | S87: 16 | T87: 16 | U87: 0 | V87: 0 | W87: 0 | X87: 0 | Y87: 126 | Z87: 0 | AA87: 0 | AB87: 0 | AC87: 0 | AD87: 0 | AE87: 126 | AF87: 0 | AG87: 0 | AH87: 0 | AI87: 0 | AJ87: 0 | AK87: 1153 | AL87: 0 | AM87: 0 | AN87: 0 | AO87: 0 | AP87: 0 | AQ87: 1153 | AR87: 0 | AS87: =Append1[[#This Row],[DAY_MCAR]]+Append1[[#This Row],[DAY_MCAR_MC]]+Append1[[#This Row],[DAY_MCAL]]+Append1[[#This Row],[DAY_MCAL_MC]]+Append1[[#This Row],[DAY_CNTY]]+Append1[[#This Row],[DAY_CNTY_MC]]+Append1[[#This Row],[DAY_THRD]]+Append1[[#This Row],[DAY_THRD_MC]]+Append1[[#This Row],[DAY_INDGNT]]+Append1[[#This Row],[DAY_OTH]]+Append1[[#This Row],[DAY_TOT]]+Append1[[#This Row],[DAY_LTC]] -> 2306 | AT87: 0 | AU87: 0 | AV87: 0 | AW87: 0 | AX87: 0 | AY87: 0 | AZ87: 0 | BA87: 0 | BB87: 0 | BC87: 0 | BD87: 0 | BE87: 0 | BF87: 0 | BG87: 0 | BH87: 0 | BI87: 993395 | BJ87: 0 | BK87: 0 | BL87: 0 | BM87: 0 | BN87: 0 | BO87: 993395 | BP87: 0 | BQ87: 0 | BR87: 0 | BS87: 0 | BT87: 0 | BU87: 0 | BV87: 0 | BW87: 0 | BX87: 0 | BY87: 0 | BZ87: 0 | CA87: 0 | CB87: 0 | CC87: 0 | CD87: 0 | CE87: 0 | CF87: 0 | CG87: 0 | CH87: 0 | CI87: 0 | CJ87: 0 | CK87: 0 | CL87: 0 | CM87: 0 | CN87: 0 | CO87: 0 | CP87: 0 | CQ87: 0 | CR87: 0 | CS87: 0 | CT87: 0 | CU87: 0 | CV87: 0 | CW87: 0 | CX87: 0 | CY87: 0 | CZ87: 0 | DA87: 993395 | DB87: 0 | DC87: 0 | DD87: 0 | DE87: 0 | DF87: 0 | DG87: 993395 | DH87: 279718 | DI87: 1148039 | DJ87: 188500 | DK87: 0 | DL87: 0 | DM87: 0 | DN87: 0 | DO87: 0 | DP87: 32110 | DQ87: 169452 | DR87: 0 | DS87: 0 | DT87: 0 | DU87: 0 | DV87: 0 | DW87: 0 | DX87: 0 | DY87: 0 | DZ87: 0 | EA87: 0 | EB87: 0 | EC87: 0 | ED87: 0
A88: 106390846 | B88: DAMERON HOSPITAL ASSOCIATION | C88: 20174 | D88: 43009 | E88: 43100 | F88: Open | G88: San Joaquin | H88: 6 | I88: 507 | J88: Non Profit Corp. | K88: Comparable | M88: 209-944-5550 | N88: 525 WEST ACACIA STREET | O88: STOCKTON | P88: 95203 | Q88: LORRAINE AUERBACH | R88: 202 | S88: 202 | T88: 38 | U88: 285 | V88: 162 | W88: 61 | X88: 201 | Y88: 0 | Z88: 0 | AA88: 11 | AB88: 132 | AC88: 0 | AD88: 10 | AE88: 862 | AF88: 0 | AG88: 1143 | AH88: 662 | AI88: 234 | AJ88: 962 | AK88: 0 | AL88: 0 | AM88: 40 | AN88: 357 | AO88: 0 | AP88: 48 | AQ88: 3446 | AR88: 0 | AS88: =Append1[[#This Row],[DAY_MCAR]]+Append1[[#This Row],[DAY_MCAR_MC]]+Append1[[#This Row],[DAY_MCAL]]+Append1[[#This Row],[DAY_MCAL_MC]]+Append1[[#This Row],[DAY_CNTY]]+Append1[[#This Row],[DAY_CNTY_MC]]+Append1[[#This Row],[DAY_THRD]]+Append1[[#This Row],[DAY_THRD_MC]]+Append1[[#This Row],[DAY_INDGNT]]+Append1[[#This Row],[DAY_OTH]]+Append1[[#This Row],[DAY_TOT]]+Append1[[#This Row],[DAY_LTC]] -> 6892 | AT88: 2630 | AU88: 1050 | AV88: 1012 | AW88: 5948 | AX88: 0 | AY88: 0 | AZ88: 1266 | BA88: 1472 | BB88: 0 | BC88: 1279 | BD88: 14657 | BE88: 40882892 | BF88: 22185169 | BG88: 8854763 | BH88: 24864517 | BI88: 0 | BJ88: 0 | BK88: 1780097 | BL88: 15903720 | BM88: 0 | BN88: 2273876 | BO88: 116745034 | BP88: 26237411 | BQ88: 14890547 | BR88: 7379480 | BS88: 40592285 | BT88: 0 | BU88: 0 | BV88: 6214125 | BW88: 14239046 | BX88: 0 | BY88: 6664844 | BZ88: 116217738 | CA88: 1478399 | CB88: 58884642 | CC88: 32552479 | CD88: 14344577 | CE88: 58099457 | CF88: 0 | CG88: 0 | CH88: 0 | CI88: 6709551 | CJ88: 22812045 | CK88: 0 | CL88: 0 | CM88: 0 | CN88: 0 | CO88: 0 | CP88: 5560177 | CQ88: 200441327 | CR88: 4045394 | CS88: 0 | CT88: 0 | CU88: 0 | CV88: 4045394 | CW88: 8235661 | CX88: 8568631 | CY88: 1889666 | CZ88: 7357345 | DA88: 0 | DB88: 0 | DC88: 1284671 | DD88: 5852322 | DE88: 0 | DF88: 3378543 | DG88: 36566839 | DH88: 770119 | DI88: 32465173 | DJ88: 760031 | DK88: 1324481 | DL88: 0 | DM88: 0 | DN88: 4167141 | DO88: 0 | DP88: 1935985 | DQ88: 62348123 | DR88: 0 | DS88: 0 | DT88: 0 | DU88: 0 | DV88: 0 | DW88: 0 | DX88: 0 | DY88: 0 | DZ88: 0 | EA88: 0 | EB88: 0 | EC88: 0 | ED88: 0
A89: 106190232 | B89: DEL AMO HOSPITAL | C89: 20174 | D89: 43009 | E89: 43100 | F89: Open | G89: Los Angeles | H89: 11 | I89: 931 | J89: Investor - Corp. | K89: Comparable | M89: 310-530-1151 | N89: 23700 CAMINO DEL SOL | O89: TORRANCE | P89: 90505 | Q89: LISA MONTES | R89: 166 | S89: 166 | T89: 166 | U89: 285 | V89: 38 | W89: 626 | X89: 0 | Y89: 0 | Z89: 0 | AA89: 145 | AB89: 467 | AC89: 6 | AD89: 63 | AE89: 1630 | AF89: 0 | AG89: 2424 | AH89: 344 | AI89: 3441 | AJ89: 0 | AK89: 0 | AL89: 0 | AM89: 1159 | AN89: 3057 | AO89: 30 | AP89: 532 | AQ89: 10987 | AR89: 0 | AS89: =Append1[[#This Row],[DAY_MCAR]]+Append1[[#This Row],[DAY_MCAR_MC]]+Append1[[#This Row],[DAY_MCAL]]+Append1[[#This Row],[DAY_MCAL_MC]]+Append1[[#This Row],[DAY_CNTY]]+Append1[[#This Row],[DAY_CNTY_MC]]+Append1[[#This Row],[DAY_THRD]]+Append1[[#This Row],[DAY_THRD_MC]]+Append1[[#This Row],[DAY_INDGNT]]+Append1[[#This Row],[DAY_OTH]]+Append1[[#This Row],[DAY_TOT]]+Append1[[#This Row],[DAY_LTC]] -> 21974 | AT89: 1908 | AU89: 118 | AV89: 0 | AW89: 0 | AX89: 0 | AY89: 0 | AZ89: 464 | BA89: 991 | BB89: 0 | BC89: 0 | BD89: 3481 | BE89: 4466070 | BF89: 652050 | BG89: 6505380 | BH89: 0 | BI89: 0 | BJ89: 0 | BK89: 2190510 | BL89: 5784490 | BM89: 57506 | BN89: 1117050 | BO89: 20773056 | BP89: 957587 | BQ89: 58760 | BR89: 0 | BS89: 0 | BT89: 0 | BU89: 0 | BV89: 231859 | BW89: 499081 | BX89: 0 | BY89: 0 | BZ89: 1747287 | CA89: 528231 | CB89: 2674982 | CC89: 387067 | CD89: 3809294 | CE89: 0 | CF89: 0 | CG89: 0 | CH89: 0 | CI89: 1091496 | CJ89: 3614947 | CK89: 0 | CL89: 57506 | CM89: 0 | CN89: 0 | CO89: 0 | CP89: 458973 | CQ89: 12622496 | CR89: 0 | CS89: 0 | CT89: 0 | CU89: 0 | CV89: 0 | CW89: 2220444 | CX89: 323743 | CY89: 2696086 | CZ89: 0 | DA89: 0 | DB89: 0 | DC89: 1330873 | DD89: 2227564 | DE89: 0 | DF89: 1099137 | DG89: 9897847 | DH89: 8206 | DI89: 7088238 | DJ89: 204395 | DK89: 9003 | DL89: 0 | DM89: 0 | DN89: 0 | DO89: 0 | DP89: 19793 | DQ89: 2137055 | DR89: 0 | DS89: 0 | DT89: 0 | DU89: 0 | DV89: 0 | DW89: 0 | DX89: 0 | DY89: 0 | DZ89: 0 | EA89: 0 | EB89: 0 | EC89: 0 | ED89: 0
A90: 106150706 | B90: DELANO REGIONAL MEDICAL CENTER | C90: 20174 | D90: 43009 | E90: 43100 | F90: Open | G90: Kern | H90: 9 | I90: 617 | J90: Non Profit Corp. | K90: Comparable | M90: 661-725-4800 | N90: 1401 GARCES HIGHWAY | O90: DELANO | P90: 93215 | Q90: BAHRAM GHAFFARI | R90: 156 | S90: 156 | T90: 156 | U90: 163 | V90: 39 | W90: 108 | X90: 275 | Y90: 0 | Z90: 0 | AA90: 18 | AB90: 27 | AC90: 0 | AD90: 17 | AE90: 647 | AF90: 8 | AG90: 2846 | AH90: 327 | AI90: 1810 | AJ90: 869 | AK90: 0 | AL90: 0 | AM90: 162 | AN90: 635 | AO90: 0 | AP90: 61 | AQ90: 6710 | AR90: 4489 | AS90: =Append1[[#This Row],[DAY_MCAR]]+Append1[[#This Row],[DAY_MCAR_MC]]+Append1[[#This Row],[DAY_MCAL]]+Append1[[#This Row],[DAY_MCAL_MC]]+Append1[[#This Row],[DAY_CNTY]]+Append1[[#This Row],[DAY_CNTY_MC]]+Append1[[#This Row],[DAY_THRD]]+Append1[[#This Row],[DAY_THRD_MC]]+Append1[[#This Row],[DAY_INDGNT]]+Append1[[#This Row],[DAY_OTH]]+Append1[[#This Row],[DAY_TOT]]+Append1[[#This Row],[DAY_LTC]] -> 17909 | AT90: 2861 | AU90: 597 | AV90: 3394 | AW90: 18003 | AX90: 0 | AY90: 0 | AZ90: 2067 | BA90: 1728 | BB90: 0 | BC90: 2750 | BD90: 31400 | BE90: 4172036 | BF90: 1671653 | BG90: 12391831 | BH90: 5841042 | BI90: 0 | BJ90: 0 | BK90: 571545 | BL90: 2123057 | BM90: 0 | BN90: 12101 | BO90: 26783265 | BP90: 3374573 | BQ90: 659399 | BR90: 2380522 | BS90: 11489550 | BT90: 0 | BU90: 0 | BV90: 2145601 | BW90: 1644282 | BX90: 0 | BY90: 1179875 | BZ90: 22873802 | CA90: 878316 | CB90: 6635755 | CC90: 2319260 | CD90: 220775 | CE90: 11719007 | CF90: -1037007 | CG90: 0 | CH90: 0 | CI90: 1399235 | CJ90: 2427876 | CK90: 0 | CL90: 0 | CM90: 0 | CN90: 0 | CO90: 0 | CP90: 0 | CQ90: 24563217 | CR90: 0 | CS90: 0 | CT90: 0 | CU90: 0 | CV90: 0 | CW90: 32538 | CX90: 11792 | CY90: 15588585 | CZ90: 5611585 | DA90: 0 | DB90: 0 | DC90: 1317911 | DD90: 1339463 | DE90: 0 | DF90: 1191976 | DG90: 25093850 | DH90: 208335 | DI90: 21517824 | DJ90: 0 | DK90: 0 | DL90: 0 | DM90: 0 | DN90: 0 | DO90: 0 | DP90: 271819 | DQ90: 45515738 | DR90: 0 | DS90: 0 | DT90: 0 | DU90: 0 | DV90: 0 | DW90: 0 | DX90: 0 | DY90: 0 | DZ90: 0 | EA90: 0 | EB90: 0 | EC90: 0 | ED90: 0
A91: 106331164 | B91: DESERT REGIONAL MEDICAL CENTER | C91: 20174 | D91: 43009 | E91: 43100 | F91: Open | G91: Riverside | H91: 12 | I91: 1105 | J91: Investor - Corp. | K91: Comparable | M91: 760-323-6511 | N91: 1150 NORTH INDIAN CANYON DRIVE | O91: PALM SPRINGS | P91: 92262 | Q91: MICHELE FINNEY | R91: 385 | S91: 351 | T91: 269 | U91: 895 | V91: 1194 | W91: 504 | X91: 1116 | Y91: 0 | Z91: 0 | AA91: 112 | AB91: 1060 | AC91: 31 | AD91: 34 | AE91: 4946 | AF91: 0 | AG91: 5332 | AH91: 5293 | AI91: 3592 | AJ91: 4629 | AK91: 0 | AL91: 0 | AM91: 749 | AN91: 3685 | AO91: 152 | AP91: 189 | AQ91: 23621 | AR91: 0 | AS91: =Append1[[#This Row],[DAY_MCAR]]+Append1[[#This Row],[DAY_MCAR_MC]]+Append1[[#This Row],[DAY_MCAL]]+Append1[[#This Row],[DAY_MCAL_MC]]+Append1[[#This Row],[DAY_CNTY]]+Append1[[#This Row],[DAY_CNTY_MC]]+Append1[[#This Row],[DAY_THRD]]+Append1[[#This Row],[DAY_THRD_MC]]+Append1[[#This Row],[DAY_INDGNT]]+Append1[[#This Row],[DAY_OTH]]+Append1[[#This Row],[DAY_TOT]]+Append1[[#This Row],[DAY_LTC]] -> 47242 | AT91: 7685 | AU91: 5105 | AV91: 3456 | AW91: 13451 | AX91: 0 | AY91: 0 | AZ91: 789 | BA91: 9797 | BB91: 240 | BC91: 1014 | BD91: 41537 | BE91: 134362091 | BF91: 150128349 | BG91: 89584477 | BH91: 130112260 | BI91: 0 | BJ91: 0 | BK91: 26250068 | BL91: 114524588 | BM91: 3892097 | BN91: 6256935 | BO91: 655110865 | BP91: 66077848 | BQ91: 46319958 | BR91: 24196881 | BS91: 72225378 | BT91: 0 | BU91: 0 | BV91: 9124704 | BW91: 67813556 | BX91: 2029935 | BY91: 5336467 | BZ91: 293124727 | CA91: 2307339 | CB91: 177245261 | CC91: 172468574 | CD91: 105456759 | CE91: 166321449 | CF91: 0 | CG91: 0 | CH91: 0 | CI91: 33430408 | CJ91: 133283496 | CK91: 0 | CL91: 5884178 | CM91: 0 | CN91: 0 | CO91: 0 | CP91: 9727058 | CQ91: 806124522 | CR91: 0 | CS91: 0 | CT91: 0 | CU91: 0 | CV91: 0 | CW91: 23194678 | CX91: 23979733 | CY91: 8324599 | CZ91: 36016189 | DA91: 0 | DB91: 0 | DC91: 1742153 | DD91: 48181841 | DE91: 37854 | DF91: 634023 | DG91: 142111070 | DH91: 188266 | DI91: 118131007 | DJ91: 0 | DK91: 171541 | DL91: 0 | DM91: 0 | DN91: 0 | DO91: 0 | DP91: 2619374 | DQ91: 91387561 | DR91: 0 | DS91: 0 | DT91: 0 | DU91: 0 | DV91: 0 | DW91: 0 | DX91: 0 | DY91: 0 | DZ91: 0 | EA91: 0 | EB91: 0 | EC91: 0 | ED91: 17360955
A92: 106364144 | B92: DESERT VALLEY HOSPITAL | C92: 20174 | D92: 43009 | E92: 43100 | F92: Open | G92: San Bernardino | H92: 12 | I92: 1211 | J92: Investor - Corp. | K92: Comparable | M92: 760-241-8000 | N92: 16850 BEAR VALLEY ROAD | O92: VICTORVILLE | P92: 92395 | Q92: FRED HUNTER | R92: 148 | S92: 148 | T92: 148 | U92: 730 | V92: 569 | W92: 150 | X92: 703 | Y92: 0 | Z92: 0 | AA92: 188 | AB92: 110 | AC92: 0 | AD92: 87 | AE92: 2537 | AF92: 0 | AG92: 3287 | AH92: 2046 | AI92: 751 | AJ92: 2733 | AK92: 0 | AL92: 0 | AM92: 837 | AN92: 280 | AO92: 0 | AP92: 128 | AQ92: 10062 | AR92: 0 | AS92: =Append1[[#This Row],[DAY_MCAR]]+Append1[[#This Row],[DAY_MCAR_MC]]+Append1[[#This Row],[DAY_MCAL]]+Append1[[#This Row],[DAY_MCAL_MC]]+Append1[[#This Row],[DAY_CNTY]]+Append1[[#This Row],[DAY_CNTY_MC]]+Append1[[#This Row],[DAY_THRD]]+Append1[[#This Row],[DAY_THRD_MC]]+Append1[[#This Row],[DAY_INDGNT]]+Append1[[#This Row],[DAY_OTH]]+Append1[[#This Row],[DAY_TOT]]+Append1[[#This Row],[DAY_LTC]] -> 20124 | AT92: 3192 | AU92: 1940 | AV92: 1014 | AW92: 5427 | AX92: 0 | AY92: 0 | AZ92: 1979 | BA92: 1105 | BB92: 0 | BC92: 2605 | BD92: 17262 | BE92: 52183711 | BF92: 34823597 | BG92: 10914764 | BH92: 38385026 | BI92: 0 | BJ92: 0 | BK92: 12424417 | BL92: 5790840 | BM92: 0 | BN92: 2117011 | BO92: 156639366 | BP92: 14372367 | BQ92: 10619434 | BR92: 4076085 | BS92: 23389966 | BT92: 0 | BU92: 0 | BV92: 6808290 | BW92: 5429035 | BX92: 0 | BY92: 3283444 | BZ92: 67978621 | CA92: 4915100 | CB92: 55681507 | CC92: 39184968 | CD92: 9486167 | CE92: 45349416 | CF92: -2532809 | CG92: 0 | CH92: 0 | CI92: 15000939 | CJ92: 7527988 | CK92: 0 | CL92: 332088 | CM92: 0 | CN92: 0 | CO92: 0 | CP92: 97095 | CQ92: 175042459 | CR92: 2109380 | CS92: 0 | CT92: 0 | CU92: 0 | CV92: 2109380 | CW92: 10874571 | CX92: 8367443 | CY92: 8037491 | CZ92: 16425576 | DA92: 0 | DB92: 0 | DC92: 4231768 | DD92: 3691887 | DE92: 0 | DF92: 56172 | DG92: 51684908 | DH92: 312804 | DI92: 37716394 | DJ92: 0 | DK92: -122130 | DL92: 0 | DM92: 0 | DN92: 0 | DO92: 0 | DP92: 466344 | DQ92: 78405096 | DR92: 0 | DS92: 22 | DT92: 67 | DU92: 175 | DV92: 1096303 | DW92: 672412 | DX92: 1610585 | DY92: 0 | DZ92: 0 | EA92: 158130 | EB92: 5743658 | EC92: 3026211 | ED92: 8552497
... A96: 106190243 | B96: DOWNEY REGIONAL MEDICAL CENTER | C96: 20174 | D96: 43009 | E96: 43100 | F96: Open | G96: Los Angeles | H96: 11 | I96: 921 | J96: Non Profit Corp. | K96: Comparable | M96: 562-904-5000 | N96: 11500 BROOKSHIRE AVENUE | O96: DOWNEY | P96: 90241 | Q96: RAMONA PRATT | R96: 199 | S96: 181 | T96: 79 | U96: 465 | V96: 518 | W96: 189 | X96: 312 | Y96: 0 | Z96: 0 | AA96: 9 | AB96: 332 | AC96: 20 | AD96: 28 | AE96: 1873 | AF96: 0 | AG96: 2444 | AH96: 1741 | AI96: 660 | AJ96: 1130 | AK96: 0 | AL96: 0 | AM96: 27 | AN96: 1128 | AO96: 45 | AP96: 54 | AQ96: 7229 | AR96: 0 | AS96: =Append1[[#This Row],[DAY_MCAR]]+Append1[[#This Row],[DAY_MCAR_MC]]+Append1[[#This Row],[DAY_MCAL]]+Append1[[#This Row],[DAY_MCAL_MC]]+Append1[[#This Row],[DAY_CNTY]]+Append1[[#This Row],[DAY_CNTY_MC]]+Append1[[#This Row],[DAY_THRD]]+Append1[[#This Row],[DAY_THRD_MC]]+Append1[[#This Row],[DAY_INDGNT]]+Append1[[#This Row],[DAY_OTH]]+Append1[[#This Row],[DAY_TOT]]+Append1[[#This Row],[DAY_LTC]] -> 14458 | AT96: 3013 | AU96: 2891 | AV96: 1574 | AW96: 6270 | AX96: 0 | AY96: 0 | AZ96: 480 | BA96: 5495 | BB96: 96 | BC96: 982 | BD96: 20801 | BE96: 33962126 | BF96: 36784883 | BG96: 14678089 | BH96: 19440696 | BI96: 0 | BJ96: 0 | BK96: 499626 | BL96: 21123468 | BM96: 166069 | BN96: 2393040 | BO96: 129047997 | BP96: 13379111 | BQ96: 24215728 | BR96: 9607116 | BS96: 31768049 | BT96: 0 | BU96: 0 | BV96: 1522433 | BW96: 26799407 | BX96: 127025 | BY96: 6143329 | BZ96: 113562198 | CA96: 856403 | CB96: 42343242 | CC96: 54065883 | CD96: 19778132 | CE96: 45828959 | CF96: 0 | CG96: 0 | CH96: 0 | CI96: 1668390 | CJ96: 35456896 | CK96: 0 | CL96: 293094 | CM96: 0 | CN96: 0 | CO96: 0 | CP96: 4852889 | CQ96: 205143888 | CR96: 0 | CS96: 0 | CT96: 0 | CU96: 0 | CV96: 0 | CW96: 4997995 | CX96: 6934727 | CY96: 4507072 | CZ96: 5379786 | DA96: 0 | DB96: 0 | DC96: 353669 | DD96: 12465979 | DE96: 0 | DF96: 2827079 | DG96: 37466307 | DH96: 599239 | DI96: 40185093 | DJ96: 0 | DK96: 0 | DL96: 0 | DM96: 0 | DN96: 0 | DO96: 0 | DP96: 3654436 | DQ96: 108599809 | DR96: 0 | DS96: 0 | DT96: 0 | DU96: 0 | DV96: 0 | DW96: 0 | DX96: 0 | DY96: 0 | DZ96: 0 | EA96: 0 | EB96: 0 | EC96: 0 | ED96: 0
A97: 106196168 | B97: EARL AND LORRAINE MILLER CHILDRENS HOSPITAL | C97: 20174 | D97: 43009 | E97: 43100 | F97: Open | G97: Los Angeles | H97: 11 | I97: 933 | J97: Non Profit Corp. | K97: Comparable | L97: Teaching | M97: 562-933-5437 | N97: 2801 ATLANTIC AVENUE | O97: LONG BEACH | P97: 90806 | Q97: JOHN BISHOP | R97: 369 | S97: 364 | T97: 212 | U97: 8 | V97: 0 | W97: 1081 | X97: 1492 | Y97: 0 | Z97: 0 | AA97: 43 | AB97: 1213 | AC97: 10 | AD97: 55 | AE97: 3902 | AF97: 0 | AG97: 34 | AH97: 0 | AI97: 7025 | AJ97: 4405 | AK97: 0 | AL97: 0 | AM97: 184 | AN97: 5663 | AO97: 24 | AP97: 357 | AQ97: 17692 | AR97: 0 | AS97: =Append1[[#This Row],[DAY_MCAR]]+Append1[[#This Row],[DAY_MCAR_MC]]+Append1[[#This Row],[DAY_MCAL]]+Append1[[#This Row],[DAY_MCAL_MC]]+Append1[[#This Row],[DAY_CNTY]]+Append1[[#This Row],[DAY_CNTY_MC]]+Append1[[#This Row],[DAY_THRD]]+Append1[[#This Row],[DAY_THRD_MC]]+Append1[[#This Row],[DAY_INDGNT]]+Append1[[#This Row],[DAY_OTH]]+Append1[[#This Row],[DAY_TOT]]+Append1[[#This Row],[DAY_LTC]] -> 35384 | AT97: 10 | AU97: 3 | AV97: 9214 | AW97: 9420 | AX97: 0 | AY97: 0 | AZ97: 127 | BA97: 5674 | BB97: 12 | BC97: 286 | BD97: 24746 | BE97: 525948 | BF97: 0 | BG97: 96269299 | BH97: 47195787 | BI97: 0 | BJ97: 0 | BK97: 2426361 | BL97: 69225436 | BM97: 295855 | BN97: 4878345 | BO97: 220817031 | BP97: 10919 | BQ97: 4020 | BR97: 13838339 | BS97: 10363274 | BT97: 0 | BU97: 0 | BV97: 323278 | BW97: 11868688 | BX97: 32456 | BY97: 843017 | BZ97: 37283991 | CA97: 1925930 | CB97: 468250 | CC97: 2990 | CD97: 31445210 | CE97: 47905207 | CF97: -3000000 | CG97: 0 | CH97: 0 | CI97: 2066894 | CJ97: 40013447 | CK97: 0 | CL97: 467800 | CM97: 0 | CN97: 0 | CO97: 0 | CP97: 3661280 | CQ97: 124957008 | CR97: 0 | CS97: 1892723 | CT97: 0 | CU97: 0 | CV97: 1892723 | CW97: 67424 | CX97: 1021 | CY97: 81660654 | CZ97: 11418680 | DA97: 0 | DB97: 0 | DC97: 676529 | DD97: 40754112 | DE97: 8786 | DF97: 449531 | DG97: 135036737 | DH97: 1539756 | DI97: 126863155 | DJ97: 0 | DK97: 1846423 | DL97: 0 | DM97: 0 | DN97: 0 | DO97: 0 | DP97: 5842093 | DQ97: 238742288 | DR97: 0 | DS97: 0 | DT97: 0 | DU97: 0 | DV97: 0 | DW97: 0 | DX97: 0 | DY97: 0 | DZ97: 0 | EA97: 0 | EB97: 0 | EC97: 0 | ED97: 0
